{"localisation": [{"sublocalisations": {"localisation": [{"tcin": "00:02:02.16", "tcout": "00:02:03.72", "tclevel": 1}, {"tcin": "00:02:13.8", "tcout": "00:02:18.08", "tclevel": 1}, {"tcin": "00:16:14.36", "tcout": "00:16:33.68", "tclevel": 1}, {"tcin": "00:01:27.16", "tcout": "00:01:29.68", "tclevel": 1}, {"tcin": "00:02:09.52", "tcout": "00:02:10.96", "tclevel": 1}, {"tcin": "00:23:22.0", "tcout": "00:23:31.08", "tclevel": 1}, {"tcin": "00:01:55.52", "tcout": "00:01:59.64", "tclevel": 1}, {"tcin": "00:23:20.68", "tcout": "00:23:21.96", "tclevel": 1}, {"tcin": "00:02:20.52", "tcout": "00:02:24.4", "tclevel": 1}, {"tcin": "00:23:42.6", "tcout": "00:23:48.6", "tclevel": 1}]}, "type": "keyframes", "tcin": "00:00:00.0000", "tcout": "00:00:15.0000", "tclevel": 0}], "id": "mo", "type": "segments", "algorithm": "demo-video-generator", "processor": "", "processed": 1421141589291, "version": 1}