{"localisation": [{"sublocalisations": {"localisation": [{"tcin": "00:00:19.0000", "tcout": "00:00:23.0000", "tclevel": 1}, {"tcin": "00:00:31.0000", "tcout": "00:00:35.0000", "tclevel": 1}, {"tcin": "00:01:22.0000", "tcout": "00:01:26.0000", "tclevel": 1}, {"tcin": "00:01:50.0000", "tcout": "00:01:57.0000", "tclevel": 1}, {"tcin": "00:03:06.0000", "tcout": "00:03:10.0000", "tclevel": 1}, {"tcin": "00:03:47.0000", "tcout": "00:03:51.0000", "tclevel": 1}, {"tcin": "00:03:54.0000", "tcout": "00:04:01.0000", "tclevel": 1}, {"tcin": "00:04:09.0000", "tcout": "00:04:13.0000", "tclevel": 1}, {"tcin": "00:04:30.0000", "tcout": "00:04:34.0000", "tclevel": 1}, {"tcin": "00:05:00.0000", "tcout": "00:05:04.0000", "tclevel": 1}, {"tcin": "00:05:28.0000", "tcout": "00:05:32.0000", "tclevel": 1}, {"tcin": "00:05:43.0000", "tcout": "00:05:47.0000", "tclevel": 1}, {"tcin": "00:06:02.0000", "tcout": "00:06:08.0000", "tclevel": 1}, {"tcin": "00:07:05.0000", "tcout": "00:07:09.0000", "tclevel": 1}, {"tcin": "00:07:38.0000", "tcout": "00:07:42.0000", "tclevel": 1}, {"tcin": "00:08:53.0000", "tcout": "00:08:57.0000", "tclevel": 1}, {"tcin": "00:09:10.0000", "tcout": "00:09:14.0000", "tclevel": 1}, {"tcin": "00:09:18.0000", "tcout": "00:09:22.0000", "tclevel": 1}, {"tcin": "00:09:32.0000", "tcout": "00:09:36.0000", "tclevel": 1}, {"tcin": "00:09:49.0000", "tcout": "00:09:53.0000", "tclevel": 1}, {"tcin": "00:10:06.0000", "tcout": "00:10:13.0000", "tclevel": 1}, {"tcin": "00:10:23.0000", "tcout": "00:10:27.0000", "tclevel": 1}, {"tcin": "00:10:41.0000", "tcout": "00:10:45.0000", "tclevel": 1}, {"tcin": "00:10:52.0000", "tcout": "00:10:56.0000", "tclevel": 1}, {"tcin": "00:11:32.0000", "tcout": "00:11:36.0000", "tclevel": 1}, {"tcin": "00:11:38.0000", "tcout": "00:11:42.0000", "tclevel": 1}, {"tcin": "00:12:08.0000", "tcout": "00:12:12.0000", "tclevel": 1}, {"tcin": "00:12:23.0000", "tcout": "00:12:27.0000", "tclevel": 1}, {"tcin": "00:12:58.0000", "tcout": "00:13:03.0000", "tclevel": 1}, {"tcin": "00:13:45.0000", "tcout": "00:13:49.0000", "tclevel": 1}, {"tcin": "00:13:51.0000", "tcout": "00:13:55.0000", "tclevel": 1}, {"tcin": "00:14:25.0000", "tcout": "00:14:29.0000", "tclevel": 1}, {"tcin": "00:15:09.0000", "tcout": "00:15:13.0000", "tclevel": 1}, {"tcin": "00:15:41.0000", "tcout": "00:15:45.0000", "tclevel": 1}, {"tcin": "00:15:46.0000", "tcout": "00:15:50.0000", "tclevel": 1}, {"tcin": "00:15:52.0000", "tcout": "00:15:56.0000", "tclevel": 1}, {"tcin": "00:16:35.0000", "tcout": "00:16:39.0000", "tclevel": 1}, {"tcin": "00:17:52.0000", "tcout": "00:17:56.0000", "tclevel": 1}, {"tcin": "00:19:09.0000", "tcout": "00:19:15.0000", "tclevel": 1}, {"tcin": "00:19:59.0000", "tcout": "00:20:03.0000", "tclevel": 1}, {"tcin": "00:20:07.0000", "tcout": "00:20:11.0000", "tclevel": 1}, {"tcin": "00:20:34.0000", "tcout": "00:20:38.0000", "tclevel": 1}, {"tcin": "00:20:43.0000", "tcout": "00:20:47.0000", "tclevel": 1}, {"tcin": "00:20:49.0000", "tcout": "00:20:53.0000", "tclevel": 1}, {"tcin": "00:21:45.0000", "tcout": "00:21:49.0000", "tclevel": 1}, {"tcin": "00:22:26.0000", "tcout": "00:22:30.0000", "tclevel": 1}, {"tcin": "00:23:01.0000", "tcout": "00:23:05.0000", "tclevel": 1}, {"tcin": "00:23:50.0000", "tcout": "00:23:54.0000", "tclevel": 1}, {"tcin": "00:24:31.0000", "tcout": "00:24:35.0000", "tclevel": 1}, {"tcin": "00:24:43.0000", "tcout": "00:24:47.0000", "tclevel": 1}, {"tcin": "00:25:34.0000", "tcout": "00:25:38.0000", "tclevel": 1}, {"tcin": "00:25:49.0000", "tcout": "00:25:54.0000", "tclevel": 1}, {"tcin": "00:26:07.0000", "tcout": "00:26:11.0000", "tclevel": 1}, {"tcin": "00:26:33.0000", "tcout": "00:26:37.0000", "tclevel": 1}, {"tcin": "00:27:25.0000", "tcout": "00:27:31.0000", "tclevel": 1}, {"tcin": "00:27:56.0000", "tcout": "00:28:00.0000", "tclevel": 1}, {"tcin": "00:29:11.0000", "tcout": "00:29:15.0000", "tclevel": 1}, {"tcin": "00:29:33.0000", "tcout": "00:29:39.0000", "tclevel": 1}, {"tcin": "00:30:13.0000", "tcout": "00:30:17.0000", "tclevel": 1}, {"tcin": "00:30:41.0000", "tcout": "00:30:45.0000", "tclevel": 1}, {"tcin": "00:32:03.0000", "tcout": "00:32:11.0000", "tclevel": 1}, {"tcin": "00:32:13.0000", "tcout": "00:32:17.0000", "tclevel": 1}, {"tcin": "00:32:25.0000", "tcout": "00:32:32.0000", "tclevel": 1}, {"tcin": "00:32:50.0000", "tcout": "00:32:57.0000", "tclevel": 1}, {"tcin": "00:32:59.0000", "tcout": "00:33:04.0000", "tclevel": 1}, {"tcin": "00:33:05.0000", "tcout": "00:33:09.0000", "tclevel": 1}, {"tcin": "00:33:19.0000", "tcout": "00:33:23.0000", "tclevel": 1}, {"tcin": "00:33:38.0000", "tcout": "00:33:42.0000", "tclevel": 1}, {"tcin": "00:33:45.0000", "tcout": "00:33:49.0000", "tclevel": 1}, {"tcin": "00:33:51.0000", "tcout": "00:33:55.0000", "tclevel": 1}, {"tcin": "00:33:56.0000", "tcout": "00:34:00.0000", "tclevel": 1}, {"tcin": "00:34:03.0000", "tcout": "00:34:07.0000", "tclevel": 1}, {"tcin": "00:34:10.0000", "tcout": "00:34:14.0000", "tclevel": 1}, {"tcin": "00:34:21.0000", "tcout": "00:34:25.0000", "tclevel": 1}, {"tcin": "00:34:57.0000", "tcout": "00:35:01.0000", "tclevel": 1}, {"tcin": "00:36:00.0000", "tcout": "00:36:04.0000", "tclevel": 1}, {"tcin": "00:36:45.0000", "tcout": "00:36:49.0000", "tclevel": 1}, {"tcin": "00:38:19.0000", "tcout": "00:38:23.0000", "tclevel": 1}, {"tcin": "00:38:30.0000", "tcout": "00:38:34.0000", "tclevel": 1}, {"tcin": "00:38:50.0000", "tcout": "00:38:54.0000", "tclevel": 1}, {"tcin": "00:39:40.0000", "tcout": "00:39:45.0000", "tclevel": 1}, {"tcin": "00:39:59.0000", "tcout": "00:40:03.0000", "tclevel": 1}, {"tcin": "00:40:23.0000", "tcout": "00:40:30.0000", "tclevel": 1}, {"tcin": "00:41:04.0000", "tcout": "00:41:08.0000", "tclevel": 1}, {"tcin": "00:41:15.0000", "tcout": "00:41:19.0000", "tclevel": 1}, {"tcin": "00:41:21.0000", "tcout": "00:41:25.0000", "tclevel": 1}, {"tcin": "00:42:28.0000", "tcout": "00:42:32.0000", "tclevel": 1}, {"tcin": "00:43:09.0000", "tcout": "00:43:13.0000", "tclevel": 1}, {"tcin": "00:43:33.0000", "tcout": "00:43:37.0000", "tclevel": 1}, {"tcin": "00:43:54.0000", "tcout": "00:43:58.0000", "tclevel": 1}, {"tcin": "00:44:37.0000", "tcout": "00:44:41.0000", "tclevel": 1}, {"tcin": "00:44:54.0000", "tcout": "00:44:58.0000", "tclevel": 1}, {"tcin": "00:45:02.0000", "tcout": "00:45:06.0000", "tclevel": 1}, {"tcin": "00:45:21.0000", "tcout": "00:45:25.0000", "tclevel": 1}, {"tcin": "00:45:41.0000", "tcout": "00:45:45.0000", "tclevel": 1}, {"tcin": "00:47:23.0000", "tcout": "00:47:27.0000", "tclevel": 1}, {"tcin": "00:47:33.0000", "tcout": "00:47:39.0000", "tclevel": 1}, {"tcin": "00:48:28.0000", "tcout": "00:48:32.0000", "tclevel": 1}, {"tcin": "00:48:45.0000", "tcout": "00:48:49.0000", "tclevel": 1}, {"tcin": "00:48:54.0000", "tcout": "00:48:58.0000", "tclevel": 1}, {"tcin": "00:49:15.0000", "tcout": "00:49:19.0000", "tclevel": 1}, {"tcin": "00:49:45.0000", "tcout": "00:49:49.0000", "tclevel": 1}, {"tcin": "00:51:12.0000", "tcout": "00:51:16.0000", "tclevel": 1}, {"tcin": "00:51:32.0000", "tcout": "00:51:36.0000", "tclevel": 1}, {"tcin": "00:52:15.0000", "tcout": "00:52:19.0000", "tclevel": 1}, {"tcin": "00:52:24.0000", "tcout": "00:52:30.0000", "tclevel": 1}, {"tcin": "00:52:36.0000", "tcout": "00:52:40.0000", "tclevel": 1}, {"tcin": "00:53:03.0000", "tcout": "00:53:07.0000", "tclevel": 1}, {"tcin": "00:53:42.0000", "tcout": "00:53:51.0000", "tclevel": 1}, {"tcin": "00:53:55.0000", "tcout": "00:53:59.0000", "tclevel": 1}, {"tcin": "00:54:19.0000", "tcout": "00:54:23.0000", "tclevel": 1}, {"tcin": "00:55:54.0000", "tcout": "00:55:58.0000", "tclevel": 1}, {"tcin": "00:57:05.0000", "tcout": "00:57:09.0000", "tclevel": 1}, {"tcin": "00:57:21.0000", "tcout": "00:57:25.0000", "tclevel": 1}, {"tcin": "00:58:06.0000", "tcout": "00:58:10.0000", "tclevel": 1}, {"tcin": "00:58:29.0000", "tcout": "00:58:33.0000", "tclevel": 1}, {"tcin": "00:58:54.0000", "tcout": "00:58:58.0000", "tclevel": 1}, {"tcin": "00:59:03.0000", "tcout": "00:59:07.0000", "tclevel": 1}, {"tcin": "00:59:20.0000", "tcout": "00:59:35.0000", "tclevel": 1}, {"tcin": "00:59:38.0000", "tcout": "00:59:47.0000", "tclevel": 1}, {"tcin": "01:00:20.0000", "tcout": "01:00:24.0000", "tclevel": 1}, {"tcin": "01:00:42.0000", "tcout": "01:00:54.0000", "tclevel": 1}, {"tcin": "01:02:00.0000", "tcout": "01:02:04.0000", "tclevel": 1}, {"tcin": "01:02:13.0000", "tcout": "01:02:21.0000", "tclevel": 1}, {"tcin": "01:03:04.0000", "tcout": "01:03:08.0000", "tclevel": 1}, {"tcin": "01:03:09.0000", "tcout": "01:03:13.0000", "tclevel": 1}, {"tcin": "01:04:59.0000", "tcout": "01:05:03.0000", "tclevel": 1}, {"tcin": "01:05:23.0000", "tcout": "01:05:30.0000", "tclevel": 1}, {"tcin": "01:06:07.0000", "tcout": "01:06:11.0000", "tclevel": 1}, {"tcin": "01:06:36.0000", "tcout": "01:06:47.0000", "tclevel": 1}, {"tcin": "01:06:48.0000", "tcout": "01:06:52.0000", "tclevel": 1}, {"tcin": "01:07:17.0000", "tcout": "01:07:21.0000", "tclevel": 1}, {"tcin": "01:07:57.0000", "tcout": "01:08:01.0000", "tclevel": 1}, {"tcin": "01:08:48.0000", "tcout": "01:08:52.0000", "tclevel": 1}, {"tcin": "01:09:10.0000", "tcout": "01:09:14.0000", "tclevel": 1}, {"tcin": "01:10:36.0000", "tcout": "01:10:43.0000", "tclevel": 1}, {"tcin": "01:11:03.0000", "tcout": "01:11:09.0000", "tclevel": 1}, {"tcin": "01:11:17.0000", "tcout": "01:11:21.0000", "tclevel": 1}, {"tcin": "01:12:50.0000", "tcout": "01:12:58.0000", "tclevel": 1}, {"tcin": "01:13:12.0000", "tcout": "01:13:16.0000", "tclevel": 1}, {"tcin": "01:13:24.0000", "tcout": "01:13:28.0000", "tclevel": 1}, {"tcin": "01:13:33.0000", "tcout": "01:13:37.0000", "tclevel": 1}, {"tcin": "01:14:32.0000", "tcout": "01:14:36.0000", "tclevel": 1}, {"tcin": "01:15:02.0000", "tcout": "01:15:06.0000", "tclevel": 1}, {"tcin": "01:16:28.0000", "tcout": "01:16:32.0000", "tclevel": 1}, {"tcin": "01:16:43.0000", "tcout": "01:16:50.0000", "tclevel": 1}, {"tcin": "01:17:09.0000", "tcout": "01:17:13.0000", "tclevel": 1}, {"tcin": "01:17:30.0000", "tcout": "01:17:34.0000", "tclevel": 1}, {"tcin": "01:17:54.0000", "tcout": "01:18:01.0000", "tclevel": 1}, {"tcin": "01:19:48.0000", "tcout": "01:19:52.0000", "tclevel": 1}, {"tcin": "01:20:11.0000", "tcout": "01:20:15.0000", "tclevel": 1}, {"tcin": "01:20:29.0000", "tcout": "01:20:33.0000", "tclevel": 1}, {"tcin": "01:21:01.0000", "tcout": "01:21:05.0000", "tclevel": 1}, {"tcin": "01:21:15.0000", "tcout": "01:21:19.0000", "tclevel": 1}, {"tcin": "01:21:33.0000", "tcout": "01:21:37.0000", "tclevel": 1}, {"tcin": "01:22:03.0000", "tcout": "01:22:07.0000", "tclevel": 1}, {"tcin": "01:22:11.0000", "tcout": "01:22:15.0000", "tclevel": 1}, {"tcin": "01:22:19.0000", "tcout": "01:22:23.0000", "tclevel": 1}, {"tcin": "01:22:28.0000", "tcout": "01:22:32.0000", "tclevel": 1}, {"tcin": "01:22:44.0000", "tcout": "01:22:48.0000", "tclevel": 1}, {"tcin": "01:22:50.0000", "tcout": "01:22:54.0000", "tclevel": 1}, {"tcin": "01:22:57.0000", "tcout": "01:23:01.0000", "tclevel": 1}, {"tcin": "01:24:24.0000", "tcout": "01:24:28.0000", "tclevel": 1}, {"tcin": "01:25:24.0000", "tcout": "01:25:28.0000", "tclevel": 1}, {"tcin": "01:25:31.0000", "tcout": "01:25:35.0000", "tclevel": 1}, {"tcin": "01:25:45.0000", "tcout": "01:25:49.0000", "tclevel": 1}, {"tcin": "01:26:28.0000", "tcout": "01:26:36.0000", "tclevel": 1}, {"tcin": "01:27:06.0000", "tcout": "01:27:10.0000", "tclevel": 1}, {"tcin": "01:27:55.0000", "tcout": "01:28:01.0000", "tclevel": 1}, {"tcin": "01:28:39.0000", "tcout": "01:28:44.0000", "tclevel": 1}, {"tcin": "01:29:10.0000", "tcout": "01:29:14.0000", "tclevel": 1}, {"tcin": "01:29:41.0000", "tcout": "01:29:45.0000", "tclevel": 1}, {"tcin": "01:30:08.0000", "tcout": "01:30:12.0000", "tclevel": 1}, {"tcin": "01:30:27.0000", "tcout": "01:30:31.0000", "tclevel": 1}, {"tcin": "01:31:17.0000", "tcout": "01:31:22.0000", "tclevel": 1}, {"tcin": "01:33:13.0000", "tcout": "01:33:17.0000", "tclevel": 1}, {"tcin": "01:33:34.0000", "tcout": "01:33:38.0000", "tclevel": 1}, {"tcin": "01:33:51.0000", "tcout": "01:33:55.0000", "tclevel": 1}, {"tcin": "01:34:22.0000", "tcout": "01:34:26.0000", "tclevel": 1}, {"tcin": "01:35:39.0000", "tcout": "01:35:43.0000", "tclevel": 1}, {"tcin": "01:35:49.0000", "tcout": "01:35:53.0000", "tclevel": 1}, {"tcin": "01:36:14.0000", "tcout": "01:36:18.0000", "tclevel": 1}, {"tcin": "01:36:23.0000", "tcout": "01:36:27.0000", "tclevel": 1}, {"tcin": "01:36:49.0000", "tcout": "01:36:53.0000", "tclevel": 1}, {"tcin": "01:36:54.0000", "tcout": "01:36:58.0000", "tclevel": 1}, {"tcin": "01:38:03.0000", "tcout": "01:38:07.0000", "tclevel": 1}, {"tcin": "01:38:27.0000", "tcout": "01:38:31.0000", "tclevel": 1}, {"tcin": "01:39:09.0000", "tcout": "01:39:13.0000", "tclevel": 1}, {"tcin": "01:39:18.0000", "tcout": "01:39:22.0000", "tclevel": 1}, {"tcin": "01:39:29.0000", "tcout": "01:39:33.0000", "tclevel": 1}, {"tcin": "01:39:46.0000", "tcout": "01:39:50.0000", "tclevel": 1}, {"tcin": "01:41:26.0000", "tcout": "01:41:33.0000", "tclevel": 1}, {"tcin": "01:41:40.0000", "tcout": "01:41:44.0000", "tclevel": 1}, {"tcin": "01:41:47.0000", "tcout": "01:41:51.0000", "tclevel": 1}, {"tcin": "01:42:07.0000", "tcout": "01:42:11.0000", "tclevel": 1}, {"tcin": "01:42:42.0000", "tcout": "01:42:46.0000", "tclevel": 1}, {"tcin": "01:42:59.0000", "tcout": "01:43:03.0000", "tclevel": 1}, {"tcin": "01:43:52.0000", "tcout": "01:43:56.0000", "tclevel": 1}, {"tcin": "01:44:13.0000", "tcout": "01:44:17.0000", "tclevel": 1}, {"tcin": "01:44:39.0000", "tcout": "01:44:43.0000", "tclevel": 1}, {"tcin": "01:46:25.0000", "tcout": "01:46:29.0000", "tclevel": 1}, {"tcin": "01:46:34.0000", "tcout": "01:46:38.0000", "tclevel": 1}, {"tcin": "01:46:39.0000", "tcout": "01:46:43.0000", "tclevel": 1}, {"tcin": "01:47:15.0000", "tcout": "01:47:19.0000", "tclevel": 1}, {"tcin": "01:49:07.0000", "tcout": "01:49:13.0000", "tclevel": 1}, {"tcin": "01:49:21.0000", "tcout": "01:49:25.0000", "tclevel": 1}, {"tcin": "01:49:42.0000", "tcout": "01:49:46.0000", "tclevel": 1}, {"tcin": "01:49:59.0000", "tcout": "01:50:06.0000", "tclevel": 1}, {"tcin": "01:50:27.0000", "tcout": "01:50:31.0000", "tclevel": 1}, {"tcin": "01:51:44.0000", "tcout": "01:51:48.0000", "tclevel": 1}, {"tcin": "01:53:54.0000", "tcout": "01:53:58.0000", "tclevel": 1}, {"tcin": "01:54:02.0000", "tcout": "01:54:06.0000", "tclevel": 1}, {"tcin": "01:54:28.0000", "tcout": "01:54:32.0000", "tclevel": 1}, {"tcin": "01:54:58.0000", "tcout": "01:55:02.0000", "tclevel": 1}, {"tcin": "01:55:09.0000", "tcout": "01:55:13.0000", "tclevel": 1}, {"tcin": "01:55:14.0000", "tcout": "01:55:18.0000", "tclevel": 1}, {"tcin": "01:55:29.0000", "tcout": "01:55:36.0000", "tclevel": 1}, {"tcin": "01:55:55.0000", "tcout": "01:55:59.0000", "tclevel": 1}, {"tcin": "01:57:05.0000", "tcout": "01:57:09.0000", "tclevel": 1}]}, "type": "keyframes", "tcin": "00:00:00.0000", "tcout": "00:00:15.0000", "tclevel": 219}], "id": "event_seg_vsum_dsf_fix", "type": "segments", "algorithm": "demo-video-generator", "processor": "mmlab", "processed": "1421141589291", "version": "1"}