{"localisation": [{"sublocalisations": {"localisation": [{"label": "1.291", "tc": "00:00:00.0000", "tclevel": 1}, {"label": "2.713", "tc": "00:00:00.1668", "tclevel": 1}, {"label": "3.533", "tc": "00:00:00.3337", "tclevel": 1}, {"label": "0.489", "tc": "00:00:00.5005", "tclevel": 1}, {"label": "3.584", "tc": "00:00:00.6673", "tclevel": 1}, {"label": "3.919", "tc": "00:00:00.8342", "tclevel": 1}, {"label": "1.975", "tc": "00:00:01.0010", "tclevel": 1}, {"label": "1.56", "tc": "00:00:01.1679", "tclevel": 1}, {"label": "4.977", "tc": "00:00:01.3347", "tclevel": 1}, {"label": "3.452", "tc": "00:00:01.5015", "tclevel": 1}, {"label": "1.328", "tc": "00:00:01.6684", "tclevel": 1}, {"label": "4.116", "tc": "00:00:01.8352", "tclevel": 1}, {"label": "0.997", "tc": "00:00:02.0020", "tclevel": 1}, {"label": "1.459", "tc": "00:00:02.1689", "tclevel": 1}, {"label": "2.666", "tc": "00:00:02.3357", "tclevel": 1}, {"label": "3.937", "tc": "00:00:02.5026", "tclevel": 1}, {"label": "3.104", "tc": "00:00:02.6694", "tclevel": 1}, {"label": "3.398", "tc": "00:00:02.8362", "tclevel": 1}, {"label": "3.064", "tc": "00:00:03.0031", "tclevel": 1}, {"label": "3.809", "tc": "00:00:03.1699", "tclevel": 1}, {"label": "0.225", "tc": "00:00:03.3367", "tclevel": 1}, {"label": "4.745", "tc": "00:00:03.5036", "tclevel": 1}, {"label": "1.407", "tc": "00:00:03.6704", "tclevel": 1}, {"label": "4.082", "tc": "00:00:03.8373", "tclevel": 1}, {"label": "0.585", "tc": "00:00:04.0041", "tclevel": 1}, {"label": "2.877", "tc": "00:00:04.1709", "tclevel": 1}, {"label": "3.923", "tc": "00:00:04.3378", "tclevel": 1}, {"label": "1.134", "tc": "00:00:04.5046", "tclevel": 1}, {"label": "1.651", "tc": "00:00:04.6714", "tclevel": 1}, {"label": "4.688", "tc": "00:00:04.8383", "tclevel": 1}, {"label": "4.393", "tc": "00:00:05.0051", "tclevel": 1}, {"label": "0.421", "tc": "00:00:05.1719", "tclevel": 1}, {"label": "0.564", "tc": "00:00:05.3388", "tclevel": 1}, {"label": "3.494", "tc": "00:00:05.5056", "tclevel": 1}, {"label": "3.458", "tc": "00:00:05.6725", "tclevel": 1}, {"label": "3.748", "tc": "00:00:05.8393", "tclevel": 1}, {"label": "1.244", "tc": "00:00:06.0061", "tclevel": 1}, {"label": "1.76", "tc": "00:00:06.1730", "tclevel": 1}, {"label": "3.041", "tc": "00:00:06.3398", "tclevel": 1}, {"label": "4.891", "tc": "00:00:06.5066", "tclevel": 1}, {"label": "1.207", "tc": "00:00:06.6735", "tclevel": 1}, {"label": "2.352", "tc": "00:00:06.8403", "tclevel": 1}, {"label": "0.103", "tc": "00:00:07.0072", "tclevel": 1}, {"label": "3.178", "tc": "00:00:07.1740", "tclevel": 1}, {"label": "1.151", "tc": "00:00:07.3408", "tclevel": 1}, {"label": "3.772", "tc": "00:00:07.5077", "tclevel": 1}, {"label": "4.065", "tc": "00:00:07.6745", "tclevel": 1}, {"label": "4.935", "tc": "00:00:07.8413", "tclevel": 1}, {"label": "3.599", "tc": "00:00:08.0082", "tclevel": 1}, {"label": "0.162", "tc": "00:00:08.1750", "tclevel": 1}, {"label": "3.975", "tc": "00:00:08.3418", "tclevel": 1}, {"label": "0.25", "tc": "00:00:08.5087", "tclevel": 1}, {"label": "4.511", "tc": "00:00:08.6755", "tclevel": 1}, {"label": "2.9", "tc": "00:00:08.8424", "tclevel": 1}, {"label": "1.669", "tc": "00:00:09.0092", "tclevel": 1}, {"label": "2.615", "tc": "00:00:09.1760", "tclevel": 1}, {"label": "3.221", "tc": "00:00:09.3429", "tclevel": 1}, {"label": "4.788", "tc": "00:00:09.5097", "tclevel": 1}, {"label": "1.463", "tc": "00:00:09.6765", "tclevel": 1}, {"label": "2.018", "tc": "00:00:09.8434", "tclevel": 1}, {"label": "3.033", "tc": "00:00:10.0102", "tclevel": 1}, {"label": "2.582", "tc": "00:00:10.1771", "tclevel": 1}, {"label": "4.022", "tc": "00:00:10.3439", "tclevel": 1}, {"label": "4.138", "tc": "00:00:10.5107", "tclevel": 1}, {"label": "3.614", "tc": "00:00:10.6776", "tclevel": 1}, {"label": "4.179", "tc": "00:00:10.8444", "tclevel": 1}, {"label": "1.857", "tc": "00:00:11.0112", "tclevel": 1}, {"label": "0.175", "tc": "00:00:11.1781", "tclevel": 1}, {"label": "0.917", "tc": "00:00:11.3449", "tclevel": 1}, {"label": "0.758", "tc": "00:00:11.5118", "tclevel": 1}, {"label": "3.511", "tc": "00:00:11.6786", "tclevel": 1}, {"label": "4.853", "tc": "00:00:11.8454", "tclevel": 1}, {"label": "1.887", "tc": "00:00:12.0123", "tclevel": 1}, {"label": "3.063", "tc": "00:00:12.1791", "tclevel": 1}, {"label": "3.046", "tc": "00:00:12.3459", "tclevel": 1}, {"label": "1.6", "tc": "00:00:12.5128", "tclevel": 1}, {"label": "2.448", "tc": "00:00:12.6796", "tclevel": 1}, {"label": "1.669", "tc": "00:00:12.8464", "tclevel": 1}, {"label": "4.567", "tc": "00:00:13.0133", "tclevel": 1}, {"label": "1.032", "tc": "00:00:13.1801", "tclevel": 1}, {"label": "1.006", "tc": "00:00:13.3470", "tclevel": 1}, {"label": "2.706", "tc": "00:00:13.5138", "tclevel": 1}, {"label": "3.48", "tc": "00:00:13.6806", "tclevel": 1}, {"label": "3.839", "tc": "00:00:13.8475", "tclevel": 1}, {"label": "2.118", "tc": "00:00:14.0143", "tclevel": 1}, {"label": "2.69", "tc": "00:00:14.1811", "tclevel": 1}, {"label": "3.994", "tc": "00:00:14.3480", "tclevel": 1}, {"label": "1.945", "tc": "00:00:14.5148", "tclevel": 1}, {"label": "1.333", "tc": "00:00:14.6817", "tclevel": 1}, {"label": "4.061", "tc": "00:00:14.8485", "tclevel": 1}, {"label": "4.589", "tc": "00:00:15.0153", "tclevel": 1}, {"label": "2.291", "tc": "00:00:15.1822", "tclevel": 1}, {"label": "1.473", "tc": "00:00:15.3490", "tclevel": 1}, {"label": "2.786", "tc": "00:00:15.5158", "tclevel": 1}, {"label": "3.04", "tc": "00:00:15.6827", "tclevel": 1}, {"label": "4.809", "tc": "00:00:15.8495", "tclevel": 1}, {"label": "4.542", "tc": "00:00:16.0164", "tclevel": 1}, {"label": "1.275", "tc": "00:00:16.1832", "tclevel": 1}, {"label": "3.895", "tc": "00:00:16.3500", "tclevel": 1}, {"label": "0.182", "tc": "00:00:16.5169", "tclevel": 1}, {"label": "0.638", "tc": "00:00:16.6837", "tclevel": 1}, {"label": "4.763", "tc": "00:00:16.8505", "tclevel": 1}, {"label": "2.947", "tc": "00:00:17.0174", "tclevel": 1}, {"label": "1.728", "tc": "00:00:17.1842", "tclevel": 1}, {"label": "3.131", "tc": "00:00:17.3510", "tclevel": 1}, {"label": "4.648", "tc": "00:00:17.5179", "tclevel": 1}, {"label": "4.017", "tc": "00:00:17.6847", "tclevel": 1}, {"label": "2.053", "tc": "00:00:17.8516", "tclevel": 1}, {"label": "3.422", "tc": "00:00:18.0184", "tclevel": 1}, {"label": "0.266", "tc": "00:00:18.1852", "tclevel": 1}, {"label": "3.074", "tc": "00:00:18.3521", "tclevel": 1}, {"label": "0.943", "tc": "00:00:18.5189", "tclevel": 1}, {"label": "0.682", "tc": "00:00:18.6857", "tclevel": 1}, {"label": "0.803", "tc": "00:00:18.8526", "tclevel": 1}, {"label": "3.826", "tc": "00:00:19.0194", "tclevel": 1}, {"label": "0.686", "tc": "00:00:19.1863", "tclevel": 1}, {"label": "0.966", "tc": "00:00:19.3531", "tclevel": 1}, {"label": "0.892", "tc": "00:00:19.5199", "tclevel": 1}, {"label": "3.508", "tc": "00:00:19.6868", "tclevel": 1}, {"label": "1.071", "tc": "00:00:19.8536", "tclevel": 1}, {"label": "1.693", "tc": "00:00:20.0204", "tclevel": 1}, {"label": "3.853", "tc": "00:00:20.1873", "tclevel": 1}, {"label": "1.655", "tc": "00:00:20.3541", "tclevel": 1}, {"label": "3.218", "tc": "00:00:20.5209", "tclevel": 1}, {"label": "1.127", "tc": "00:00:20.6878", "tclevel": 1}, {"label": "1.046", "tc": "00:00:20.8546", "tclevel": 1}, {"label": "2.475", "tc": "00:00:21.0215", "tclevel": 1}, {"label": "1.934", "tc": "00:00:21.1883", "tclevel": 1}, {"label": "2.213", "tc": "00:00:21.3551", "tclevel": 1}, {"label": "2.819", "tc": "00:00:21.5220", "tclevel": 1}, {"label": "0.469", "tc": "00:00:21.6888", "tclevel": 1}, {"label": "3.261", "tc": "00:00:21.8556", "tclevel": 1}, {"label": "0.313", "tc": "00:00:22.0225", "tclevel": 1}, {"label": "3.104", "tc": "00:00:22.1893", "tclevel": 1}, {"label": "3.671", "tc": "00:00:22.3562", "tclevel": 1}, {"label": "4.026", "tc": "00:00:22.5230", "tclevel": 1}, {"label": "0.961", "tc": "00:00:22.6898", "tclevel": 1}, {"label": "2.178", "tc": "00:00:22.8567", "tclevel": 1}, {"label": "0.113", "tc": "00:00:23.0235", "tclevel": 1}, {"label": "1.495", "tc": "00:00:23.1903", "tclevel": 1}, {"label": "1.504", "tc": "00:00:23.3572", "tclevel": 1}, {"label": "1.322", "tc": "00:00:23.5240", "tclevel": 1}, {"label": "1.253", "tc": "00:00:23.6909", "tclevel": 1}, {"label": "4.422", "tc": "00:00:23.8577", "tclevel": 1}, {"label": "1.948", "tc": "00:00:24.0245", "tclevel": 1}, {"label": "3.93", "tc": "00:00:24.1914", "tclevel": 1}, {"label": "4.174", "tc": "00:00:24.3582", "tclevel": 1}, {"label": "0.158", "tc": "00:00:24.5250", "tclevel": 1}, {"label": "0.249", "tc": "00:00:24.6919", "tclevel": 1}, {"label": "3.803", "tc": "00:00:24.8587", "tclevel": 1}, {"label": "3.595", "tc": "00:00:25.0255", "tclevel": 1}, {"label": "0.877", "tc": "00:00:25.1924", "tclevel": 1}, {"label": "2.998", "tc": "00:00:25.3592", "tclevel": 1}, {"label": "4.587", "tc": "00:00:25.5261", "tclevel": 1}, {"label": "1.383", "tc": "00:00:25.6929", "tclevel": 1}, {"label": "2.376", "tc": "00:00:25.8597", "tclevel": 1}, {"label": "1.458", "tc": "00:00:26.0266", "tclevel": 1}, {"label": "0.262", "tc": "00:00:26.1934", "tclevel": 1}, {"label": "2.139", "tc": "00:00:26.3602", "tclevel": 1}, {"label": "0.864", "tc": "00:00:26.5271", "tclevel": 1}, {"label": "3.747", "tc": "00:00:26.6939", "tclevel": 1}, {"label": "3.84", "tc": "00:00:26.8608", "tclevel": 1}, {"label": "2.27", "tc": "00:00:27.0276", "tclevel": 1}, {"label": "2.757", "tc": "00:00:27.1944", "tclevel": 1}, {"label": "0.876", "tc": "00:00:27.3613", "tclevel": 1}, {"label": "0.159", "tc": "00:00:27.5281", "tclevel": 1}, {"label": "3.108", "tc": "00:00:27.6949", "tclevel": 1}, {"label": "3.518", "tc": "00:00:27.8618", "tclevel": 1}, {"label": "1.159", "tc": "00:00:28.0286", "tclevel": 1}, {"label": "0.277", "tc": "00:00:28.1955", "tclevel": 1}, {"label": "1.409", "tc": "00:00:28.3623", "tclevel": 1}, {"label": "2.184", "tc": "00:00:28.5291", "tclevel": 1}, {"label": "3.397", "tc": "00:00:28.6960", "tclevel": 1}, {"label": "3.153", "tc": "00:00:28.8628", "tclevel": 1}, {"label": "2.521", "tc": "00:00:29.0296", "tclevel": 1}, {"label": "4.008", "tc": "00:00:29.1965", "tclevel": 1}, {"label": "3.011", "tc": "00:00:29.3633", "tclevel": 1}, {"label": "4.876", "tc": "00:00:29.5301", "tclevel": 1}, {"label": "2.687", "tc": "00:00:29.6970", "tclevel": 1}, {"label": "2.664", "tc": "00:00:29.8638", "tclevel": 1}, {"label": "1.589", "tc": "00:00:30.0307", "tclevel": 1}, {"label": "4.399", "tc": "00:00:30.1975", "tclevel": 1}, {"label": "4.718", "tc": "00:00:30.3643", "tclevel": 1}, {"label": "2.628", "tc": "00:00:30.5312", "tclevel": 1}, {"label": "3.656", "tc": "00:00:30.6980", "tclevel": 1}, {"label": "0.906", "tc": "00:00:30.8648", "tclevel": 1}, {"label": "3.012", "tc": "00:00:31.0317", "tclevel": 1}, {"label": "1.76", "tc": "00:00:31.1985", "tclevel": 1}, {"label": "0.384", "tc": "00:00:31.3654", "tclevel": 1}, {"label": "2.012", "tc": "00:00:31.5322", "tclevel": 1}, {"label": "2.47", "tc": "00:00:31.6990", "tclevel": 1}, {"label": "0.676", "tc": "00:00:31.8659", "tclevel": 1}, {"label": "3.515", "tc": "00:00:32.0327", "tclevel": 1}, {"label": "4.519", "tc": "00:00:32.1995", "tclevel": 1}, {"label": "4.837", "tc": "00:00:32.3664", "tclevel": 1}, {"label": "0.666", "tc": "00:00:32.5332", "tclevel": 1}, {"label": "2.269", "tc": "00:00:32.7000", "tclevel": 1}, {"label": "1.521", "tc": "00:00:32.8669", "tclevel": 1}, {"label": "4.948", "tc": "00:00:33.0337", "tclevel": 1}, {"label": "3.305", "tc": "00:00:33.2006", "tclevel": 1}, {"label": "4.76", "tc": "00:00:33.3674", "tclevel": 1}, {"label": "4.583", "tc": "00:00:33.5342", "tclevel": 1}, {"label": "2.263", "tc": "00:00:33.7011", "tclevel": 1}, {"label": "4.176", "tc": "00:00:33.8679", "tclevel": 1}, {"label": "4.96", "tc": "00:00:34.0347", "tclevel": 1}, {"label": "0.016", "tc": "00:00:34.2016", "tclevel": 1}, {"label": "2.889", "tc": "00:00:34.3684", "tclevel": 1}, {"label": "1.43", "tc": "00:00:34.5353", "tclevel": 1}, {"label": "2.862", "tc": "00:00:34.7021", "tclevel": 1}, {"label": "3.502", "tc": "00:00:34.8689", "tclevel": 1}, {"label": "2.76", "tc": "00:00:35.0358", "tclevel": 1}, {"label": "2.907", "tc": "00:00:35.2026", "tclevel": 1}, {"label": "1.858", "tc": "00:00:35.3694", "tclevel": 1}, {"label": "4.431", "tc": "00:00:35.5363", "tclevel": 1}, {"label": "4.143", "tc": "00:00:35.7031", "tclevel": 1}, {"label": "4.593", "tc": "00:00:35.8700", "tclevel": 1}, {"label": "3.779", "tc": "00:00:36.0368", "tclevel": 1}, {"label": "2.585", "tc": "00:00:36.2036", "tclevel": 1}, {"label": "0.834", "tc": "00:00:36.3705", "tclevel": 1}, {"label": "3.686", "tc": "00:00:36.5373", "tclevel": 1}, {"label": "0.544", "tc": "00:00:36.7041", "tclevel": 1}, {"label": "2.625", "tc": "00:00:36.8710", "tclevel": 1}, {"label": "3.79", "tc": "00:00:37.0378", "tclevel": 1}, {"label": "3.06", "tc": "00:00:37.2046", "tclevel": 1}, {"label": "0.763", "tc": "00:00:37.3715", "tclevel": 1}, {"label": "0.519", "tc": "00:00:37.5383", "tclevel": 1}, {"label": "0.632", "tc": "00:00:37.7052", "tclevel": 1}, {"label": "1.086", "tc": "00:00:37.8720", "tclevel": 1}, {"label": "0.167", "tc": "00:00:38.0388", "tclevel": 1}, {"label": "4.092", "tc": "00:00:38.2057", "tclevel": 1}, {"label": "1.952", "tc": "00:00:38.3725", "tclevel": 1}, {"label": "2.286", "tc": "00:00:38.5393", "tclevel": 1}, {"label": "3.583", "tc": "00:00:38.7062", "tclevel": 1}, {"label": "3.608", "tc": "00:00:38.8730", "tclevel": 1}, {"label": "3.394", "tc": "00:00:39.0399", "tclevel": 1}, {"label": "0.457", "tc": "00:00:39.2067", "tclevel": 1}, {"label": "2.716", "tc": "00:00:39.3735", "tclevel": 1}, {"label": "3.944", "tc": "00:00:39.5404", "tclevel": 1}, {"label": "0.764", "tc": "00:00:39.7072", "tclevel": 1}, {"label": "0.062", "tc": "00:00:39.8740", "tclevel": 1}, {"label": "1.744", "tc": "00:00:40.0409", "tclevel": 1}, {"label": "2.378", "tc": "00:00:40.2077", "tclevel": 1}, {"label": "3.952", "tc": "00:00:40.3746", "tclevel": 1}, {"label": "4.484", "tc": "00:00:40.5414", "tclevel": 1}, {"label": "2.017", "tc": "00:00:40.7082", "tclevel": 1}, {"label": "3.923", "tc": "00:00:40.8751", "tclevel": 1}, {"label": "4.775", "tc": "00:00:41.0419", "tclevel": 1}, {"label": "2.961", "tc": "00:00:41.2087", "tclevel": 1}, {"label": "4.314", "tc": "00:00:41.3756", "tclevel": 1}, {"label": "4.026", "tc": "00:00:41.5424", "tclevel": 1}, {"label": "1.87", "tc": "00:00:41.7092", "tclevel": 1}, {"label": "0.303", "tc": "00:00:41.8761", "tclevel": 1}, {"label": "4.033", "tc": "00:00:42.0429", "tclevel": 1}, {"label": "1.132", "tc": "00:00:42.2098", "tclevel": 1}, {"label": "3.781", "tc": "00:00:42.3766", "tclevel": 1}, {"label": "2.994", "tc": "00:00:42.5434", "tclevel": 1}, {"label": "4.811", "tc": "00:00:42.7103", "tclevel": 1}, {"label": "2.298", "tc": "00:00:42.8771", "tclevel": 1}, {"label": "4.602", "tc": "00:00:43.0439", "tclevel": 1}, {"label": "1.332", "tc": "00:00:43.2108", "tclevel": 1}, {"label": "2.826", "tc": "00:00:43.3776", "tclevel": 1}, {"label": "3.608", "tc": "00:00:43.5445", "tclevel": 1}, {"label": "1.387", "tc": "00:00:43.7113", "tclevel": 1}, {"label": "1.706", "tc": "00:00:43.8781", "tclevel": 1}, {"label": "3.118", "tc": "00:00:44.0450", "tclevel": 1}, {"label": "3.053", "tc": "00:00:44.2118", "tclevel": 1}, {"label": "0.25", "tc": "00:00:44.3786", "tclevel": 1}, {"label": "0.68", "tc": "00:00:44.5455", "tclevel": 1}, {"label": "2.718", "tc": "00:00:44.7123", "tclevel": 1}, {"label": "3.34", "tc": "00:00:44.8791", "tclevel": 1}, {"label": "4.173", "tc": "00:00:45.0460", "tclevel": 1}, {"label": "2.76", "tc": "00:00:45.2128", "tclevel": 1}, {"label": "4.217", "tc": "00:00:45.3797", "tclevel": 1}, {"label": "3.864", "tc": "00:00:45.5465", "tclevel": 1}, {"label": "4.671", "tc": "00:00:45.7133", "tclevel": 1}, {"label": "4.788", "tc": "00:00:45.8802", "tclevel": 1}, {"label": "0.16", "tc": "00:00:46.0470", "tclevel": 1}, {"label": "4.055", "tc": "00:00:46.2138", "tclevel": 1}, {"label": "2.505", "tc": "00:00:46.3807", "tclevel": 1}, {"label": "2.592", "tc": "00:00:46.5475", "tclevel": 1}, {"label": "3.502", "tc": "00:00:46.7144", "tclevel": 1}, {"label": "0.503", "tc": "00:00:46.8812", "tclevel": 1}, {"label": "4.344", "tc": "00:00:47.0480", "tclevel": 1}, {"label": "2.691", "tc": "00:00:47.2149", "tclevel": 1}, {"label": "2.955", "tc": "00:00:47.3817", "tclevel": 1}, {"label": "4.289", "tc": "00:00:47.5485", "tclevel": 1}, {"label": "2.356", "tc": "00:00:47.7154", "tclevel": 1}, {"label": "1.831", "tc": "00:00:47.8822", "tclevel": 1}, {"label": "4.45", "tc": "00:00:48.0491", "tclevel": 1}, {"label": "4.219", "tc": "00:00:48.2159", "tclevel": 1}, {"label": "2.019", "tc": "00:00:48.3827", "tclevel": 1}, {"label": "1.243", "tc": "00:00:48.5496", "tclevel": 1}, {"label": "1.995", "tc": "00:00:48.7164", "tclevel": 1}, {"label": "2.853", "tc": "00:00:48.8832", "tclevel": 1}, {"label": "1.988", "tc": "00:00:49.0501", "tclevel": 1}, {"label": "0.329", "tc": "00:00:49.2169", "tclevel": 1}, {"label": "3.055", "tc": "00:00:49.3837", "tclevel": 1}, {"label": "4.728", "tc": "00:00:49.5506", "tclevel": 1}, {"label": "3.123", "tc": "00:00:49.7174", "tclevel": 1}, {"label": "3.248", "tc": "00:00:49.8843", "tclevel": 1}, {"label": "4.976", "tc": "00:00:50.0511", "tclevel": 1}, {"label": "0.364", "tc": "00:00:50.2179", "tclevel": 1}, {"label": "0.771", "tc": "00:00:50.3848", "tclevel": 1}, {"label": "0.752", "tc": "00:00:50.5516", "tclevel": 1}, {"label": "1.756", "tc": "00:00:50.7184", "tclevel": 1}, {"label": "4.33", "tc": "00:00:50.8853", "tclevel": 1}, {"label": "2.79", "tc": "00:00:51.0521", "tclevel": 1}, {"label": "3.958", "tc": "00:00:51.2190", "tclevel": 1}, {"label": "0.954", "tc": "00:00:51.3858", "tclevel": 1}, {"label": "1.085", "tc": "00:00:51.5526", "tclevel": 1}, {"label": "0.638", "tc": "00:00:51.7195", "tclevel": 1}, {"label": "1.86", "tc": "00:00:51.8863", "tclevel": 1}, {"label": "1.152", "tc": "00:00:52.0531", "tclevel": 1}, {"label": "4.678", "tc": "00:00:52.2200", "tclevel": 1}, {"label": "4.532", "tc": "00:00:52.3868", "tclevel": 1}, {"label": "3.812", "tc": "00:00:52.5537", "tclevel": 1}, {"label": "4.267", "tc": "00:00:52.7205", "tclevel": 1}, {"label": "4.413", "tc": "00:00:52.8873", "tclevel": 1}, {"label": "2.434", "tc": "00:00:53.0542", "tclevel": 1}, {"label": "4.128", "tc": "00:00:53.2210", "tclevel": 1}, {"label": "4.42", "tc": "00:00:53.3878", "tclevel": 1}, {"label": "1.654", "tc": "00:00:53.5547", "tclevel": 1}, {"label": "0.509", "tc": "00:00:53.7215", "tclevel": 1}, {"label": "3.695", "tc": "00:00:53.8883", "tclevel": 1}, {"label": "0.914", "tc": "00:00:54.0552", "tclevel": 1}, {"label": "1.475", "tc": "00:00:54.2220", "tclevel": 1}, {"label": "4.138", "tc": "00:00:54.3889", "tclevel": 1}, {"label": "1.679", "tc": "00:00:54.5557", "tclevel": 1}, {"label": "4.244", "tc": "00:00:54.7225", "tclevel": 1}, {"label": "3.236", "tc": "00:00:54.8894", "tclevel": 1}, {"label": "4.81", "tc": "00:00:55.0562", "tclevel": 1}, {"label": "2.681", "tc": "00:00:55.2230", "tclevel": 1}, {"label": "2.259", "tc": "00:00:55.3899", "tclevel": 1}, {"label": "1.41", "tc": "00:00:55.5567", "tclevel": 1}, {"label": "1.54", "tc": "00:00:55.7236", "tclevel": 1}, {"label": "0.152", "tc": "00:00:55.8904", "tclevel": 1}, {"label": "0.706", "tc": "00:00:56.0572", "tclevel": 1}, {"label": "0.783", "tc": "00:00:56.2241", "tclevel": 1}, {"label": "2.238", "tc": "00:00:56.3909", "tclevel": 1}, {"label": "0.8", "tc": "00:00:56.5577", "tclevel": 1}, {"label": "4.631", "tc": "00:00:56.7246", "tclevel": 1}, {"label": "0.485", "tc": "00:00:56.8914", "tclevel": 1}, {"label": "0.483", "tc": "00:00:57.0582", "tclevel": 1}, {"label": "4.629", "tc": "00:00:57.2251", "tclevel": 1}, {"label": "4.508", "tc": "00:00:57.3919", "tclevel": 1}, {"label": "3.775", "tc": "00:00:57.5588", "tclevel": 1}, {"label": "0.62", "tc": "00:00:57.7256", "tclevel": 1}, {"label": "0.168", "tc": "00:00:57.8924", "tclevel": 1}, {"label": "2.694", "tc": "00:00:58.0593", "tclevel": 1}, {"label": "2.21", "tc": "00:00:58.2261", "tclevel": 1}, {"label": "4.522", "tc": "00:00:58.3929", "tclevel": 1}, {"label": "1.761", "tc": "00:00:58.5598", "tclevel": 1}, {"label": "1.711", "tc": "00:00:58.7266", "tclevel": 1}, {"label": "0.171", "tc": "00:00:58.8935", "tclevel": 1}, {"label": "3.543", "tc": "00:00:59.0603", "tclevel": 1}, {"label": "0.916", "tc": "00:00:59.2271", "tclevel": 1}, {"label": "4.528", "tc": "00:00:59.3940", "tclevel": 1}, {"label": "0.465", "tc": "00:00:59.5608", "tclevel": 1}, {"label": "3.381", "tc": "00:00:59.7276", "tclevel": 1}, {"label": "4.367", "tc": "00:00:59.8945", "tclevel": 1}, {"label": "1.072", "tc": "00:01:00.0613", "tclevel": 1}, {"label": "3.514", "tc": "00:01:00.2282", "tclevel": 1}, {"label": "0.7", "tc": "00:01:00.3950", "tclevel": 1}, {"label": "1.254", "tc": "00:01:00.5618", "tclevel": 1}, {"label": "4.57", "tc": "00:01:00.7287", "tclevel": 1}, {"label": "4.432", "tc": "00:01:00.8955", "tclevel": 1}, {"label": "4.581", "tc": "00:01:01.0623", "tclevel": 1}, {"label": "1.37", "tc": "00:01:01.2292", "tclevel": 1}, {"label": "4.032", "tc": "00:01:01.3960", "tclevel": 1}, {"label": "4.034", "tc": "00:01:01.5628", "tclevel": 1}, {"label": "4.65", "tc": "00:01:01.7297", "tclevel": 1}, {"label": "0.829", "tc": "00:01:01.8965", "tclevel": 1}, {"label": "0.565", "tc": "00:01:02.0634", "tclevel": 1}, {"label": "3.873", "tc": "00:01:02.2302", "tclevel": 1}, {"label": "4.914", "tc": "00:01:02.3970", "tclevel": 1}, {"label": "4.198", "tc": "00:01:02.5639", "tclevel": 1}, {"label": "3.336", "tc": "00:01:02.7307", "tclevel": 1}, {"label": "1.586", "tc": "00:01:02.8975", "tclevel": 1}, {"label": "4.848", "tc": "00:01:03.0644", "tclevel": 1}, {"label": "2.132", "tc": "00:01:03.2312", "tclevel": 1}, {"label": "1.394", "tc": "00:01:03.3981", "tclevel": 1}, {"label": "0.872", "tc": "00:01:03.5649", "tclevel": 1}, {"label": "3.943", "tc": "00:01:03.7317", "tclevel": 1}, {"label": "3.399", "tc": "00:01:03.8986", "tclevel": 1}, {"label": "1.001", "tc": "00:01:04.0654", "tclevel": 1}, {"label": "3.046", "tc": "00:01:04.2322", "tclevel": 1}, {"label": "1.281", "tc": "00:01:04.3991", "tclevel": 1}, {"label": "1.842", "tc": "00:01:04.5659", "tclevel": 1}, {"label": "4.134", "tc": "00:01:04.7328", "tclevel": 1}, {"label": "4.47", "tc": "00:01:04.8996", "tclevel": 1}, {"label": "3.835", "tc": "00:01:05.0664", "tclevel": 1}, {"label": "4.982", "tc": "00:01:05.2333", "tclevel": 1}, {"label": "1.169", "tc": "00:01:05.4001", "tclevel": 1}, {"label": "0.61", "tc": "00:01:05.5669", "tclevel": 1}, {"label": "0.269", "tc": "00:01:05.7338", "tclevel": 1}, {"label": "3.892", "tc": "00:01:05.9006", "tclevel": 1}, {"label": "2.216", "tc": "00:01:06.0674", "tclevel": 1}, {"label": "2.327", "tc": "00:01:06.2343", "tclevel": 1}, {"label": "3.401", "tc": "00:01:06.4011", "tclevel": 1}, {"label": "3.859", "tc": "00:01:06.5680", "tclevel": 1}, {"label": "0.844", "tc": "00:01:06.7348", "tclevel": 1}, {"label": "0.489", "tc": "00:01:06.9016", "tclevel": 1}, {"label": "2.242", "tc": "00:01:07.0685", "tclevel": 1}, {"label": "3.193", "tc": "00:01:07.2353", "tclevel": 1}, {"label": "1.894", "tc": "00:01:07.4021", "tclevel": 1}, {"label": "4.07", "tc": "00:01:07.5690", "tclevel": 1}, {"label": "2.3", "tc": "00:01:07.7358", "tclevel": 1}, {"label": "3.19", "tc": "00:01:07.9027", "tclevel": 1}, {"label": "2.785", "tc": "00:01:08.0695", "tclevel": 1}, {"label": "0.6", "tc": "00:01:08.2363", "tclevel": 1}, {"label": "3.668", "tc": "00:01:08.4032", "tclevel": 1}, {"label": "1.223", "tc": "00:01:08.5700", "tclevel": 1}, {"label": "0.464", "tc": "00:01:08.7368", "tclevel": 1}, {"label": "2.146", "tc": "00:01:08.9037", "tclevel": 1}, {"label": "4.454", "tc": "00:01:09.0705", "tclevel": 1}, {"label": "4.9", "tc": "00:01:09.2373", "tclevel": 1}, {"label": "4.532", "tc": "00:01:09.4042", "tclevel": 1}, {"label": "4.827", "tc": "00:01:09.5710", "tclevel": 1}, {"label": "3.828", "tc": "00:01:09.7379", "tclevel": 1}, {"label": "2.316", "tc": "00:01:09.9047", "tclevel": 1}, {"label": "3.47", "tc": "00:01:10.0715", "tclevel": 1}, {"label": "4.015", "tc": "00:01:10.2384", "tclevel": 1}, {"label": "0.88", "tc": "00:01:10.4052", "tclevel": 1}, {"label": "1.069", "tc": "00:01:10.5720", "tclevel": 1}, {"label": "0.742", "tc": "00:01:10.7389", "tclevel": 1}, {"label": "4.533", "tc": "00:01:10.9057", "tclevel": 1}, {"label": "3.094", "tc": "00:01:11.0726", "tclevel": 1}, {"label": "4.578", "tc": "00:01:11.2394", "tclevel": 1}, {"label": "1.98", "tc": "00:01:11.4062", "tclevel": 1}, {"label": "4.374", "tc": "00:01:11.5731", "tclevel": 1}, {"label": "4.803", "tc": "00:01:11.7399", "tclevel": 1}, {"label": "0.962", "tc": "00:01:11.9067", "tclevel": 1}, {"label": "1.633", "tc": "00:01:12.0736", "tclevel": 1}, {"label": "2.382", "tc": "00:01:12.2404", "tclevel": 1}, {"label": "1.412", "tc": "00:01:12.4073", "tclevel": 1}, {"label": "2.812", "tc": "00:01:12.5741", "tclevel": 1}, {"label": "3.701", "tc": "00:01:12.7409", "tclevel": 1}, {"label": "2.832", "tc": "00:01:12.9078", "tclevel": 1}, {"label": "0.528", "tc": "00:01:13.0746", "tclevel": 1}, {"label": "3.813", "tc": "00:01:13.2414", "tclevel": 1}, {"label": "0.123", "tc": "00:01:13.4083", "tclevel": 1}, {"label": "0.508", "tc": "00:01:13.5751", "tclevel": 1}, {"label": "1.496", "tc": "00:01:13.7419", "tclevel": 1}, {"label": "0.2", "tc": "00:01:13.9088", "tclevel": 1}, {"label": "4.103", "tc": "00:01:14.0756", "tclevel": 1}, {"label": "2.818", "tc": "00:01:14.2425", "tclevel": 1}, {"label": "4.979", "tc": "00:01:14.4093", "tclevel": 1}, {"label": "2.669", "tc": "00:01:14.5761", "tclevel": 1}, {"label": "0.777", "tc": "00:01:14.7430", "tclevel": 1}, {"label": "0.259", "tc": "00:01:14.9098", "tclevel": 1}, {"label": "0.475", "tc": "00:01:15.0766", "tclevel": 1}, {"label": "4.752", "tc": "00:01:15.2435", "tclevel": 1}, {"label": "4.12", "tc": "00:01:15.4103", "tclevel": 1}, {"label": "3.178", "tc": "00:01:15.5772", "tclevel": 1}, {"label": "0.069", "tc": "00:01:15.7440", "tclevel": 1}, {"label": "2.105", "tc": "00:01:15.9108", "tclevel": 1}, {"label": "2.857", "tc": "00:01:16.0777", "tclevel": 1}, {"label": "4.563", "tc": "00:01:16.2445", "tclevel": 1}, {"label": "3.746", "tc": "00:01:16.4113", "tclevel": 1}, {"label": "3.946", "tc": "00:01:16.5782", "tclevel": 1}, {"label": "4.864", "tc": "00:01:16.7450", "tclevel": 1}, {"label": "4.128", "tc": "00:01:16.9119", "tclevel": 1}, {"label": "1.201", "tc": "00:01:17.0787", "tclevel": 1}, {"label": "3.098", "tc": "00:01:17.2455", "tclevel": 1}, {"label": "0.191", "tc": "00:01:17.4124", "tclevel": 1}, {"label": "1.362", "tc": "00:01:17.5792", "tclevel": 1}, {"label": "3.302", "tc": "00:01:17.7460", "tclevel": 1}, {"label": "3.377", "tc": "00:01:17.9129", "tclevel": 1}, {"label": "0.585", "tc": "00:01:18.0797", "tclevel": 1}, {"label": "0.339", "tc": "00:01:18.2465", "tclevel": 1}, {"label": "0.64", "tc": "00:01:18.4134", "tclevel": 1}, {"label": "0.975", "tc": "00:01:18.5802", "tclevel": 1}, {"label": "2.91", "tc": "00:01:18.7471", "tclevel": 1}, {"label": "1.535", "tc": "00:01:18.9139", "tclevel": 1}, {"label": "4.166", "tc": "00:01:19.0807", "tclevel": 1}, {"label": "1.883", "tc": "00:01:19.2476", "tclevel": 1}, {"label": "2.598", "tc": "00:01:19.4144", "tclevel": 1}, {"label": "4.784", "tc": "00:01:19.5812", "tclevel": 1}, {"label": "0.908", "tc": "00:01:19.7481", "tclevel": 1}, {"label": "2.96", "tc": "00:01:19.9149", "tclevel": 1}, {"label": "3.036", "tc": "00:01:20.0818", "tclevel": 1}, {"label": "3.161", "tc": "00:01:20.2486", "tclevel": 1}, {"label": "0.255", "tc": "00:01:20.4154", "tclevel": 1}, {"label": "4.861", "tc": "00:01:20.5823", "tclevel": 1}, {"label": "4.833", "tc": "00:01:20.7491", "tclevel": 1}, {"label": "0.358", "tc": "00:01:20.9159", "tclevel": 1}, {"label": "1.458", "tc": "00:01:21.0828", "tclevel": 1}, {"label": "2.754", "tc": "00:01:21.2496", "tclevel": 1}, {"label": "1.595", "tc": "00:01:21.4164", "tclevel": 1}, {"label": "4.336", "tc": "00:01:21.5833", "tclevel": 1}, {"label": "0.077", "tc": "00:01:21.7501", "tclevel": 1}, {"label": "4.997", "tc": "00:01:21.9170", "tclevel": 1}, {"label": "3.768", "tc": "00:01:22.0838", "tclevel": 1}, {"label": "2.072", "tc": "00:01:22.2506", "tclevel": 1}, {"label": "0.26", "tc": "00:01:22.4175", "tclevel": 1}, {"label": "3.247", "tc": "00:01:22.5843", "tclevel": 1}, {"label": "3.27", "tc": "00:01:22.7511", "tclevel": 1}, {"label": "0.477", "tc": "00:01:22.9180", "tclevel": 1}, {"label": "1.227", "tc": "00:01:23.0848", "tclevel": 1}, {"label": "3.576", "tc": "00:01:23.2517", "tclevel": 1}, {"label": "1.631", "tc": "00:01:23.4185", "tclevel": 1}, {"label": "2.339", "tc": "00:01:23.5853", "tclevel": 1}, {"label": "4.077", "tc": "00:01:23.7522", "tclevel": 1}, {"label": "4.754", "tc": "00:01:23.9190", "tclevel": 1}, {"label": "1.493", "tc": "00:01:24.0858", "tclevel": 1}, {"label": "0.115", "tc": "00:01:24.2527", "tclevel": 1}, {"label": "4.236", "tc": "00:01:24.4195", "tclevel": 1}, {"label": "3.188", "tc": "00:01:24.5864", "tclevel": 1}, {"label": "1.351", "tc": "00:01:24.7532", "tclevel": 1}, {"label": "0.994", "tc": "00:01:24.9200", "tclevel": 1}, {"label": "0.328", "tc": "00:01:25.0869", "tclevel": 1}, {"label": "1.234", "tc": "00:01:25.2537", "tclevel": 1}, {"label": "2.131", "tc": "00:01:25.4205", "tclevel": 1}, {"label": "3.108", "tc": "00:01:25.5874", "tclevel": 1}, {"label": "4.137", "tc": "00:01:25.7542", "tclevel": 1}, {"label": "4.837", "tc": "00:01:25.9210", "tclevel": 1}, {"label": "4.856", "tc": "00:01:26.0879", "tclevel": 1}, {"label": "3.064", "tc": "00:01:26.2547", "tclevel": 1}, {"label": "2.264", "tc": "00:01:26.4216", "tclevel": 1}, {"label": "3.074", "tc": "00:01:26.5884", "tclevel": 1}, {"label": "0.094", "tc": "00:01:26.7552", "tclevel": 1}, {"label": "0.377", "tc": "00:01:26.9221", "tclevel": 1}, {"label": "4.041", "tc": "00:01:27.0889", "tclevel": 1}, {"label": "3.663", "tc": "00:01:27.2557", "tclevel": 1}, {"label": "0.817", "tc": "00:01:27.4226", "tclevel": 1}, {"label": "0.266", "tc": "00:01:27.5894", "tclevel": 1}, {"label": "2.262", "tc": "00:01:27.7563", "tclevel": 1}, {"label": "4.609", "tc": "00:01:27.9231", "tclevel": 1}, {"label": "4.184", "tc": "00:01:28.0899", "tclevel": 1}, {"label": "4.9", "tc": "00:01:28.2568", "tclevel": 1}, {"label": "2.003", "tc": "00:01:28.4236", "tclevel": 1}, {"label": "4.66", "tc": "00:01:28.5904", "tclevel": 1}, {"label": "4.741", "tc": "00:01:28.7573", "tclevel": 1}, {"label": "2.969", "tc": "00:01:28.9241", "tclevel": 1}, {"label": "2.755", "tc": "00:01:29.0910", "tclevel": 1}, {"label": "2.738", "tc": "00:01:29.2578", "tclevel": 1}, {"label": "0.19", "tc": "00:01:29.4246", "tclevel": 1}, {"label": "1.314", "tc": "00:01:29.5915", "tclevel": 1}, {"label": "2.12", "tc": "00:01:29.7583", "tclevel": 1}, {"label": "2.114", "tc": "00:01:29.9251", "tclevel": 1}, {"label": "2.066", "tc": "00:01:30.0920", "tclevel": 1}, {"label": "2.912", "tc": "00:01:30.2588", "tclevel": 1}, {"label": "3.525", "tc": "00:01:30.4256", "tclevel": 1}, {"label": "0.264", "tc": "00:01:30.5925", "tclevel": 1}, {"label": "1.992", "tc": "00:01:30.7593", "tclevel": 1}, {"label": "3.264", "tc": "00:01:30.9262", "tclevel": 1}, {"label": "3.123", "tc": "00:01:31.0930", "tclevel": 1}, {"label": "2.512", "tc": "00:01:31.2598", "tclevel": 1}, {"label": "0.026", "tc": "00:01:31.4267", "tclevel": 1}, {"label": "3.501", "tc": "00:01:31.5935", "tclevel": 1}, {"label": "2.119", "tc": "00:01:31.7603", "tclevel": 1}, {"label": "0.71", "tc": "00:01:31.9272", "tclevel": 1}, {"label": "2.146", "tc": "00:01:32.0940", "tclevel": 1}, {"label": "3.054", "tc": "00:01:32.2609", "tclevel": 1}, {"label": "4.026", "tc": "00:01:32.4277", "tclevel": 1}, {"label": "3.68", "tc": "00:01:32.5945", "tclevel": 1}, {"label": "3.32", "tc": "00:01:32.7614", "tclevel": 1}, {"label": "3.362", "tc": "00:01:32.9282", "tclevel": 1}, {"label": "3.441", "tc": "00:01:33.0950", "tclevel": 1}, {"label": "0.592", "tc": "00:01:33.2619", "tclevel": 1}, {"label": "1.1", "tc": "00:01:33.4287", "tclevel": 1}, {"label": "4.274", "tc": "00:01:33.5955", "tclevel": 1}, {"label": "3.299", "tc": "00:01:33.7624", "tclevel": 1}, {"label": "0.429", "tc": "00:01:33.9292", "tclevel": 1}, {"label": "0.346", "tc": "00:01:34.0961", "tclevel": 1}, {"label": "2.502", "tc": "00:01:34.2629", "tclevel": 1}, {"label": "3.218", "tc": "00:01:34.4297", "tclevel": 1}, {"label": "2.638", "tc": "00:01:34.5966", "tclevel": 1}, {"label": "1.48", "tc": "00:01:34.7634", "tclevel": 1}, {"label": "3.487", "tc": "00:01:34.9302", "tclevel": 1}, {"label": "4.622", "tc": "00:01:35.0971", "tclevel": 1}, {"label": "2.605", "tc": "00:01:35.2639", "tclevel": 1}, {"label": "1.288", "tc": "00:01:35.4308", "tclevel": 1}, {"label": "3.703", "tc": "00:01:35.5976", "tclevel": 1}, {"label": "1.305", "tc": "00:01:35.7644", "tclevel": 1}, {"label": "4.224", "tc": "00:01:35.9313", "tclevel": 1}, {"label": "4.296", "tc": "00:01:36.0981", "tclevel": 1}, {"label": "2.791", "tc": "00:01:36.2649", "tclevel": 1}, {"label": "4.384", "tc": "00:01:36.4318", "tclevel": 1}, {"label": "0.797", "tc": "00:01:36.5986", "tclevel": 1}, {"label": "3.602", "tc": "00:01:36.7655", "tclevel": 1}, {"label": "0.973", "tc": "00:01:36.9323", "tclevel": 1}, {"label": "0.572", "tc": "00:01:37.0991", "tclevel": 1}, {"label": "1.302", "tc": "00:01:37.2660", "tclevel": 1}, {"label": "1.316", "tc": "00:01:37.4328", "tclevel": 1}, {"label": "2.329", "tc": "00:01:37.5996", "tclevel": 1}, {"label": "4.64", "tc": "00:01:37.7665", "tclevel": 1}, {"label": "1.951", "tc": "00:01:37.9333", "tclevel": 1}, {"label": "4.577", "tc": "00:01:38.1001", "tclevel": 1}, {"label": "4.702", "tc": "00:01:38.2670", "tclevel": 1}, {"label": "1.002", "tc": "00:01:38.4338", "tclevel": 1}, {"label": "4.344", "tc": "00:01:38.6007", "tclevel": 1}, {"label": "0.75", "tc": "00:01:38.7675", "tclevel": 1}, {"label": "1.948", "tc": "00:01:38.9343", "tclevel": 1}, {"label": "4.653", "tc": "00:01:39.1012", "tclevel": 1}, {"label": "4.172", "tc": "00:01:39.2680", "tclevel": 1}, {"label": "3.331", "tc": "00:01:39.4348", "tclevel": 1}, {"label": "3.381", "tc": "00:01:39.6017", "tclevel": 1}, {"label": "3.14", "tc": "00:01:39.7685", "tclevel": 1}, {"label": "1.703", "tc": "00:01:39.9354", "tclevel": 1}, {"label": "0.458", "tc": "00:01:40.1022", "tclevel": 1}, {"label": "3.548", "tc": "00:01:40.2690", "tclevel": 1}, {"label": "2.446", "tc": "00:01:40.4359", "tclevel": 1}, {"label": "3.801", "tc": "00:01:40.6027", "tclevel": 1}, {"label": "1.387", "tc": "00:01:40.7695", "tclevel": 1}, {"label": "2.31", "tc": "00:01:40.9364", "tclevel": 1}, {"label": "1.614", "tc": "00:01:41.1032", "tclevel": 1}, {"label": "2.111", "tc": "00:01:41.2701", "tclevel": 1}, {"label": "2.195", "tc": "00:01:41.4369", "tclevel": 1}, {"label": "3.321", "tc": "00:01:41.6037", "tclevel": 1}, {"label": "3.768", "tc": "00:01:41.7706", "tclevel": 1}, {"label": "2.029", "tc": "00:01:41.9374", "tclevel": 1}, {"label": "3.891", "tc": "00:01:42.1042", "tclevel": 1}, {"label": "4.196", "tc": "00:01:42.2711", "tclevel": 1}, {"label": "1.91", "tc": "00:01:42.4379", "tclevel": 1}, {"label": "1.89", "tc": "00:01:42.6047", "tclevel": 1}, {"label": "2.403", "tc": "00:01:42.7716", "tclevel": 1}, {"label": "1.824", "tc": "00:01:42.9384", "tclevel": 1}, {"label": "3.884", "tc": "00:01:43.1053", "tclevel": 1}, {"label": "4.411", "tc": "00:01:43.2721", "tclevel": 1}, {"label": "0.976", "tc": "00:01:43.4389", "tclevel": 1}, {"label": "2.811", "tc": "00:01:43.6058", "tclevel": 1}, {"label": "4.474", "tc": "00:01:43.7726", "tclevel": 1}, {"label": "4.763", "tc": "00:01:43.9394", "tclevel": 1}, {"label": "1.77", "tc": "00:01:44.1063", "tclevel": 1}, {"label": "1.326", "tc": "00:01:44.2731", "tclevel": 1}, {"label": "4.695", "tc": "00:01:44.4400", "tclevel": 1}, {"label": "2.148", "tc": "00:01:44.6068", "tclevel": 1}, {"label": "2.8", "tc": "00:01:44.7736", "tclevel": 1}, {"label": "2.108", "tc": "00:01:44.9405", "tclevel": 1}, {"label": "1.004", "tc": "00:01:45.1073", "tclevel": 1}, {"label": "2.358", "tc": "00:01:45.2741", "tclevel": 1}, {"label": "1.814", "tc": "00:01:45.4410", "tclevel": 1}, {"label": "2.946", "tc": "00:01:45.6078", "tclevel": 1}, {"label": "3.185", "tc": "00:01:45.7747", "tclevel": 1}, {"label": "0.32", "tc": "00:01:45.9415", "tclevel": 1}, {"label": "0.555", "tc": "00:01:46.1083", "tclevel": 1}, {"label": "4.988", "tc": "00:01:46.2752", "tclevel": 1}, {"label": "3.346", "tc": "00:01:46.4420", "tclevel": 1}, {"label": "1.3", "tc": "00:01:46.6088", "tclevel": 1}, {"label": "2.386", "tc": "00:01:46.7757", "tclevel": 1}, {"label": "4.705", "tc": "00:01:46.9425", "tclevel": 1}, {"label": "3.272", "tc": "00:01:47.1093", "tclevel": 1}, {"label": "2.769", "tc": "00:01:47.2762", "tclevel": 1}, {"label": "1.878", "tc": "00:01:47.4430", "tclevel": 1}, {"label": "0.318", "tc": "00:01:47.6099", "tclevel": 1}, {"label": "2.206", "tc": "00:01:47.7767", "tclevel": 1}, {"label": "1.477", "tc": "00:01:47.9435", "tclevel": 1}, {"label": "4.623", "tc": "00:01:48.1104", "tclevel": 1}, {"label": "1.141", "tc": "00:01:48.2772", "tclevel": 1}, {"label": "0.798", "tc": "00:01:48.4440", "tclevel": 1}, {"label": "3.508", "tc": "00:01:48.6109", "tclevel": 1}, {"label": "1.05", "tc": "00:01:48.7777", "tclevel": 1}, {"label": "3.695", "tc": "00:01:48.9446", "tclevel": 1}, {"label": "3.601", "tc": "00:01:49.1114", "tclevel": 1}, {"label": "3.087", "tc": "00:01:49.2782", "tclevel": 1}, {"label": "0.002", "tc": "00:01:49.4451", "tclevel": 1}, {"label": "1.683", "tc": "00:01:49.6119", "tclevel": 1}, {"label": "1.64", "tc": "00:01:49.7787", "tclevel": 1}, {"label": "3.295", "tc": "00:01:49.9456", "tclevel": 1}, {"label": "0.18", "tc": "00:01:50.1124", "tclevel": 1}, {"label": "1.621", "tc": "00:01:50.2792", "tclevel": 1}, {"label": "1.541", "tc": "00:01:50.4461", "tclevel": 1}, {"label": "2.077", "tc": "00:01:50.6129", "tclevel": 1}, {"label": "3.408", "tc": "00:01:50.7798", "tclevel": 1}, {"label": "4.386", "tc": "00:01:50.9466", "tclevel": 1}, {"label": "1.287", "tc": "00:01:51.1134", "tclevel": 1}, {"label": "3.989", "tc": "00:01:51.2803", "tclevel": 1}, {"label": "4.037", "tc": "00:01:51.4471", "tclevel": 1}, {"label": "2.3", "tc": "00:01:51.6139", "tclevel": 1}, {"label": "3.033", "tc": "00:01:51.7808", "tclevel": 1}, {"label": "3.178", "tc": "00:01:51.9476", "tclevel": 1}, {"label": "4.985", "tc": "00:01:52.1145", "tclevel": 1}, {"label": "2.815", "tc": "00:01:52.2813", "tclevel": 1}, {"label": "2.014", "tc": "00:01:52.4481", "tclevel": 1}, {"label": "4.395", "tc": "00:01:52.6150", "tclevel": 1}, {"label": "3.348", "tc": "00:01:52.7818", "tclevel": 1}, {"label": "1.545", "tc": "00:01:52.9486", "tclevel": 1}, {"label": "3.869", "tc": "00:01:53.1155", "tclevel": 1}, {"label": "3.8", "tc": "00:01:53.2823", "tclevel": 1}, {"label": "2.931", "tc": "00:01:53.4492", "tclevel": 1}, {"label": "1.468", "tc": "00:01:53.6160", "tclevel": 1}, {"label": "1.422", "tc": "00:01:53.7828", "tclevel": 1}, {"label": "0.174", "tc": "00:01:53.9497", "tclevel": 1}, {"label": "4.676", "tc": "00:01:54.1165", "tclevel": 1}, {"label": "1.536", "tc": "00:01:54.2833", "tclevel": 1}, {"label": "2.132", "tc": "00:01:54.4502", "tclevel": 1}, {"label": "4.676", "tc": "00:01:54.6170", "tclevel": 1}, {"label": "3.326", "tc": "00:01:54.7838", "tclevel": 1}, {"label": "4.443", "tc": "00:01:54.9507", "tclevel": 1}, {"label": "1.223", "tc": "00:01:55.1175", "tclevel": 1}, {"label": "3.014", "tc": "00:01:55.2844", "tclevel": 1}, {"label": "3.712", "tc": "00:01:55.4512", "tclevel": 1}, {"label": "1.724", "tc": "00:01:55.6180", "tclevel": 1}, {"label": "1.171", "tc": "00:01:55.7849", "tclevel": 1}, {"label": "3.501", "tc": "00:01:55.9517", "tclevel": 1}, {"label": "2.896", "tc": "00:01:56.1185", "tclevel": 1}, {"label": "1.774", "tc": "00:01:56.2854", "tclevel": 1}, {"label": "2.326", "tc": "00:01:56.4522", "tclevel": 1}, {"label": "2.946", "tc": "00:01:56.6191", "tclevel": 1}, {"label": "0.863", "tc": "00:01:56.7859", "tclevel": 1}, {"label": "2.849", "tc": "00:01:56.9527", "tclevel": 1}, {"label": "2.89", "tc": "00:01:57.1196", "tclevel": 1}, {"label": "4.84", "tc": "00:01:57.2864", "tclevel": 1}, {"label": "4.024", "tc": "00:01:57.4532", "tclevel": 1}, {"label": "1.451", "tc": "00:01:57.6201", "tclevel": 1}, {"label": "2.949", "tc": "00:01:57.7869", "tclevel": 1}, {"label": "2.46", "tc": "00:01:57.9538", "tclevel": 1}, {"label": "4.703", "tc": "00:01:58.1206", "tclevel": 1}, {"label": "2.038", "tc": "00:01:58.2874", "tclevel": 1}, {"label": "4.727", "tc": "00:01:58.4543", "tclevel": 1}, {"label": "4.161", "tc": "00:01:58.6211", "tclevel": 1}, {"label": "2.403", "tc": "00:01:58.7879", "tclevel": 1}, {"label": "1.24", "tc": "00:01:58.9548", "tclevel": 1}, {"label": "2.536", "tc": "00:01:59.1216", "tclevel": 1}, {"label": "4.499", "tc": "00:01:59.2884", "tclevel": 1}, {"label": "1.699", "tc": "00:01:59.4553", "tclevel": 1}, {"label": "2.228", "tc": "00:01:59.6221", "tclevel": 1}, {"label": "2.904", "tc": "00:01:59.7890", "tclevel": 1}, {"label": "4.211", "tc": "00:01:59.9558", "tclevel": 1}, {"label": "3.224", "tc": "00:02:00.1226", "tclevel": 1}, {"label": "1.533", "tc": "00:02:00.2895", "tclevel": 1}, {"label": "0.087", "tc": "00:02:00.4563", "tclevel": 1}, {"label": "3.675", "tc": "00:02:00.6231", "tclevel": 1}, {"label": "3.14", "tc": "00:02:00.7900", "tclevel": 1}, {"label": "0.172", "tc": "00:02:00.9568", "tclevel": 1}, {"label": "4.935", "tc": "00:02:01.1237", "tclevel": 1}, {"label": "4.433", "tc": "00:02:01.2905", "tclevel": 1}, {"label": "2.982", "tc": "00:02:01.4573", "tclevel": 1}, {"label": "0.413", "tc": "00:02:01.6242", "tclevel": 1}, {"label": "2.663", "tc": "00:02:01.7910", "tclevel": 1}, {"label": "3.368", "tc": "00:02:01.9578", "tclevel": 1}, {"label": "3.238", "tc": "00:02:02.1247", "tclevel": 1}, {"label": "4.956", "tc": "00:02:02.2915", "tclevel": 1}, {"label": "4.726", "tc": "00:02:02.4583", "tclevel": 1}, {"label": "0.577", "tc": "00:02:02.6252", "tclevel": 1}, {"label": "1.907", "tc": "00:02:02.7920", "tclevel": 1}, {"label": "2.81", "tc": "00:02:02.9589", "tclevel": 1}, {"label": "3.588", "tc": "00:02:03.1257", "tclevel": 1}, {"label": "0.063", "tc": "00:02:03.2925", "tclevel": 1}, {"label": "4.336", "tc": "00:02:03.4594", "tclevel": 1}, {"label": "1.583", "tc": "00:02:03.6262", "tclevel": 1}, {"label": "3.421", "tc": "00:02:03.7930", "tclevel": 1}, {"label": "1.9", "tc": "00:02:03.9599", "tclevel": 1}, {"label": "3.836", "tc": "00:02:04.1267", "tclevel": 1}, {"label": "2.539", "tc": "00:02:04.2936", "tclevel": 1}, {"label": "4.232", "tc": "00:02:04.4604", "tclevel": 1}, {"label": "1.647", "tc": "00:02:04.6272", "tclevel": 1}, {"label": "2.241", "tc": "00:02:04.7941", "tclevel": 1}, {"label": "3.238", "tc": "00:02:04.9609", "tclevel": 1}, {"label": "4.76", "tc": "00:02:05.1277", "tclevel": 1}, {"label": "3.687", "tc": "00:02:05.2946", "tclevel": 1}, {"label": "2.295", "tc": "00:02:05.4614", "tclevel": 1}, {"label": "2.85", "tc": "00:02:05.6283", "tclevel": 1}, {"label": "0.28", "tc": "00:02:05.7951", "tclevel": 1}, {"label": "4.075", "tc": "00:02:05.9619", "tclevel": 1}, {"label": "2.079", "tc": "00:02:06.1288", "tclevel": 1}, {"label": "1.337", "tc": "00:02:06.2956", "tclevel": 1}, {"label": "4.573", "tc": "00:02:06.4624", "tclevel": 1}, {"label": "1.469", "tc": "00:02:06.6293", "tclevel": 1}, {"label": "3.324", "tc": "00:02:06.7961", "tclevel": 1}, {"label": "3.089", "tc": "00:02:06.9629", "tclevel": 1}, {"label": "4.337", "tc": "00:02:07.1298", "tclevel": 1}, {"label": "3.099", "tc": "00:02:07.2966", "tclevel": 1}, {"label": "3.982", "tc": "00:02:07.4635", "tclevel": 1}, {"label": "3.093", "tc": "00:02:07.6303", "tclevel": 1}, {"label": "3.464", "tc": "00:02:07.7971", "tclevel": 1}, {"label": "4.899", "tc": "00:02:07.9640", "tclevel": 1}, {"label": "2.626", "tc": "00:02:08.1308", "tclevel": 1}, {"label": "2.902", "tc": "00:02:08.2976", "tclevel": 1}, {"label": "0.898", "tc": "00:02:08.4645", "tclevel": 1}, {"label": "2.891", "tc": "00:02:08.6313", "tclevel": 1}, {"label": "3.154", "tc": "00:02:08.7982", "tclevel": 1}, {"label": "3.174", "tc": "00:02:08.9650", "tclevel": 1}, {"label": "2.019", "tc": "00:02:09.1318", "tclevel": 1}, {"label": "1.154", "tc": "00:02:09.2987", "tclevel": 1}, {"label": "1.42", "tc": "00:02:09.4655", "tclevel": 1}, {"label": "4.211", "tc": "00:02:09.6323", "tclevel": 1}, {"label": "4.569", "tc": "00:02:09.7992", "tclevel": 1}, {"label": "0.016", "tc": "00:02:09.9660", "tclevel": 1}, {"label": "2.258", "tc": "00:02:10.1329", "tclevel": 1}, {"label": "1.276", "tc": "00:02:10.2997", "tclevel": 1}, {"label": "3.46", "tc": "00:02:10.4665", "tclevel": 1}, {"label": "2.201", "tc": "00:02:10.6334", "tclevel": 1}, {"label": "3.554", "tc": "00:02:10.8002", "tclevel": 1}, {"label": "4.535", "tc": "00:02:10.9670", "tclevel": 1}, {"label": "1.175", "tc": "00:02:11.1339", "tclevel": 1}, {"label": "2.25", "tc": "00:02:11.3007", "tclevel": 1}, {"label": "3.193", "tc": "00:02:11.4675", "tclevel": 1}, {"label": "0.021", "tc": "00:02:11.6344", "tclevel": 1}, {"label": "0.062", "tc": "00:02:11.8012", "tclevel": 1}, {"label": "3.972", "tc": "00:02:11.9681", "tclevel": 1}, {"label": "2.557", "tc": "00:02:12.1349", "tclevel": 1}, {"label": "4.662", "tc": "00:02:12.3017", "tclevel": 1}, {"label": "2.598", "tc": "00:02:12.4686", "tclevel": 1}, {"label": "1.994", "tc": "00:02:12.6354", "tclevel": 1}, {"label": "0.514", "tc": "00:02:12.8022", "tclevel": 1}, {"label": "0.207", "tc": "00:02:12.9691", "tclevel": 1}, {"label": "0.509", "tc": "00:02:13.1359", "tclevel": 1}, {"label": "4.788", "tc": "00:02:13.3028", "tclevel": 1}, {"label": "1.971", "tc": "00:02:13.4696", "tclevel": 1}, {"label": "2.943", "tc": "00:02:13.6364", "tclevel": 1}, {"label": "2.796", "tc": "00:02:13.8033", "tclevel": 1}, {"label": "0.789", "tc": "00:02:13.9701", "tclevel": 1}, {"label": "0.283", "tc": "00:02:14.1369", "tclevel": 1}, {"label": "2.814", "tc": "00:02:14.3038", "tclevel": 1}, {"label": "1.919", "tc": "00:02:14.4706", "tclevel": 1}, {"label": "2.446", "tc": "00:02:14.6374", "tclevel": 1}, {"label": "3.823", "tc": "00:02:14.8043", "tclevel": 1}, {"label": "1.698", "tc": "00:02:14.9711", "tclevel": 1}, {"label": "2.922", "tc": "00:02:15.1380", "tclevel": 1}, {"label": "3.153", "tc": "00:02:15.3048", "tclevel": 1}, {"label": "1.072", "tc": "00:02:15.4716", "tclevel": 1}, {"label": "1.343", "tc": "00:02:15.6385", "tclevel": 1}, {"label": "2.525", "tc": "00:02:15.8053", "tclevel": 1}, {"label": "3.578", "tc": "00:02:15.9721", "tclevel": 1}, {"label": "4.012", "tc": "00:02:16.1390", "tclevel": 1}, {"label": "1.356", "tc": "00:02:16.3058", "tclevel": 1}, {"label": "3.444", "tc": "00:02:16.4727", "tclevel": 1}, {"label": "1.734", "tc": "00:02:16.6395", "tclevel": 1}, {"label": "4.108", "tc": "00:02:16.8063", "tclevel": 1}, {"label": "3.066", "tc": "00:02:16.9732", "tclevel": 1}, {"label": "1.229", "tc": "00:02:17.1400", "tclevel": 1}, {"label": "0.403", "tc": "00:02:17.3068", "tclevel": 1}, {"label": "4.417", "tc": "00:02:17.4737", "tclevel": 1}, {"label": "0.396", "tc": "00:02:17.6405", "tclevel": 1}, {"label": "1.755", "tc": "00:02:17.8074", "tclevel": 1}, {"label": "2.073", "tc": "00:02:17.9742", "tclevel": 1}, {"label": "1.321", "tc": "00:02:18.1410", "tclevel": 1}, {"label": "1.71", "tc": "00:02:18.3079", "tclevel": 1}, {"label": "2.867", "tc": "00:02:18.4747", "tclevel": 1}, {"label": "2.392", "tc": "00:02:18.6415", "tclevel": 1}, {"label": "4.331", "tc": "00:02:18.8084", "tclevel": 1}, {"label": "2.945", "tc": "00:02:18.9752", "tclevel": 1}, {"label": "3.362", "tc": "00:02:19.1420", "tclevel": 1}, {"label": "2.404", "tc": "00:02:19.3089", "tclevel": 1}, {"label": "1.735", "tc": "00:02:19.4757", "tclevel": 1}, {"label": "3.886", "tc": "00:02:19.6426", "tclevel": 1}, {"label": "1.304", "tc": "00:02:19.8094", "tclevel": 1}, {"label": "4.82", "tc": "00:02:19.9762", "tclevel": 1}, {"label": "4.942", "tc": "00:02:20.1431", "tclevel": 1}, {"label": "1.61", "tc": "00:02:20.3099", "tclevel": 1}, {"label": "4.792", "tc": "00:02:20.4767", "tclevel": 1}, {"label": "1.406", "tc": "00:02:20.6436", "tclevel": 1}, {"label": "3.518", "tc": "00:02:20.8104", "tclevel": 1}, {"label": "2.339", "tc": "00:02:20.9773", "tclevel": 1}, {"label": "2.342", "tc": "00:02:21.1441", "tclevel": 1}, {"label": "0.317", "tc": "00:02:21.3109", "tclevel": 1}, {"label": "2.2", "tc": "00:02:21.4778", "tclevel": 1}, {"label": "0.69", "tc": "00:02:21.6446", "tclevel": 1}, {"label": "2.818", "tc": "00:02:21.8114", "tclevel": 1}, {"label": "1.347", "tc": "00:02:21.9783", "tclevel": 1}, {"label": "1.913", "tc": "00:02:22.1451", "tclevel": 1}, {"label": "0.012", "tc": "00:02:22.3120", "tclevel": 1}, {"label": "3.041", "tc": "00:02:22.4788", "tclevel": 1}, {"label": "4.073", "tc": "00:02:22.6456", "tclevel": 1}, {"label": "2.239", "tc": "00:02:22.8125", "tclevel": 1}, {"label": "2.847", "tc": "00:02:22.9793", "tclevel": 1}, {"label": "1.452", "tc": "00:02:23.1461", "tclevel": 1}, {"label": "2.825", "tc": "00:02:23.3130", "tclevel": 1}, {"label": "3.205", "tc": "00:02:23.4798", "tclevel": 1}, {"label": "1.131", "tc": "00:02:23.6466", "tclevel": 1}, {"label": "0.13", "tc": "00:02:23.8135", "tclevel": 1}, {"label": "2.918", "tc": "00:02:23.9803", "tclevel": 1}, {"label": "3.64", "tc": "00:02:24.1472", "tclevel": 1}, {"label": "3.509", "tc": "00:02:24.3140", "tclevel": 1}, {"label": "3.829", "tc": "00:02:24.4808", "tclevel": 1}, {"label": "4.371", "tc": "00:02:24.6477", "tclevel": 1}, {"label": "2.172", "tc": "00:02:24.8145", "tclevel": 1}, {"label": "2.644", "tc": "00:02:24.9813", "tclevel": 1}, {"label": "1.757", "tc": "00:02:25.1482", "tclevel": 1}, {"label": "3.934", "tc": "00:02:25.3150", "tclevel": 1}, {"label": "3.396", "tc": "00:02:25.4819", "tclevel": 1}, {"label": "0.034", "tc": "00:02:25.6487", "tclevel": 1}, {"label": "4.985", "tc": "00:02:25.8155", "tclevel": 1}, {"label": "3.786", "tc": "00:02:25.9824", "tclevel": 1}, {"label": "2.733", "tc": "00:02:26.1492", "tclevel": 1}, {"label": "3.025", "tc": "00:02:26.3160", "tclevel": 1}, {"label": "1.935", "tc": "00:02:26.4829", "tclevel": 1}, {"label": "0.33", "tc": "00:02:26.6497", "tclevel": 1}, {"label": "2.685", "tc": "00:02:26.8165", "tclevel": 1}, {"label": "2.659", "tc": "00:02:26.9834", "tclevel": 1}, {"label": "0.541", "tc": "00:02:27.1502", "tclevel": 1}, {"label": "1.325", "tc": "00:02:27.3171", "tclevel": 1}, {"label": "1.257", "tc": "00:02:27.4839", "tclevel": 1}, {"label": "1.737", "tc": "00:02:27.6507", "tclevel": 1}, {"label": "4.626", "tc": "00:02:27.8176", "tclevel": 1}, {"label": "0.524", "tc": "00:02:27.9844", "tclevel": 1}, {"label": "2.958", "tc": "00:02:28.1512", "tclevel": 1}, {"label": "4.865", "tc": "00:02:28.3181", "tclevel": 1}, {"label": "3.664", "tc": "00:02:28.4849", "tclevel": 1}, {"label": "4.779", "tc": "00:02:28.6518", "tclevel": 1}, {"label": "0.319", "tc": "00:02:28.8186", "tclevel": 1}, {"label": "3.815", "tc": "00:02:28.9854", "tclevel": 1}, {"label": "0.144", "tc": "00:02:29.1523", "tclevel": 1}, {"label": "0.071", "tc": "00:02:29.3191", "tclevel": 1}, {"label": "2.356", "tc": "00:02:29.4859", "tclevel": 1}, {"label": "1.712", "tc": "00:02:29.6528", "tclevel": 1}, {"label": "4.872", "tc": "00:02:29.8196", "tclevel": 1}, {"label": "2.882", "tc": "00:02:29.9865", "tclevel": 1}, {"label": "3.542", "tc": "00:02:30.1533", "tclevel": 1}, {"label": "2.853", "tc": "00:02:30.3201", "tclevel": 1}, {"label": "4.613", "tc": "00:02:30.4870", "tclevel": 1}, {"label": "3.461", "tc": "00:02:30.6538", "tclevel": 1}, {"label": "3.661", "tc": "00:02:30.8206", "tclevel": 1}, {"label": "4.243", "tc": "00:02:30.9875", "tclevel": 1}, {"label": "1.312", "tc": "00:02:31.1543", "tclevel": 1}, {"label": "2.62", "tc": "00:02:31.3211", "tclevel": 1}, {"label": "3.786", "tc": "00:02:31.4880", "tclevel": 1}, {"label": "3.131", "tc": "00:02:31.6548", "tclevel": 1}, {"label": "2.14", "tc": "00:02:31.8217", "tclevel": 1}, {"label": "4.101", "tc": "00:02:31.9885", "tclevel": 1}, {"label": "0.139", "tc": "00:02:32.1553", "tclevel": 1}, {"label": "1.897", "tc": "00:02:32.3222", "tclevel": 1}, {"label": "3.706", "tc": "00:02:32.4890", "tclevel": 1}, {"label": "0.9", "tc": "00:02:32.6558", "tclevel": 1}, {"label": "1.978", "tc": "00:02:32.8227", "tclevel": 1}, {"label": "2.559", "tc": "00:02:32.9895", "tclevel": 1}, {"label": "2.582", "tc": "00:02:33.1564", "tclevel": 1}, {"label": "2.298", "tc": "00:02:33.3232", "tclevel": 1}, {"label": "3.336", "tc": "00:02:33.4900", "tclevel": 1}, {"label": "3.406", "tc": "00:02:33.6569", "tclevel": 1}, {"label": "4.846", "tc": "00:02:33.8237", "tclevel": 1}, {"label": "3.407", "tc": "00:02:33.9905", "tclevel": 1}, {"label": "1.603", "tc": "00:02:34.1574", "tclevel": 1}, {"label": "0.72", "tc": "00:02:34.3242", "tclevel": 1}, {"label": "4.683", "tc": "00:02:34.4911", "tclevel": 1}, {"label": "1.506", "tc": "00:02:34.6579", "tclevel": 1}, {"label": "0.548", "tc": "00:02:34.8247", "tclevel": 1}, {"label": "3.086", "tc": "00:02:34.9916", "tclevel": 1}, {"label": "4.726", "tc": "00:02:35.1584", "tclevel": 1}, {"label": "4.59", "tc": "00:02:35.3252", "tclevel": 1}, {"label": "2.939", "tc": "00:02:35.4921", "tclevel": 1}, {"label": "3.244", "tc": "00:02:35.6589", "tclevel": 1}, {"label": "0.542", "tc": "00:02:35.8257", "tclevel": 1}, {"label": "4.123", "tc": "00:02:35.9926", "tclevel": 1}, {"label": "1.163", "tc": "00:02:36.1594", "tclevel": 1}, {"label": "0.253", "tc": "00:02:36.3263", "tclevel": 1}, {"label": "1.173", "tc": "00:02:36.4931", "tclevel": 1}, {"label": "2.347", "tc": "00:02:36.6599", "tclevel": 1}, {"label": "4.51", "tc": "00:02:36.8268", "tclevel": 1}, {"label": "1.105", "tc": "00:02:36.9936", "tclevel": 1}, {"label": "1.865", "tc": "00:02:37.1604", "tclevel": 1}, {"label": "0.86", "tc": "00:02:37.3273", "tclevel": 1}, {"label": "2.338", "tc": "00:02:37.4941", "tclevel": 1}, {"label": "1.763", "tc": "00:02:37.6610", "tclevel": 1}, {"label": "4.703", "tc": "00:02:37.8278", "tclevel": 1}, {"label": "4.045", "tc": "00:02:37.9946", "tclevel": 1}, {"label": "2.866", "tc": "00:02:38.1615", "tclevel": 1}, {"label": "0.321", "tc": "00:02:38.3283", "tclevel": 1}, {"label": "1.479", "tc": "00:02:38.4951", "tclevel": 1}, {"label": "3.197", "tc": "00:02:38.6620", "tclevel": 1}, {"label": "4.691", "tc": "00:02:38.8288", "tclevel": 1}, {"label": "2.212", "tc": "00:02:38.9956", "tclevel": 1}, {"label": "4.206", "tc": "00:02:39.1625", "tclevel": 1}, {"label": "2.286", "tc": "00:02:39.3293", "tclevel": 1}, {"label": "3.721", "tc": "00:02:39.4962", "tclevel": 1}, {"label": "0.256", "tc": "00:02:39.6630", "tclevel": 1}, {"label": "2.269", "tc": "00:02:39.8298", "tclevel": 1}, {"label": "2.427", "tc": "00:02:39.9967", "tclevel": 1}, {"label": "4.798", "tc": "00:02:40.1635", "tclevel": 1}, {"label": "3.748", "tc": "00:02:40.3303", "tclevel": 1}, {"label": "0.161", "tc": "00:02:40.4972", "tclevel": 1}, {"label": "3.96", "tc": "00:02:40.6640", "tclevel": 1}, {"label": "3.362", "tc": "00:02:40.8309", "tclevel": 1}, {"label": "3.032", "tc": "00:02:40.9977", "tclevel": 1}, {"label": "2.096", "tc": "00:02:41.1645", "tclevel": 1}, {"label": "1.33", "tc": "00:02:41.3314", "tclevel": 1}, {"label": "0.276", "tc": "00:02:41.4982", "tclevel": 1}, {"label": "4.738", "tc": "00:02:41.6650", "tclevel": 1}, {"label": "4.245", "tc": "00:02:41.8319", "tclevel": 1}, {"label": "3.248", "tc": "00:02:41.9987", "tclevel": 1}, {"label": "2.425", "tc": "00:02:42.1656", "tclevel": 1}, {"label": "4.283", "tc": "00:02:42.3324", "tclevel": 1}, {"label": "4.657", "tc": "00:02:42.4992", "tclevel": 1}, {"label": "1.907", "tc": "00:02:42.6661", "tclevel": 1}, {"label": "0.988", "tc": "00:02:42.8329", "tclevel": 1}, {"label": "2.498", "tc": "00:02:42.9997", "tclevel": 1}, {"label": "4.92", "tc": "00:02:43.1666", "tclevel": 1}, {"label": "4.687", "tc": "00:02:43.3334", "tclevel": 1}, {"label": "1.137", "tc": "00:02:43.5002", "tclevel": 1}, {"label": "1.897", "tc": "00:02:43.6671", "tclevel": 1}, {"label": "0.258", "tc": "00:02:43.8339", "tclevel": 1}, {"label": "1.613", "tc": "00:02:44.0008", "tclevel": 1}, {"label": "2.867", "tc": "00:02:44.1676", "tclevel": 1}, {"label": "0.521", "tc": "00:02:44.3344", "tclevel": 1}, {"label": "2.534", "tc": "00:02:44.5013", "tclevel": 1}, {"label": "4.935", "tc": "00:02:44.6681", "tclevel": 1}, {"label": "3.014", "tc": "00:02:44.8349", "tclevel": 1}, {"label": "2.591", "tc": "00:02:45.0018", "tclevel": 1}, {"label": "4.445", "tc": "00:02:45.1686", "tclevel": 1}, {"label": "3.848", "tc": "00:02:45.3355", "tclevel": 1}, {"label": "0.855", "tc": "00:02:45.5023", "tclevel": 1}, {"label": "1.621", "tc": "00:02:45.6691", "tclevel": 1}, {"label": "1.454", "tc": "00:02:45.8360", "tclevel": 1}, {"label": "1.049", "tc": "00:02:46.0028", "tclevel": 1}, {"label": "1.913", "tc": "00:02:46.1696", "tclevel": 1}, {"label": "4.15", "tc": "00:02:46.3365", "tclevel": 1}, {"label": "0.157", "tc": "00:02:46.5033", "tclevel": 1}, {"label": "0.844", "tc": "00:02:46.6702", "tclevel": 1}, {"label": "3.539", "tc": "00:02:46.8370", "tclevel": 1}, {"label": "0.487", "tc": "00:02:47.0038", "tclevel": 1}, {"label": "3.689", "tc": "00:02:47.1707", "tclevel": 1}, {"label": "3.089", "tc": "00:02:47.3375", "tclevel": 1}, {"label": "0.345", "tc": "00:02:47.5043", "tclevel": 1}, {"label": "4.103", "tc": "00:02:47.6712", "tclevel": 1}, {"label": "1.478", "tc": "00:02:47.8380", "tclevel": 1}, {"label": "0.971", "tc": "00:02:48.0048", "tclevel": 1}, {"label": "3.024", "tc": "00:02:48.1717", "tclevel": 1}, {"label": "3.435", "tc": "00:02:48.3385", "tclevel": 1}, {"label": "2.009", "tc": "00:02:48.5054", "tclevel": 1}, {"label": "3.394", "tc": "00:02:48.6722", "tclevel": 1}, {"label": "1.112", "tc": "00:02:48.8390", "tclevel": 1}, {"label": "3.277", "tc": "00:02:49.0059", "tclevel": 1}, {"label": "1.92", "tc": "00:02:49.1727", "tclevel": 1}, {"label": "3.929", "tc": "00:02:49.3395", "tclevel": 1}, {"label": "3.359", "tc": "00:02:49.5064", "tclevel": 1}, {"label": "4.357", "tc": "00:02:49.6732", "tclevel": 1}, {"label": "1.361", "tc": "00:02:49.8401", "tclevel": 1}, {"label": "3.243", "tc": "00:02:50.0069", "tclevel": 1}, {"label": "1.827", "tc": "00:02:50.1737", "tclevel": 1}, {"label": "3.3", "tc": "00:02:50.3406", "tclevel": 1}, {"label": "1.573", "tc": "00:02:50.5074", "tclevel": 1}, {"label": "3.352", "tc": "00:02:50.6742", "tclevel": 1}, {"label": "3.64", "tc": "00:02:50.8411", "tclevel": 1}, {"label": "4.875", "tc": "00:02:51.0079", "tclevel": 1}, {"label": "2.623", "tc": "00:02:51.1747", "tclevel": 1}, {"label": "3.119", "tc": "00:02:51.3416", "tclevel": 1}, {"label": "2.592", "tc": "00:02:51.5084", "tclevel": 1}, {"label": "4.453", "tc": "00:02:51.6753", "tclevel": 1}, {"label": "0.458", "tc": "00:02:51.8421", "tclevel": 1}, {"label": "1.697", "tc": "00:02:52.0089", "tclevel": 1}, {"label": "4.353", "tc": "00:02:52.1758", "tclevel": 1}, {"label": "4.29", "tc": "00:02:52.3426", "tclevel": 1}, {"label": "2.9", "tc": "00:02:52.5094", "tclevel": 1}, {"label": "4.249", "tc": "00:02:52.6763", "tclevel": 1}, {"label": "1.48", "tc": "00:02:52.8431", "tclevel": 1}, {"label": "0.039", "tc": "00:02:53.0100", "tclevel": 1}, {"label": "4.727", "tc": "00:02:53.1768", "tclevel": 1}, {"label": "3.375", "tc": "00:02:53.3436", "tclevel": 1}, {"label": "1.177", "tc": "00:02:53.5105", "tclevel": 1}, {"label": "0.189", "tc": "00:02:53.6773", "tclevel": 1}, {"label": "3.751", "tc": "00:02:53.8441", "tclevel": 1}, {"label": "1.864", "tc": "00:02:54.0110", "tclevel": 1}, {"label": "4.627", "tc": "00:02:54.1778", "tclevel": 1}, {"label": "1.28", "tc": "00:02:54.3447", "tclevel": 1}, {"label": "2.526", "tc": "00:02:54.5115", "tclevel": 1}, {"label": "1.036", "tc": "00:02:54.6783", "tclevel": 1}, {"label": "0.928", "tc": "00:02:54.8452", "tclevel": 1}, {"label": "4.991", "tc": "00:02:55.0120", "tclevel": 1}, {"label": "3.148", "tc": "00:02:55.1788", "tclevel": 1}, {"label": "3.864", "tc": "00:02:55.3457", "tclevel": 1}, {"label": "4.286", "tc": "00:02:55.5125", "tclevel": 1}, {"label": "1.61", "tc": "00:02:55.6793", "tclevel": 1}, {"label": "0.171", "tc": "00:02:55.8462", "tclevel": 1}, {"label": "0.314", "tc": "00:02:56.0130", "tclevel": 1}, {"label": "1.239", "tc": "00:02:56.1799", "tclevel": 1}, {"label": "1.559", "tc": "00:02:56.3467", "tclevel": 1}, {"label": "1.393", "tc": "00:02:56.5135", "tclevel": 1}, {"label": "3.709", "tc": "00:02:56.6804", "tclevel": 1}, {"label": "0.562", "tc": "00:02:56.8472", "tclevel": 1}, {"label": "3.549", "tc": "00:02:57.0140", "tclevel": 1}, {"label": "1.778", "tc": "00:02:57.1809", "tclevel": 1}, {"label": "1.234", "tc": "00:02:57.3477", "tclevel": 1}, {"label": "3.683", "tc": "00:02:57.5146", "tclevel": 1}, {"label": "4.847", "tc": "00:02:57.6814", "tclevel": 1}, {"label": "4.669", "tc": "00:02:57.8482", "tclevel": 1}, {"label": "4.529", "tc": "00:02:58.0151", "tclevel": 1}, {"label": "3.845", "tc": "00:02:58.1819", "tclevel": 1}, {"label": "3.726", "tc": "00:02:58.3487", "tclevel": 1}, {"label": "1.721", "tc": "00:02:58.5156", "tclevel": 1}, {"label": "3.935", "tc": "00:02:58.6824", "tclevel": 1}, {"label": "3.454", "tc": "00:02:58.8493", "tclevel": 1}, {"label": "1.94", "tc": "00:02:59.0161", "tclevel": 1}, {"label": "4.801", "tc": "00:02:59.1829", "tclevel": 1}, {"label": "3.056", "tc": "00:02:59.3498", "tclevel": 1}, {"label": "1.168", "tc": "00:02:59.5166", "tclevel": 1}, {"label": "2.852", "tc": "00:02:59.6834", "tclevel": 1}, {"label": "1.284", "tc": "00:02:59.8503", "tclevel": 1}, {"label": "0.36", "tc": "00:03:00.0171", "tclevel": 1}, {"label": "4.733", "tc": "00:03:00.1839", "tclevel": 1}, {"label": "3.452", "tc": "00:03:00.3508", "tclevel": 1}, {"label": "2.215", "tc": "00:03:00.5176", "tclevel": 1}, {"label": "2.376", "tc": "00:03:00.6845", "tclevel": 1}, {"label": "4.942", "tc": "00:03:00.8513", "tclevel": 1}, {"label": "1.615", "tc": "00:03:01.0181", "tclevel": 1}, {"label": "3.81", "tc": "00:03:01.1850", "tclevel": 1}, {"label": "4.864", "tc": "00:03:01.3518", "tclevel": 1}, {"label": "3.337", "tc": "00:03:01.5186", "tclevel": 1}, {"label": "3.49", "tc": "00:03:01.6855", "tclevel": 1}, {"label": "0.061", "tc": "00:03:01.8523", "tclevel": 1}, {"label": "0.276", "tc": "00:03:02.0192", "tclevel": 1}, {"label": "1.709", "tc": "00:03:02.1860", "tclevel": 1}, {"label": "2.355", "tc": "00:03:02.3528", "tclevel": 1}, {"label": "1.037", "tc": "00:03:02.5197", "tclevel": 1}, {"label": "2.975", "tc": "00:03:02.6865", "tclevel": 1}, {"label": "0.664", "tc": "00:03:02.8533", "tclevel": 1}, {"label": "0.794", "tc": "00:03:03.0202", "tclevel": 1}, {"label": "3.052", "tc": "00:03:03.1870", "tclevel": 1}, {"label": "3.437", "tc": "00:03:03.3538", "tclevel": 1}, {"label": "1.366", "tc": "00:03:03.5207", "tclevel": 1}, {"label": "4.249", "tc": "00:03:03.6875", "tclevel": 1}, {"label": "0.032", "tc": "00:03:03.8544", "tclevel": 1}, {"label": "4.422", "tc": "00:03:04.0212", "tclevel": 1}, {"label": "1.411", "tc": "00:03:04.1880", "tclevel": 1}, {"label": "0.084", "tc": "00:03:04.3549", "tclevel": 1}, {"label": "1.803", "tc": "00:03:04.5217", "tclevel": 1}, {"label": "2.677", "tc": "00:03:04.6885", "tclevel": 1}, {"label": "4.611", "tc": "00:03:04.8554", "tclevel": 1}, {"label": "1.624", "tc": "00:03:05.0222", "tclevel": 1}, {"label": "0.893", "tc": "00:03:05.1891", "tclevel": 1}, {"label": "1.361", "tc": "00:03:05.3559", "tclevel": 1}, {"label": "2.667", "tc": "00:03:05.5227", "tclevel": 1}, {"label": "3.259", "tc": "00:03:05.6896", "tclevel": 1}, {"label": "4.713", "tc": "00:03:05.8564", "tclevel": 1}, {"label": "4.744", "tc": "00:03:06.0232", "tclevel": 1}, {"label": "2.02", "tc": "00:03:06.1901", "tclevel": 1}, {"label": "0.779", "tc": "00:03:06.3569", "tclevel": 1}, {"label": "0.188", "tc": "00:03:06.5238", "tclevel": 1}, {"label": "0.828", "tc": "00:03:06.6906", "tclevel": 1}, {"label": "4.585", "tc": "00:03:06.8574", "tclevel": 1}, {"label": "3.607", "tc": "00:03:07.0243", "tclevel": 1}, {"label": "1.605", "tc": "00:03:07.1911", "tclevel": 1}, {"label": "3.586", "tc": "00:03:07.3579", "tclevel": 1}, {"label": "0.424", "tc": "00:03:07.5248", "tclevel": 1}, {"label": "4.838", "tc": "00:03:07.6916", "tclevel": 1}, {"label": "1.023", "tc": "00:03:07.8584", "tclevel": 1}, {"label": "2.169", "tc": "00:03:08.0253", "tclevel": 1}, {"label": "3.062", "tc": "00:03:08.1921", "tclevel": 1}, {"label": "0.609", "tc": "00:03:08.3590", "tclevel": 1}, {"label": "2.284", "tc": "00:03:08.5258", "tclevel": 1}, {"label": "1.486", "tc": "00:03:08.6926", "tclevel": 1}, {"label": "0.589", "tc": "00:03:08.8595", "tclevel": 1}, {"label": "4.697", "tc": "00:03:09.0263", "tclevel": 1}, {"label": "4.246", "tc": "00:03:09.1931", "tclevel": 1}, {"label": "3.908", "tc": "00:03:09.3600", "tclevel": 1}, {"label": "3.408", "tc": "00:03:09.5268", "tclevel": 1}, {"label": "0.178", "tc": "00:03:09.6937", "tclevel": 1}, {"label": "0.959", "tc": "00:03:09.8605", "tclevel": 1}, {"label": "3.943", "tc": "00:03:10.0273", "tclevel": 1}, {"label": "1.926", "tc": "00:03:10.1942", "tclevel": 1}, {"label": "3.237", "tc": "00:03:10.3610", "tclevel": 1}, {"label": "3.121", "tc": "00:03:10.5278", "tclevel": 1}, {"label": "3.823", "tc": "00:03:10.6947", "tclevel": 1}, {"label": "2.136", "tc": "00:03:10.8615", "tclevel": 1}, {"label": "1.409", "tc": "00:03:11.0284", "tclevel": 1}, {"label": "2.246", "tc": "00:03:11.1952", "tclevel": 1}, {"label": "1.303", "tc": "00:03:11.3620", "tclevel": 1}, {"label": "0.596", "tc": "00:03:11.5289", "tclevel": 1}, {"label": "3.121", "tc": "00:03:11.6957", "tclevel": 1}, {"label": "4.374", "tc": "00:03:11.8625", "tclevel": 1}, {"label": "3.241", "tc": "00:03:12.0294", "tclevel": 1}, {"label": "0.905", "tc": "00:03:12.1962", "tclevel": 1}, {"label": "3.962", "tc": "00:03:12.3630", "tclevel": 1}, {"label": "4.91", "tc": "00:03:12.5299", "tclevel": 1}, {"label": "2.0", "tc": "00:03:12.6967", "tclevel": 1}, {"label": "3.299", "tc": "00:03:12.8636", "tclevel": 1}, {"label": "0.226", "tc": "00:03:13.0304", "tclevel": 1}, {"label": "0.721", "tc": "00:03:13.1972", "tclevel": 1}, {"label": "0.739", "tc": "00:03:13.3641", "tclevel": 1}, {"label": "3.035", "tc": "00:03:13.5309", "tclevel": 1}, {"label": "3.62", "tc": "00:03:13.6977", "tclevel": 1}, {"label": "0.231", "tc": "00:03:13.8646", "tclevel": 1}, {"label": "2.042", "tc": "00:03:14.0314", "tclevel": 1}, {"label": "4.379", "tc": "00:03:14.1983", "tclevel": 1}, {"label": "4.868", "tc": "00:03:14.3651", "tclevel": 1}, {"label": "1.624", "tc": "00:03:14.5319", "tclevel": 1}, {"label": "4.147", "tc": "00:03:14.6988", "tclevel": 1}, {"label": "3.353", "tc": "00:03:14.8656", "tclevel": 1}, {"label": "1.351", "tc": "00:03:15.0324", "tclevel": 1}, {"label": "4.015", "tc": "00:03:15.1993", "tclevel": 1}, {"label": "1.687", "tc": "00:03:15.3661", "tclevel": 1}, {"label": "4.66", "tc": "00:03:15.5329", "tclevel": 1}, {"label": "4.786", "tc": "00:03:15.6998", "tclevel": 1}, {"label": "1.649", "tc": "00:03:15.8666", "tclevel": 1}, {"label": "3.115", "tc": "00:03:16.0335", "tclevel": 1}, {"label": "2.325", "tc": "00:03:16.2003", "tclevel": 1}, {"label": "1.369", "tc": "00:03:16.3671", "tclevel": 1}, {"label": "1.05", "tc": "00:03:16.5340", "tclevel": 1}, {"label": "4.79", "tc": "00:03:16.7008", "tclevel": 1}, {"label": "1.652", "tc": "00:03:16.8676", "tclevel": 1}, {"label": "4.132", "tc": "00:03:17.0345", "tclevel": 1}, {"label": "0.716", "tc": "00:03:17.2013", "tclevel": 1}, {"label": "0.731", "tc": "00:03:17.3682", "tclevel": 1}, {"label": "3.093", "tc": "00:03:17.5350", "tclevel": 1}, {"label": "4.24", "tc": "00:03:17.7018", "tclevel": 1}, {"label": "4.895", "tc": "00:03:17.8687", "tclevel": 1}, {"label": "3.079", "tc": "00:03:18.0355", "tclevel": 1}, {"label": "1.326", "tc": "00:03:18.2023", "tclevel": 1}, {"label": "3.588", "tc": "00:03:18.3692", "tclevel": 1}, {"label": "4.483", "tc": "00:03:18.5360", "tclevel": 1}, {"label": "2.255", "tc": "00:03:18.7029", "tclevel": 1}, {"label": "4.563", "tc": "00:03:18.8697", "tclevel": 1}, {"label": "1.19", "tc": "00:03:19.0365", "tclevel": 1}, {"label": "4.251", "tc": "00:03:19.2034", "tclevel": 1}, {"label": "3.624", "tc": "00:03:19.3702", "tclevel": 1}, {"label": "3.36", "tc": "00:03:19.5370", "tclevel": 1}, {"label": "4.12", "tc": "00:03:19.7039", "tclevel": 1}, {"label": "1.384", "tc": "00:03:19.8707", "tclevel": 1}, {"label": "2.556", "tc": "00:03:20.0375", "tclevel": 1}, {"label": "2.795", "tc": "00:03:20.2044", "tclevel": 1}, {"label": "4.793", "tc": "00:03:20.3712", "tclevel": 1}, {"label": "1.592", "tc": "00:03:20.5381", "tclevel": 1}, {"label": "0.356", "tc": "00:03:20.7049", "tclevel": 1}, {"label": "3.851", "tc": "00:03:20.8717", "tclevel": 1}, {"label": "1.879", "tc": "00:03:21.0386", "tclevel": 1}, {"label": "4.272", "tc": "00:03:21.2054", "tclevel": 1}, {"label": "1.725", "tc": "00:03:21.3722", "tclevel": 1}, {"label": "0.335", "tc": "00:03:21.5391", "tclevel": 1}, {"label": "4.731", "tc": "00:03:21.7059", "tclevel": 1}, {"label": "4.784", "tc": "00:03:21.8728", "tclevel": 1}, {"label": "2.071", "tc": "00:03:22.0396", "tclevel": 1}, {"label": "2.527", "tc": "00:03:22.2064", "tclevel": 1}, {"label": "3.662", "tc": "00:03:22.3733", "tclevel": 1}, {"label": "4.332", "tc": "00:03:22.5401", "tclevel": 1}, {"label": "4.373", "tc": "00:03:22.7069", "tclevel": 1}, {"label": "2.721", "tc": "00:03:22.8738", "tclevel": 1}, {"label": "0.348", "tc": "00:03:23.0406", "tclevel": 1}, {"label": "1.45", "tc": "00:03:23.2075", "tclevel": 1}, {"label": "4.492", "tc": "00:03:23.3743", "tclevel": 1}, {"label": "1.342", "tc": "00:03:23.5411", "tclevel": 1}, {"label": "3.5", "tc": "00:03:23.7080", "tclevel": 1}, {"label": "3.882", "tc": "00:03:23.8748", "tclevel": 1}, {"label": "0.433", "tc": "00:03:24.0416", "tclevel": 1}, {"label": "3.565", "tc": "00:03:24.2085", "tclevel": 1}, {"label": "1.343", "tc": "00:03:24.3753", "tclevel": 1}, {"label": "0.194", "tc": "00:03:24.5421", "tclevel": 1}, {"label": "4.519", "tc": "00:03:24.7090", "tclevel": 1}, {"label": "4.941", "tc": "00:03:24.8758", "tclevel": 1}, {"label": "3.344", "tc": "00:03:25.0427", "tclevel": 1}, {"label": "1.324", "tc": "00:03:25.2095", "tclevel": 1}, {"label": "1.185", "tc": "00:03:25.3763", "tclevel": 1}, {"label": "2.147", "tc": "00:03:25.5432", "tclevel": 1}, {"label": "4.849", "tc": "00:03:25.7100", "tclevel": 1}, {"label": "2.455", "tc": "00:03:25.8768", "tclevel": 1}, {"label": "4.846", "tc": "00:03:26.0437", "tclevel": 1}, {"label": "2.832", "tc": "00:03:26.2105", "tclevel": 1}, {"label": "4.705", "tc": "00:03:26.3774", "tclevel": 1}, {"label": "3.811", "tc": "00:03:26.5442", "tclevel": 1}, {"label": "2.627", "tc": "00:03:26.7110", "tclevel": 1}, {"label": "0.043", "tc": "00:03:26.8779", "tclevel": 1}, {"label": "1.158", "tc": "00:03:27.0447", "tclevel": 1}, {"label": "4.32", "tc": "00:03:27.2115", "tclevel": 1}, {"label": "2.058", "tc": "00:03:27.3784", "tclevel": 1}, {"label": "1.01", "tc": "00:03:27.5452", "tclevel": 1}, {"label": "1.174", "tc": "00:03:27.7120", "tclevel": 1}, {"label": "3.573", "tc": "00:03:27.8789", "tclevel": 1}, {"label": "3.225", "tc": "00:03:28.0457", "tclevel": 1}, {"label": "3.484", "tc": "00:03:28.2126", "tclevel": 1}, {"label": "4.45", "tc": "00:03:28.3794", "tclevel": 1}, {"label": "1.128", "tc": "00:03:28.5462", "tclevel": 1}, {"label": "3.548", "tc": "00:03:28.7131", "tclevel": 1}, {"label": "1.093", "tc": "00:03:28.8799", "tclevel": 1}, {"label": "4.224", "tc": "00:03:29.0467", "tclevel": 1}, {"label": "2.144", "tc": "00:03:29.2136", "tclevel": 1}, {"label": "1.511", "tc": "00:03:29.3804", "tclevel": 1}, {"label": "0.126", "tc": "00:03:29.5473", "tclevel": 1}, {"label": "3.197", "tc": "00:03:29.7141", "tclevel": 1}, {"label": "0.123", "tc": "00:03:29.8809", "tclevel": 1}, {"label": "4.382", "tc": "00:03:30.0478", "tclevel": 1}, {"label": "4.049", "tc": "00:03:30.2146", "tclevel": 1}, {"label": "4.097", "tc": "00:03:30.3814", "tclevel": 1}, {"label": "2.425", "tc": "00:03:30.5483", "tclevel": 1}, {"label": "2.628", "tc": "00:03:30.7151", "tclevel": 1}, {"label": "4.585", "tc": "00:03:30.8820", "tclevel": 1}, {"label": "2.739", "tc": "00:03:31.0488", "tclevel": 1}, {"label": "1.148", "tc": "00:03:31.2156", "tclevel": 1}, {"label": "3.297", "tc": "00:03:31.3825", "tclevel": 1}, {"label": "0.643", "tc": "00:03:31.5493", "tclevel": 1}, {"label": "1.819", "tc": "00:03:31.7161", "tclevel": 1}, {"label": "0.73", "tc": "00:03:31.8830", "tclevel": 1}, {"label": "2.228", "tc": "00:03:32.0498", "tclevel": 1}, {"label": "4.534", "tc": "00:03:32.2166", "tclevel": 1}, {"label": "0.666", "tc": "00:03:32.3835", "tclevel": 1}, {"label": "3.261", "tc": "00:03:32.5503", "tclevel": 1}, {"label": "0.155", "tc": "00:03:32.7172", "tclevel": 1}, {"label": "0.299", "tc": "00:03:32.8840", "tclevel": 1}, {"label": "4.992", "tc": "00:03:33.0508", "tclevel": 1}, {"label": "4.072", "tc": "00:03:33.2177", "tclevel": 1}, {"label": "3.354", "tc": "00:03:33.3845", "tclevel": 1}, {"label": "4.803", "tc": "00:03:33.5513", "tclevel": 1}, {"label": "1.603", "tc": "00:03:33.7182", "tclevel": 1}, {"label": "3.215", "tc": "00:03:33.8850", "tclevel": 1}, {"label": "4.762", "tc": "00:03:34.0519", "tclevel": 1}, {"label": "0.654", "tc": "00:03:34.2187", "tclevel": 1}, {"label": "1.592", "tc": "00:03:34.3855", "tclevel": 1}, {"label": "4.252", "tc": "00:03:34.5524", "tclevel": 1}, {"label": "0.301", "tc": "00:03:34.7192", "tclevel": 1}, {"label": "2.031", "tc": "00:03:34.8860", "tclevel": 1}, {"label": "4.026", "tc": "00:03:35.0529", "tclevel": 1}, {"label": "0.026", "tc": "00:03:35.2197", "tclevel": 1}, {"label": "2.985", "tc": "00:03:35.3866", "tclevel": 1}, {"label": "0.103", "tc": "00:03:35.5534", "tclevel": 1}, {"label": "0.361", "tc": "00:03:35.7202", "tclevel": 1}, {"label": "0.766", "tc": "00:03:35.8871", "tclevel": 1}, {"label": "4.275", "tc": "00:03:36.0539", "tclevel": 1}, {"label": "2.377", "tc": "00:03:36.2207", "tclevel": 1}, {"label": "4.538", "tc": "00:03:36.3876", "tclevel": 1}, {"label": "2.299", "tc": "00:03:36.5544", "tclevel": 1}, {"label": "2.702", "tc": "00:03:36.7212", "tclevel": 1}, {"label": "2.673", "tc": "00:03:36.8881", "tclevel": 1}, {"label": "4.378", "tc": "00:03:37.0549", "tclevel": 1}, {"label": "1.521", "tc": "00:03:37.2218", "tclevel": 1}, {"label": "2.612", "tc": "00:03:37.3886", "tclevel": 1}, {"label": "4.292", "tc": "00:03:37.5554", "tclevel": 1}, {"label": "0.297", "tc": "00:03:37.7223", "tclevel": 1}, {"label": "4.509", "tc": "00:03:37.8891", "tclevel": 1}, {"label": "4.184", "tc": "00:03:38.0559", "tclevel": 1}, {"label": "1.627", "tc": "00:03:38.2228", "tclevel": 1}, {"label": "1.457", "tc": "00:03:38.3896", "tclevel": 1}, {"label": "4.519", "tc": "00:03:38.5565", "tclevel": 1}, {"label": "2.565", "tc": "00:03:38.7233", "tclevel": 1}, {"label": "3.055", "tc": "00:03:38.8901", "tclevel": 1}, {"label": "3.181", "tc": "00:03:39.0570", "tclevel": 1}, {"label": "2.412", "tc": "00:03:39.2238", "tclevel": 1}, {"label": "2.809", "tc": "00:03:39.3906", "tclevel": 1}, {"label": "4.858", "tc": "00:03:39.5575", "tclevel": 1}, {"label": "4.282", "tc": "00:03:39.7243", "tclevel": 1}, {"label": "3.302", "tc": "00:03:39.8911", "tclevel": 1}, {"label": "4.897", "tc": "00:03:40.0580", "tclevel": 1}, {"label": "1.571", "tc": "00:03:40.2248", "tclevel": 1}, {"label": "4.542", "tc": "00:03:40.3917", "tclevel": 1}, {"label": "4.927", "tc": "00:03:40.5585", "tclevel": 1}, {"label": "2.203", "tc": "00:03:40.7253", "tclevel": 1}, {"label": "2.001", "tc": "00:03:40.8922", "tclevel": 1}, {"label": "3.197", "tc": "00:03:41.0590", "tclevel": 1}, {"label": "2.439", "tc": "00:03:41.2258", "tclevel": 1}, {"label": "4.604", "tc": "00:03:41.3927", "tclevel": 1}, {"label": "2.772", "tc": "00:03:41.5595", "tclevel": 1}, {"label": "1.475", "tc": "00:03:41.7264", "tclevel": 1}, {"label": "3.878", "tc": "00:03:41.8932", "tclevel": 1}, {"label": "0.13", "tc": "00:03:42.0600", "tclevel": 1}, {"label": "0.809", "tc": "00:03:42.2269", "tclevel": 1}, {"label": "4.999", "tc": "00:03:42.3937", "tclevel": 1}, {"label": "2.421", "tc": "00:03:42.5605", "tclevel": 1}, {"label": "2.401", "tc": "00:03:42.7274", "tclevel": 1}, {"label": "4.128", "tc": "00:03:42.8942", "tclevel": 1}, {"label": "2.082", "tc": "00:03:43.0611", "tclevel": 1}, {"label": "2.968", "tc": "00:03:43.2279", "tclevel": 1}, {"label": "2.551", "tc": "00:03:43.3947", "tclevel": 1}, {"label": "0.736", "tc": "00:03:43.5616", "tclevel": 1}, {"label": "3.489", "tc": "00:03:43.7284", "tclevel": 1}, {"label": "4.22", "tc": "00:03:43.8952", "tclevel": 1}, {"label": "3.25", "tc": "00:03:44.0621", "tclevel": 1}, {"label": "0.879", "tc": "00:03:44.2289", "tclevel": 1}, {"label": "0.95", "tc": "00:03:44.3957", "tclevel": 1}, {"label": "1.147", "tc": "00:03:44.5626", "tclevel": 1}, {"label": "3.299", "tc": "00:03:44.7294", "tclevel": 1}, {"label": "3.931", "tc": "00:03:44.8963", "tclevel": 1}, {"label": "2.94", "tc": "00:03:45.0631", "tclevel": 1}, {"label": "1.279", "tc": "00:03:45.2299", "tclevel": 1}, {"label": "0.76", "tc": "00:03:45.3968", "tclevel": 1}, {"label": "2.72", "tc": "00:03:45.5636", "tclevel": 1}, {"label": "2.801", "tc": "00:03:45.7304", "tclevel": 1}, {"label": "1.466", "tc": "00:03:45.8973", "tclevel": 1}, {"label": "3.64", "tc": "00:03:46.0641", "tclevel": 1}, {"label": "2.784", "tc": "00:03:46.2310", "tclevel": 1}, {"label": "0.129", "tc": "00:03:46.3978", "tclevel": 1}, {"label": "1.432", "tc": "00:03:46.5646", "tclevel": 1}, {"label": "0.614", "tc": "00:03:46.7315", "tclevel": 1}, {"label": "2.309", "tc": "00:03:46.8983", "tclevel": 1}, {"label": "3.942", "tc": "00:03:47.0651", "tclevel": 1}, {"label": "2.579", "tc": "00:03:47.2320", "tclevel": 1}, {"label": "4.595", "tc": "00:03:47.3988", "tclevel": 1}, {"label": "2.23", "tc": "00:03:47.5657", "tclevel": 1}, {"label": "0.354", "tc": "00:03:47.7325", "tclevel": 1}, {"label": "2.708", "tc": "00:03:47.8993", "tclevel": 1}, {"label": "4.546", "tc": "00:03:48.0662", "tclevel": 1}, {"label": "4.834", "tc": "00:03:48.2330", "tclevel": 1}, {"label": "3.81", "tc": "00:03:48.3998", "tclevel": 1}, {"label": "0.413", "tc": "00:03:48.5667", "tclevel": 1}, {"label": "2.665", "tc": "00:03:48.7335", "tclevel": 1}, {"label": "2.01", "tc": "00:03:48.9003", "tclevel": 1}, {"label": "4.09", "tc": "00:03:49.0672", "tclevel": 1}, {"label": "3.335", "tc": "00:03:49.2340", "tclevel": 1}, {"label": "2.791", "tc": "00:03:49.4009", "tclevel": 1}, {"label": "0.627", "tc": "00:03:49.5677", "tclevel": 1}, {"label": "4.855", "tc": "00:03:49.7345", "tclevel": 1}, {"label": "0.984", "tc": "00:03:49.9014", "tclevel": 1}, {"label": "2.242", "tc": "00:03:50.0682", "tclevel": 1}, {"label": "1.082", "tc": "00:03:50.2350", "tclevel": 1}, {"label": "4.339", "tc": "00:03:50.4019", "tclevel": 1}, {"label": "0.783", "tc": "00:03:50.5687", "tclevel": 1}, {"label": "2.107", "tc": "00:03:50.7356", "tclevel": 1}, {"label": "3.761", "tc": "00:03:50.9024", "tclevel": 1}, {"label": "3.527", "tc": "00:03:51.0692", "tclevel": 1}, {"label": "3.605", "tc": "00:03:51.2361", "tclevel": 1}, {"label": "3.049", "tc": "00:03:51.4029", "tclevel": 1}, {"label": "0.082", "tc": "00:03:51.5697", "tclevel": 1}, {"label": "1.169", "tc": "00:03:51.7366", "tclevel": 1}, {"label": "4.971", "tc": "00:03:51.9034", "tclevel": 1}, {"label": "2.442", "tc": "00:03:52.0702", "tclevel": 1}, {"label": "0.163", "tc": "00:03:52.2371", "tclevel": 1}, {"label": "0.406", "tc": "00:03:52.4039", "tclevel": 1}, {"label": "2.253", "tc": "00:03:52.5708", "tclevel": 1}, {"label": "2.43", "tc": "00:03:52.7376", "tclevel": 1}, {"label": "4.321", "tc": "00:03:52.9044", "tclevel": 1}, {"label": "1.32", "tc": "00:03:53.0713", "tclevel": 1}, {"label": "3.907", "tc": "00:03:53.2381", "tclevel": 1}, {"label": "2.308", "tc": "00:03:53.4049", "tclevel": 1}, {"label": "2.571", "tc": "00:03:53.5718", "tclevel": 1}, {"label": "3.185", "tc": "00:03:53.7386", "tclevel": 1}, {"label": "3.709", "tc": "00:03:53.9055", "tclevel": 1}, {"label": "2.22", "tc": "00:03:54.0723", "tclevel": 1}, {"label": "2.936", "tc": "00:03:54.2391", "tclevel": 1}, {"label": "1.359", "tc": "00:03:54.4060", "tclevel": 1}, {"label": "3.396", "tc": "00:03:54.5728", "tclevel": 1}, {"label": "4.069", "tc": "00:03:54.7396", "tclevel": 1}, {"label": "3.304", "tc": "00:03:54.9065", "tclevel": 1}, {"label": "0.895", "tc": "00:03:55.0733", "tclevel": 1}, {"label": "3.507", "tc": "00:03:55.2402", "tclevel": 1}, {"label": "2.719", "tc": "00:03:55.4070", "tclevel": 1}, {"label": "1.597", "tc": "00:03:55.5738", "tclevel": 1}, {"label": "3.192", "tc": "00:03:55.7407", "tclevel": 1}, {"label": "1.718", "tc": "00:03:55.9075", "tclevel": 1}, {"label": "0.536", "tc": "00:03:56.0743", "tclevel": 1}, {"label": "4.353", "tc": "00:03:56.2412", "tclevel": 1}, {"label": "2.925", "tc": "00:03:56.4080", "tclevel": 1}, {"label": "3.528", "tc": "00:03:56.5748", "tclevel": 1}, {"label": "0.344", "tc": "00:03:56.7417", "tclevel": 1}, {"label": "4.019", "tc": "00:03:56.9085", "tclevel": 1}, {"label": "3.159", "tc": "00:03:57.0754", "tclevel": 1}, {"label": "3.375", "tc": "00:03:57.2422", "tclevel": 1}, {"label": "1.76", "tc": "00:03:57.4090", "tclevel": 1}, {"label": "2.332", "tc": "00:03:57.5759", "tclevel": 1}, {"label": "4.567", "tc": "00:03:57.7427", "tclevel": 1}, {"label": "2.62", "tc": "00:03:57.9095", "tclevel": 1}, {"label": "1.507", "tc": "00:03:58.0764", "tclevel": 1}, {"label": "3.645", "tc": "00:03:58.2432", "tclevel": 1}, {"label": "3.368", "tc": "00:03:58.4101", "tclevel": 1}, {"label": "2.317", "tc": "00:03:58.5769", "tclevel": 1}, {"label": "3.476", "tc": "00:03:58.7437", "tclevel": 1}, {"label": "4.113", "tc": "00:03:58.9106", "tclevel": 1}, {"label": "2.559", "tc": "00:03:59.0774", "tclevel": 1}, {"label": "2.819", "tc": "00:03:59.2442", "tclevel": 1}, {"label": "0.382", "tc": "00:03:59.4111", "tclevel": 1}, {"label": "3.692", "tc": "00:03:59.5779", "tclevel": 1}, {"label": "1.25", "tc": "00:03:59.7448", "tclevel": 1}, {"label": "4.284", "tc": "00:03:59.9116", "tclevel": 1}, {"label": "0.474", "tc": "00:04:00.0784", "tclevel": 1}, {"label": "2.163", "tc": "00:04:00.2453", "tclevel": 1}, {"label": "1.021", "tc": "00:04:00.4121", "tclevel": 1}, {"label": "0.327", "tc": "00:04:00.5789", "tclevel": 1}, {"label": "2.992", "tc": "00:04:00.7458", "tclevel": 1}, {"label": "4.217", "tc": "00:04:00.9126", "tclevel": 1}, {"label": "1.913", "tc": "00:04:01.0794", "tclevel": 1}, {"label": "3.898", "tc": "00:04:01.2463", "tclevel": 1}, {"label": "0.505", "tc": "00:04:01.4131", "tclevel": 1}, {"label": "1.67", "tc": "00:04:01.5800", "tclevel": 1}, {"label": "2.947", "tc": "00:04:01.7468", "tclevel": 1}, {"label": "2.742", "tc": "00:04:01.9136", "tclevel": 1}, {"label": "3.308", "tc": "00:04:02.0805", "tclevel": 1}, {"label": "4.158", "tc": "00:04:02.2473", "tclevel": 1}, {"label": "2.781", "tc": "00:04:02.4141", "tclevel": 1}, {"label": "3.824", "tc": "00:04:02.5810", "tclevel": 1}, {"label": "1.159", "tc": "00:04:02.7478", "tclevel": 1}, {"label": "0.852", "tc": "00:04:02.9147", "tclevel": 1}, {"label": "4.748", "tc": "00:04:03.0815", "tclevel": 1}, {"label": "4.607", "tc": "00:04:03.2483", "tclevel": 1}, {"label": "3.608", "tc": "00:04:03.4152", "tclevel": 1}, {"label": "1.252", "tc": "00:04:03.5820", "tclevel": 1}, {"label": "1.385", "tc": "00:04:03.7488", "tclevel": 1}, {"label": "4.931", "tc": "00:04:03.9157", "tclevel": 1}, {"label": "3.696", "tc": "00:04:04.0825", "tclevel": 1}, {"label": "2.244", "tc": "00:04:04.2493", "tclevel": 1}, {"label": "2.055", "tc": "00:04:04.4162", "tclevel": 1}, {"label": "0.547", "tc": "00:04:04.5830", "tclevel": 1}, {"label": "2.339", "tc": "00:04:04.7499", "tclevel": 1}, {"label": "0.064", "tc": "00:04:04.9167", "tclevel": 1}, {"label": "0.217", "tc": "00:04:05.0835", "tclevel": 1}, {"label": "1.26", "tc": "00:04:05.2504", "tclevel": 1}, {"label": "3.177", "tc": "00:04:05.4172", "tclevel": 1}, {"label": "3.341", "tc": "00:04:05.5840", "tclevel": 1}, {"label": "0.8", "tc": "00:04:05.7509", "tclevel": 1}, {"label": "0.501", "tc": "00:04:05.9177", "tclevel": 1}, {"label": "0.277", "tc": "00:04:06.0846", "tclevel": 1}, {"label": "2.949", "tc": "00:04:06.2514", "tclevel": 1}, {"label": "3.213", "tc": "00:04:06.4182", "tclevel": 1}, {"label": "1.436", "tc": "00:04:06.5851", "tclevel": 1}, {"label": "0.539", "tc": "00:04:06.7519", "tclevel": 1}, {"label": "0.119", "tc": "00:04:06.9187", "tclevel": 1}, {"label": "4.55", "tc": "00:04:07.0856", "tclevel": 1}, {"label": "3.199", "tc": "00:04:07.2524", "tclevel": 1}, {"label": "3.265", "tc": "00:04:07.4193", "tclevel": 1}, {"label": "3.805", "tc": "00:04:07.5861", "tclevel": 1}, {"label": "1.297", "tc": "00:04:07.7529", "tclevel": 1}, {"label": "1.665", "tc": "00:04:07.9198", "tclevel": 1}, {"label": "0.805", "tc": "00:04:08.0866", "tclevel": 1}, {"label": "1.43", "tc": "00:04:08.2534", "tclevel": 1}, {"label": "2.584", "tc": "00:04:08.4203", "tclevel": 1}, {"label": "0.455", "tc": "00:04:08.5871", "tclevel": 1}, {"label": "1.683", "tc": "00:04:08.7539", "tclevel": 1}, {"label": "2.537", "tc": "00:04:08.9208", "tclevel": 1}, {"label": "4.293", "tc": "00:04:09.0876", "tclevel": 1}, {"label": "4.964", "tc": "00:04:09.2545", "tclevel": 1}, {"label": "1.48", "tc": "00:04:09.4213", "tclevel": 1}, {"label": "1.668", "tc": "00:04:09.5881", "tclevel": 1}, {"label": "4.414", "tc": "00:04:09.7550", "tclevel": 1}, {"label": "3.183", "tc": "00:04:09.9218", "tclevel": 1}, {"label": "2.076", "tc": "00:04:10.0886", "tclevel": 1}, {"label": "0.58", "tc": "00:04:10.2555", "tclevel": 1}, {"label": "2.439", "tc": "00:04:10.4223", "tclevel": 1}, {"label": "0.235", "tc": "00:04:10.5892", "tclevel": 1}, {"label": "0.041", "tc": "00:04:10.7560", "tclevel": 1}, {"label": "2.136", "tc": "00:04:10.9228", "tclevel": 1}, {"label": "0.013", "tc": "00:04:11.0897", "tclevel": 1}, {"label": "4.335", "tc": "00:04:11.2565", "tclevel": 1}, {"label": "1.78", "tc": "00:04:11.4233", "tclevel": 1}, {"label": "4.6", "tc": "00:04:11.5902", "tclevel": 1}, {"label": "2.336", "tc": "00:04:11.7570", "tclevel": 1}, {"label": "2.425", "tc": "00:04:11.9239", "tclevel": 1}, {"label": "1.794", "tc": "00:04:12.0907", "tclevel": 1}, {"label": "2.246", "tc": "00:04:12.2575", "tclevel": 1}, {"label": "2.209", "tc": "00:04:12.4244", "tclevel": 1}, {"label": "0.286", "tc": "00:04:12.5912", "tclevel": 1}, {"label": "0.897", "tc": "00:04:12.7580", "tclevel": 1}, {"label": "3.418", "tc": "00:04:12.9249", "tclevel": 1}, {"label": "0.965", "tc": "00:04:13.0917", "tclevel": 1}, {"label": "2.489", "tc": "00:04:13.2585", "tclevel": 1}, {"label": "3.205", "tc": "00:04:13.4254", "tclevel": 1}, {"label": "1.316", "tc": "00:04:13.5922", "tclevel": 1}, {"label": "0.736", "tc": "00:04:13.7591", "tclevel": 1}, {"label": "4.174", "tc": "00:04:13.9259", "tclevel": 1}, {"label": "2.836", "tc": "00:04:14.0927", "tclevel": 1}, {"label": "3.271", "tc": "00:04:14.2596", "tclevel": 1}, {"label": "2.0", "tc": "00:04:14.4264", "tclevel": 1}, {"label": "1.631", "tc": "00:04:14.5932", "tclevel": 1}, {"label": "3.179", "tc": "00:04:14.7601", "tclevel": 1}, {"label": "0.116", "tc": "00:04:14.9269", "tclevel": 1}, {"label": "0.189", "tc": "00:04:15.0938", "tclevel": 1}, {"label": "1.033", "tc": "00:04:15.2606", "tclevel": 1}, {"label": "4.479", "tc": "00:04:15.4274", "tclevel": 1}, {"label": "3.683", "tc": "00:04:15.5943", "tclevel": 1}, {"label": "0.478", "tc": "00:04:15.7611", "tclevel": 1}, {"label": "4.264", "tc": "00:04:15.9279", "tclevel": 1}, {"label": "2.587", "tc": "00:04:16.0948", "tclevel": 1}, {"label": "4.472", "tc": "00:04:16.2616", "tclevel": 1}, {"label": "3.372", "tc": "00:04:16.4284", "tclevel": 1}, {"label": "1.035", "tc": "00:04:16.5953", "tclevel": 1}, {"label": "0.382", "tc": "00:04:16.7621", "tclevel": 1}, {"label": "4.793", "tc": "00:04:16.9290", "tclevel": 1}, {"label": "4.962", "tc": "00:04:17.0958", "tclevel": 1}, {"label": "1.281", "tc": "00:04:17.2626", "tclevel": 1}, {"label": "3.182", "tc": "00:04:17.4295", "tclevel": 1}, {"label": "0.819", "tc": "00:04:17.5963", "tclevel": 1}, {"label": "0.779", "tc": "00:04:17.7631", "tclevel": 1}, {"label": "0.399", "tc": "00:04:17.9300", "tclevel": 1}, {"label": "0.316", "tc": "00:04:18.0968", "tclevel": 1}, {"label": "0.379", "tc": "00:04:18.2637", "tclevel": 1}, {"label": "3.118", "tc": "00:04:18.4305", "tclevel": 1}, {"label": "0.76", "tc": "00:04:18.5973", "tclevel": 1}, {"label": "3.165", "tc": "00:04:18.7642", "tclevel": 1}, {"label": "0.581", "tc": "00:04:18.9310", "tclevel": 1}, {"label": "3.447", "tc": "00:04:19.0978", "tclevel": 1}, {"label": "3.774", "tc": "00:04:19.2647", "tclevel": 1}, {"label": "4.729", "tc": "00:04:19.4315", "tclevel": 1}, {"label": "0.677", "tc": "00:04:19.5984", "tclevel": 1}, {"label": "4.93", "tc": "00:04:19.7652", "tclevel": 1}, {"label": "2.477", "tc": "00:04:19.9320", "tclevel": 1}, {"label": "0.608", "tc": "00:04:20.0989", "tclevel": 1}, {"label": "0.205", "tc": "00:04:20.2657", "tclevel": 1}, {"label": "3.894", "tc": "00:04:20.4325", "tclevel": 1}, {"label": "3.461", "tc": "00:04:20.5994", "tclevel": 1}, {"label": "2.462", "tc": "00:04:20.7662", "tclevel": 1}, {"label": "2.048", "tc": "00:04:20.9330", "tclevel": 1}, {"label": "2.753", "tc": "00:04:21.0999", "tclevel": 1}, {"label": "4.465", "tc": "00:04:21.2667", "tclevel": 1}, {"label": "0.439", "tc": "00:04:21.4336", "tclevel": 1}, {"label": "0.113", "tc": "00:04:21.6004", "tclevel": 1}, {"label": "1.929", "tc": "00:04:21.7672", "tclevel": 1}, {"label": "0.63", "tc": "00:04:21.9341", "tclevel": 1}, {"label": "3.048", "tc": "00:04:22.1009", "tclevel": 1}, {"label": "3.574", "tc": "00:04:22.2677", "tclevel": 1}, {"label": "2.799", "tc": "00:04:22.4346", "tclevel": 1}, {"label": "4.958", "tc": "00:04:22.6014", "tclevel": 1}, {"label": "0.687", "tc": "00:04:22.7683", "tclevel": 1}, {"label": "4.173", "tc": "00:04:22.9351", "tclevel": 1}, {"label": "2.712", "tc": "00:04:23.1019", "tclevel": 1}, {"label": "2.488", "tc": "00:04:23.2688", "tclevel": 1}, {"label": "1.109", "tc": "00:04:23.4356", "tclevel": 1}, {"label": "4.362", "tc": "00:04:23.6024", "tclevel": 1}, {"label": "2.719", "tc": "00:04:23.7693", "tclevel": 1}, {"label": "3.193", "tc": "00:04:23.9361", "tclevel": 1}, {"label": "4.332", "tc": "00:04:24.1030", "tclevel": 1}, {"label": "2.447", "tc": "00:04:24.2698", "tclevel": 1}, {"label": "2.951", "tc": "00:04:24.4366", "tclevel": 1}, {"label": "0.741", "tc": "00:04:24.6035", "tclevel": 1}, {"label": "1.521", "tc": "00:04:24.7703", "tclevel": 1}, {"label": "3.091", "tc": "00:04:24.9371", "tclevel": 1}, {"label": "0.278", "tc": "00:04:25.1040", "tclevel": 1}, {"label": "0.284", "tc": "00:04:25.2708", "tclevel": 1}, {"label": "2.527", "tc": "00:04:25.4376", "tclevel": 1}, {"label": "0.996", "tc": "00:04:25.6045", "tclevel": 1}, {"label": "3.193", "tc": "00:04:25.7713", "tclevel": 1}, {"label": "3.096", "tc": "00:04:25.9382", "tclevel": 1}, {"label": "0.782", "tc": "00:04:26.1050", "tclevel": 1}, {"label": "4.368", "tc": "00:04:26.2718", "tclevel": 1}, {"label": "2.774", "tc": "00:04:26.4387", "tclevel": 1}, {"label": "2.504", "tc": "00:04:26.6055", "tclevel": 1}, {"label": "0.763", "tc": "00:04:26.7723", "tclevel": 1}, {"label": "1.582", "tc": "00:04:26.9392", "tclevel": 1}, {"label": "0.189", "tc": "00:04:27.1060", "tclevel": 1}, {"label": "2.516", "tc": "00:04:27.2729", "tclevel": 1}, {"label": "3.327", "tc": "00:04:27.4397", "tclevel": 1}, {"label": "2.718", "tc": "00:04:27.6065", "tclevel": 1}, {"label": "1.362", "tc": "00:04:27.7734", "tclevel": 1}, {"label": "1.477", "tc": "00:04:27.9402", "tclevel": 1}, {"label": "0.352", "tc": "00:04:28.1070", "tclevel": 1}, {"label": "3.268", "tc": "00:04:28.2739", "tclevel": 1}, {"label": "3.113", "tc": "00:04:28.4407", "tclevel": 1}, {"label": "4.981", "tc": "00:04:28.6075", "tclevel": 1}, {"label": "4.494", "tc": "00:04:28.7744", "tclevel": 1}, {"label": "2.687", "tc": "00:04:28.9412", "tclevel": 1}, {"label": "1.351", "tc": "00:04:29.1081", "tclevel": 1}]}, "type": "keyframes", "tcin": "00:00:00.0000", "tcout": "00:00:15.0000", "tclevel": 0}], "id": "rethinking_score_random", "type": "events", "algorithm": "demo-video-generator", "processor": "", "processed": 1421141589291, "version": 1}