{"localisation": [{"sublocalisations": {"localisation": [{"tcin": "00:00:20.0015", "tcout": "00:00:22.0016", "tclevel": 10}, {"tcin": "00:00:22.0016", "tcout": "00:00:24.0018", "tclevel": 11}, {"tcin": "00:00:42.0031", "tcout": "00:00:44.0032", "tclevel": 21}, {"tcin": "00:01:00.0044", "tcout": "00:01:02.0046", "tclevel": 30}, {"tcin": "00:01:06.0049", "tcout": "00:01:08.0050", "tclevel": 33}, {"tcin": "00:01:46.0078", "tcout": "00:01:48.0080", "tclevel": 53}, {"tcin": "00:01:54.0084", "tcout": "00:01:56.0086", "tclevel": 57}, {"tcin": "00:01:58.0087", "tcout": "00:02:00.0089", "tclevel": 59}, {"tcin": "00:02:00.0089", "tcout": "00:02:02.0090", "tclevel": 60}, {"tcin": "00:02:08.0095", "tcout": "00:02:10.0096", "tclevel": 64}, {"tcin": "00:02:16.0100", "tcout": "00:02:18.0102", "tclevel": 68}, {"tcin": "00:02:18.0102", "tcout": "00:02:20.0103", "tclevel": 69}, {"tcin": "00:02:20.0103", "tcout": "00:02:22.0105", "tclevel": 70}, {"tcin": "00:02:56.0130", "tcout": "00:02:58.0131", "tclevel": 88}]}, "type": "keyframes", "tcin": "00:00:00.0000", "tcout": "00:00:15.0000", "tclevel": 95}], "id": "seg_gt", "type": "segments", "algorithm": "demo-video-generator", "processor": "mmlab", "processed": "1421141589291", "version": "1"}