{"localisation": [{"sublocalisations": {"localisation": [{"label": "0.6316728", "tc": "00:55:19.52", "tclevel": 1}, {"label": "0.61908", "tc": "00:52:28.76", "tclevel": 1}, {"label": "0.6055382", "tc": "00:38:24.04", "tclevel": 1}, {"label": "0.60064036", "tc": "00:55:54.92", "tclevel": 1}, {"label": "0.59728456", "tc": "00:55:27.96", "tclevel": 1}]}, "type": "keyframes", "tcin": "00:00:00.0000", "tcout": "00:00:15.0000", "tclevel": 0}], "id": "shot_gt", "type": "events", "algorithm": "demo-video-generator", "processor": "", "processed": 1421141589291, "version": 1}