{"localisation": [{"sublocalisations": {"localisation": [{"label": 3.4, "tc": "00:00:00.0000", "tclevel": 1}, {"label": 3.2, "tc": "00:00:02.0021", "tclevel": 1}, {"label": 1.5, "tc": "00:00:04.0041", "tclevel": 1}, {"label": 1.8, "tc": "00:00:06.0062", "tclevel": 1}, {"label": 2.9, "tc": "00:00:08.0082", "tclevel": 1}, {"label": 1.5, "tc": "00:00:10.0103", "tclevel": 1}, {"label": 3.8, "tc": "00:00:12.0124", "tclevel": 1}, {"label": 4.9, "tc": "00:00:14.0144", "tclevel": 1}, {"label": 1.6, "tc": "00:00:16.0165", "tclevel": 1}, {"label": 3.7, "tc": "00:00:18.0185", "tclevel": 1}, {"label": 3.5, "tc": "00:00:20.0206", "tclevel": 1}, {"label": 3.4, "tc": "00:00:22.0227", "tclevel": 1}, {"label": 1.1, "tc": "00:00:24.0247", "tclevel": 1}, {"label": 4.6, "tc": "00:00:26.0268", "tclevel": 1}, {"label": 2.9, "tc": "00:00:28.0288", "tclevel": 1}, {"label": 1.9, "tc": "00:00:30.0309", "tclevel": 1}, {"label": 3.6, "tc": "00:00:32.0330", "tclevel": 1}, {"label": 3.1, "tc": "00:00:34.0350", "tclevel": 1}, {"label": 5.0, "tc": "00:00:36.0371", "tclevel": 1}, {"label": 4.7, "tc": "00:00:38.0391", "tclevel": 1}, {"label": 2.1, "tc": "00:00:40.0412", "tclevel": 1}, {"label": 3.4, "tc": "00:00:42.0433", "tclevel": 1}, {"label": 3.0, "tc": "00:00:44.0453", "tclevel": 1}, {"label": 2.2, "tc": "00:00:46.0474", "tclevel": 1}, {"label": 3.3, "tc": "00:00:48.0494", "tclevel": 1}, {"label": 4.5, "tc": "00:00:50.0515", "tclevel": 1}, {"label": 4.1, "tc": "00:00:52.0535", "tclevel": 1}, {"label": 3.8, "tc": "00:00:54.0556", "tclevel": 1}, {"label": 2.3, "tc": "00:00:56.0577", "tclevel": 1}, {"label": 2.2, "tc": "00:00:58.0597", "tclevel": 1}, {"label": 3.1, "tc": "00:01:00.0618", "tclevel": 1}, {"label": 3.4, "tc": "00:01:02.0638", "tclevel": 1}, {"label": 1.5, "tc": "00:01:04.0659", "tclevel": 1}, {"label": 1.8, "tc": "00:01:06.0680", "tclevel": 1}, {"label": 3.7, "tc": "00:01:08.0700", "tclevel": 1}, {"label": 1.1, "tc": "00:01:10.0721", "tclevel": 1}, {"label": 4.0, "tc": "00:01:12.0741", "tclevel": 1}, {"label": 3.4, "tc": "00:01:14.0762", "tclevel": 1}, {"label": 4.5, "tc": "00:01:16.0783", "tclevel": 1}, {"label": 4.2, "tc": "00:01:18.0803", "tclevel": 1}, {"label": 1.1, "tc": "00:01:20.0824", "tclevel": 1}, {"label": 4.6, "tc": "00:01:22.0844", "tclevel": 1}, {"label": 1.1, "tc": "00:01:24.0865", "tclevel": 1}, {"label": 2.1, "tc": "00:01:26.0886", "tclevel": 1}, {"label": 4.5, "tc": "00:01:28.0906", "tclevel": 1}, {"label": 3.4, "tc": "00:01:30.0927", "tclevel": 1}, {"label": 1.2, "tc": "00:01:32.0947", "tclevel": 1}, {"label": 1.0, "tc": "00:01:34.0968", "tclevel": 1}, {"label": 1.1, "tc": "00:01:36.0989", "tclevel": 1}, {"label": 1.1, "tc": "00:01:38.1009", "tclevel": 1}, {"label": 1.7, "tc": "00:01:40.1030", "tclevel": 1}, {"label": 3.1, "tc": "00:01:42.1050", "tclevel": 1}, {"label": 2.2, "tc": "00:01:44.1071", "tclevel": 1}, {"label": 4.1, "tc": "00:01:46.1092", "tclevel": 1}, {"label": 1.5, "tc": "00:01:48.1112", "tclevel": 1}, {"label": 3.0, "tc": "00:01:50.1133", "tclevel": 1}, {"label": 3.6, "tc": "00:01:52.1153", "tclevel": 1}, {"label": 2.9, "tc": "00:01:54.1174", "tclevel": 1}, {"label": 2.1, "tc": "00:01:56.1195", "tclevel": 1}, {"label": 4.2, "tc": "00:01:58.1215", "tclevel": 1}, {"label": 3.8, "tc": "00:02:00.1236", "tclevel": 1}, {"label": 4.6, "tc": "00:02:02.1256", "tclevel": 1}, {"label": 3.0, "tc": "00:02:04.1277", "tclevel": 1}, {"label": 3.0, "tc": "00:02:06.1298", "tclevel": 1}, {"label": 2.1, "tc": "00:02:08.1318", "tclevel": 1}, {"label": 4.9, "tc": "00:02:10.1339", "tclevel": 1}, {"label": 3.9, "tc": "00:02:12.1359", "tclevel": 1}, {"label": 3.6, "tc": "00:02:14.1380", "tclevel": 1}, {"label": 4.0, "tc": "00:02:16.1401", "tclevel": 1}, {"label": 5.0, "tc": "00:02:18.1421", "tclevel": 1}, {"label": 2.7, "tc": "00:02:20.1442", "tclevel": 1}, {"label": 3.6, "tc": "00:02:22.1462", "tclevel": 1}, {"label": 2.4, "tc": "00:02:24.1483", "tclevel": 1}, {"label": 4.1, "tc": "00:02:26.1503", "tclevel": 1}, {"label": 3.7, "tc": "00:02:28.1524", "tclevel": 1}, {"label": 2.4, "tc": "00:02:30.1545", "tclevel": 1}, {"label": 3.5, "tc": "00:02:32.1565", "tclevel": 1}, {"label": 2.5, "tc": "00:02:34.1586", "tclevel": 1}, {"label": 2.0, "tc": "00:02:36.1606", "tclevel": 1}]}, "type": "keyframes", "tcin": "00:00:00.0000", "tcout": "00:00:15.0000", "tclevel": 0}], "id": "shot_bl", "type": "events", "algorithm": "demo-video-generator", "processor": "", "processed": 1421141589291, "version": 1}