{"localisation": [{"sublocalisations": {"localisation": [{"tcin": "00:00:10.0103", "tcout": "00:00:12.0123", "tclevel": 1}, {"tcin": "00:00:36.0370", "tcout": "00:00:38.0391", "tclevel": 1}, {"tcin": "00:01:10.0719", "tcout": "00:01:12.0740", "tclevel": 1}, {"tcin": "00:01:40.1028", "tcout": "00:01:44.1069", "tclevel": 1}, {"tcin": "00:01:46.1089", "tcout": "00:01:48.1110", "tclevel": 1}, {"tcin": "00:01:56.1192", "tcout": "00:01:58.1213", "tclevel": 1}, {"tcin": "00:02:22.1459", "tcout": "00:02:24.1480", "tclevel": 1}, {"tcin": "00:02:28.1521", "tcout": "00:02:30.1541", "tclevel": 1}, {"tcin": "00:02:38.1624", "tcout": "00:02:40.1644", "tclevel": 1}, {"tcin": "00:02:54.1788", "tcout": "00:02:58.1829", "tclevel": 1}, {"tcin": "00:03:08.1932", "tcout": "00:03:10.1953", "tclevel": 1}, {"tcin": "00:03:14.1994", "tcout": "00:03:16.2014", "tclevel": 1}, {"tcin": "00:03:18.2035", "tcout": "00:03:20.2055", "tclevel": 1}, {"tcin": "00:03:36.2220", "tcout": "00:03:40.2261", "tclevel": 1}, {"tcin": "00:03:44.2302", "tcout": "00:03:46.2322", "tclevel": 1}, {"tcin": "00:04:12.2590", "tcout": "00:04:14.2610", "tclevel": 1}, {"tcin": "00:04:24.2713", "tcout": "00:04:26.2734", "tclevel": 1}, {"tcin": "00:04:32.2795", "tcout": "00:04:34.2816", "tclevel": 1}]}, "type": "keyframes", "tcin": "00:00:00.0000", "tcout": "00:00:15.0000", "tclevel": 18}], "id": "seg_vsum_dsf_rgb_only_vgg16", "type": "segments", "algorithm": "demo-video-generator", "processor": "mmlab", "processed": "1421141589291", "version": "1"}