{"localisation": [{"sublocalisations": {"localisation": [{"label": "0.7346771", "tc": "01:37:20.04", "tclevel": 1}, {"label": "0.7178218", "tc": "01:37:15.56", "tclevel": 1}, {"label": "0.70913506", "tc": "01:37:25.44", "tclevel": 1}, {"label": "0.70822316", "tc": "01:41:22.84", "tclevel": 1}, {"label": "0.69848734", "tc": "01:36:43.92", "tclevel": 1}, {"label": "0.6856944", "tc": "01:20:49.96", "tclevel": 1}, {"label": "0.6814194", "tc": "01:37:08.44", "tclevel": 1}, {"label": "0.6752431", "tc": "01:20:45.48", "tclevel": 1}, {"label": "0.6735652", "tc": "01:36:49.88", "tclevel": 1}, {"label": "0.6730401", "tc": "01:19:06.2", "tclevel": 1}, {"label": "0.6725149", "tc": "01:17:50.0", "tclevel": 1}, {"label": "0.6661636", "tc": "01:17:37.08", "tclevel": 1}, {"label": "0.66607124", "tc": "01:31:03.52", "tclevel": 1}, {"label": "0.6659859", "tc": "01:20:58.72", "tclevel": 1}, {"label": "0.66581196", "tc": "01:17:47.0", "tclevel": 1}]}, "type": "keyframes", "tcin": "00:00:00.0000", "tcout": "00:00:15.0000", "tclevel": 0}], "id": "shot_gt", "type": "events", "algorithm": "demo-video-generator", "processor": "", "processed": 1421141589291, "version": 1}