{"localisation": [{"sublocalisations": {"localisation": [{"label": "0.7601217", "tc": "01:44:13.08", "tclevel": 1}, {"label": "0.7446268", "tc": "00:51:08.68", "tclevel": 1}, {"label": "0.7434362", "tc": "01:44:04.12", "tclevel": 1}, {"label": "0.73433614", "tc": "00:32:22.08", "tclevel": 1}, {"label": "0.7259519", "tc": "01:44:22.24", "tclevel": 1}, {"label": "0.72384167", "tc": "01:44:30.56", "tclevel": 1}, {"label": "0.72178185", "tc": "01:40:50.4", "tclevel": 1}, {"label": "0.71298134", "tc": "00:32:47.56", "tclevel": 1}, {"label": "0.7115517", "tc": "01:44:17.6", "tclevel": 1}, {"label": "0.70917976", "tc": "01:40:25.76", "tclevel": 1}, {"label": "0.7051827", "tc": "01:44:32.6", "tclevel": 1}, {"label": "0.7022139", "tc": "01:44:26.48", "tclevel": 1}, {"label": "0.70211554", "tc": "00:51:31.48", "tclevel": 1}, {"label": "0.6973362", "tc": "00:32:38.04", "tclevel": 1}, {"label": "0.6963752", "tc": "01:33:40.92", "tclevel": 1}, {"label": "0.69567823", "tc": "01:33:27.8", "tclevel": 1}, {"label": "0.6956744", "tc": "00:32:42.0", "tclevel": 1}, {"label": "0.6919687", "tc": "01:40:49.08", "tclevel": 1}]}, "type": "keyframes", "tcin": "00:00:00.0000", "tcout": "00:00:15.0000", "tclevel": 0}], "id": "shot_gt", "type": "events", "algorithm": "demo-video-generator", "processor": "", "processed": 1421141589291, "version": 1}