{"localisation": [{"sublocalisations": {"localisation": [{"label": "0.293", "tc": "00:00:00.0000", "tclevel": 1}, {"label": "0.251", "tc": "00:00:00.5000", "tclevel": 1}, {"label": "0.268", "tc": "00:00:01.0000", "tclevel": 1}, {"label": "0.268", "tc": "00:00:01.5000", "tclevel": 1}, {"label": "0.24", "tc": "00:00:02.0000", "tclevel": 1}, {"label": "0.242", "tc": "00:00:02.5000", "tclevel": 1}, {"label": "0.255", "tc": "00:00:03.0000", "tclevel": 1}, {"label": "0.246", "tc": "00:00:03.5000", "tclevel": 1}, {"label": "0.239", "tc": "00:00:04.0000", "tclevel": 1}, {"label": "0.229", "tc": "00:00:04.5000", "tclevel": 1}, {"label": "0.234", "tc": "00:00:05.0000", "tclevel": 1}, {"label": "0.236", "tc": "00:00:05.5000", "tclevel": 1}, {"label": "0.238", "tc": "00:00:06.0000", "tclevel": 1}, {"label": "0.221", "tc": "00:00:06.5000", "tclevel": 1}, {"label": "0.243", "tc": "00:00:07.0000", "tclevel": 1}, {"label": "0.252", "tc": "00:00:07.5000", "tclevel": 1}, {"label": "0.42", "tc": "00:00:08.0000", "tclevel": 1}, {"label": "0.521", "tc": "00:00:08.5000", "tclevel": 1}, {"label": "0.808", "tc": "00:00:09.0000", "tclevel": 1}, {"label": "0.78", "tc": "00:00:09.5000", "tclevel": 1}, {"label": "0.828", "tc": "00:00:10.0000", "tclevel": 1}, {"label": "0.572", "tc": "00:00:10.5000", "tclevel": 1}, {"label": "0.955", "tc": "00:00:11.0000", "tclevel": 1}, {"label": "1.267", "tc": "00:00:11.5000", "tclevel": 1}, {"label": "1.24", "tc": "00:00:12.0000", "tclevel": 1}, {"label": "0.865", "tc": "00:00:12.5000", "tclevel": 1}, {"label": "0.817", "tc": "00:00:13.0000", "tclevel": 1}, {"label": "0.755", "tc": "00:00:13.5000", "tclevel": 1}, {"label": "0.867", "tc": "00:00:14.0000", "tclevel": 1}, {"label": "0.505", "tc": "00:00:14.5000", "tclevel": 1}, {"label": "0.37", "tc": "00:00:15.0000", "tclevel": 1}, {"label": "0.353", "tc": "00:00:15.5000", "tclevel": 1}, {"label": "0.29", "tc": "00:00:16.0000", "tclevel": 1}, {"label": "0.322", "tc": "00:00:16.5000", "tclevel": 1}, {"label": "0.31", "tc": "00:00:17.0000", "tclevel": 1}, {"label": "0.273", "tc": "00:00:17.5000", "tclevel": 1}, {"label": "0.431", "tc": "00:00:18.0000", "tclevel": 1}, {"label": "0.475", "tc": "00:00:18.5000", "tclevel": 1}, {"label": "0.432", "tc": "00:00:19.0000", "tclevel": 1}, {"label": "0.513", "tc": "00:00:19.5000", "tclevel": 1}, {"label": "0.418", "tc": "00:00:20.0000", "tclevel": 1}, {"label": "0.231", "tc": "00:00:20.5000", "tclevel": 1}, {"label": "0.486", "tc": "00:00:21.0000", "tclevel": 1}, {"label": "0.477", "tc": "00:00:21.5000", "tclevel": 1}, {"label": "0.55", "tc": "00:00:22.0000", "tclevel": 1}, {"label": "0.608", "tc": "00:00:22.5000", "tclevel": 1}, {"label": "0.448", "tc": "00:00:23.0000", "tclevel": 1}, {"label": "0.495", "tc": "00:00:23.5000", "tclevel": 1}, {"label": "0.46", "tc": "00:00:24.0000", "tclevel": 1}, {"label": "0.361", "tc": "00:00:24.5000", "tclevel": 1}, {"label": "0.372", "tc": "00:00:25.0000", "tclevel": 1}, {"label": "0.494", "tc": "00:00:25.5000", "tclevel": 1}, {"label": "0.624", "tc": "00:00:26.0000", "tclevel": 1}, {"label": "0.503", "tc": "00:00:26.5000", "tclevel": 1}, {"label": "0.591", "tc": "00:00:27.0000", "tclevel": 1}, {"label": "0.373", "tc": "00:00:27.5000", "tclevel": 1}, {"label": "0.371", "tc": "00:00:28.0000", "tclevel": 1}, {"label": "0.338", "tc": "00:00:28.5000", "tclevel": 1}, {"label": "0.381", "tc": "00:00:29.0000", "tclevel": 1}, {"label": "0.262", "tc": "00:00:29.5000", "tclevel": 1}, {"label": "0.298", "tc": "00:00:30.0000", "tclevel": 1}, {"label": "0.294", "tc": "00:00:30.5000", "tclevel": 1}, {"label": "0.314", "tc": "00:00:31.0000", "tclevel": 1}, {"label": "0.245", "tc": "00:00:31.5000", "tclevel": 1}, {"label": "0.272", "tc": "00:00:32.0000", "tclevel": 1}, {"label": "0.346", "tc": "00:00:32.5000", "tclevel": 1}, {"label": "0.296", "tc": "00:00:33.0000", "tclevel": 1}, {"label": "0.215", "tc": "00:00:33.5000", "tclevel": 1}, {"label": "0.36", "tc": "00:00:34.0000", "tclevel": 1}, {"label": "0.345", "tc": "00:00:34.5000", "tclevel": 1}, {"label": "0.385", "tc": "00:00:35.0000", "tclevel": 1}, {"label": "0.423", "tc": "00:00:35.5000", "tclevel": 1}, {"label": "0.311", "tc": "00:00:36.0000", "tclevel": 1}, {"label": "0.236", "tc": "00:00:36.5000", "tclevel": 1}, {"label": "0.238", "tc": "00:00:37.0000", "tclevel": 1}, {"label": "0.482", "tc": "00:00:37.5000", "tclevel": 1}, {"label": "0.566", "tc": "00:00:38.0000", "tclevel": 1}, {"label": "0.467", "tc": "00:00:38.5000", "tclevel": 1}, {"label": "0.327", "tc": "00:00:39.0000", "tclevel": 1}, {"label": "0.454", "tc": "00:00:39.5000", "tclevel": 1}, {"label": "0.287", "tc": "00:00:40.0000", "tclevel": 1}, {"label": "0.241", "tc": "00:00:40.5000", "tclevel": 1}, {"label": "0.25", "tc": "00:00:41.0000", "tclevel": 1}, {"label": "0.317", "tc": "00:00:41.5000", "tclevel": 1}, {"label": "0.355", "tc": "00:00:42.0000", "tclevel": 1}, {"label": "0.384", "tc": "00:00:42.5000", "tclevel": 1}, {"label": "0.418", "tc": "00:00:43.0000", "tclevel": 1}, {"label": "0.402", "tc": "00:00:43.5000", "tclevel": 1}, {"label": "0.515", "tc": "00:00:44.0000", "tclevel": 1}, {"label": "0.572", "tc": "00:00:44.5000", "tclevel": 1}, {"label": "1.06", "tc": "00:00:45.0000", "tclevel": 1}, {"label": "0.872", "tc": "00:00:45.5000", "tclevel": 1}, {"label": "0.64", "tc": "00:00:46.0000", "tclevel": 1}, {"label": "0.495", "tc": "00:00:46.5000", "tclevel": 1}, {"label": "0.452", "tc": "00:00:47.0000", "tclevel": 1}, {"label": "0.41", "tc": "00:00:47.5000", "tclevel": 1}, {"label": "0.358", "tc": "00:00:48.0000", "tclevel": 1}, {"label": "0.295", "tc": "00:00:48.5000", "tclevel": 1}, {"label": "0.352", "tc": "00:00:49.0000", "tclevel": 1}, {"label": "0.269", "tc": "00:00:49.5000", "tclevel": 1}, {"label": "0.211", "tc": "00:00:50.0000", "tclevel": 1}, {"label": "0.246", "tc": "00:00:50.5000", "tclevel": 1}, {"label": "0.338", "tc": "00:00:51.0000", "tclevel": 1}, {"label": "0.362", "tc": "00:00:51.5000", "tclevel": 1}, {"label": "0.303", "tc": "00:00:52.0000", "tclevel": 1}, {"label": "0.294", "tc": "00:00:52.5000", "tclevel": 1}, {"label": "0.214", "tc": "00:00:53.0000", "tclevel": 1}, {"label": "0.233", "tc": "00:00:53.5000", "tclevel": 1}]}, "type": "keyframes", "tcin": "00:00:00.0000", "tcout": "00:00:15.0000", "tclevel": 0}], "id": "VASNet_Score", "type": "events", "algorithm": "demo-video-generator", "processor": "", "processed": 1421141589291, "version": 1}