{"localisation": [{"sublocalisations": {"localisation": [{"label": "1.0", "tc": "00:00:00.0000", "tclevel": 1}, {"label": "1.0", "tc": "00:00:03.1701", "tclevel": 1}, {"label": "1.0", "tc": "00:00:06.5738", "tclevel": 1}, {"label": "1.0", "tc": "00:00:12.1798", "tclevel": 1}, {"label": "1.0", "tc": "00:00:15.4500", "tclevel": 1}, {"label": "1.0", "tc": "00:00:21.8236", "tclevel": 1}, {"label": "1.0", "tc": "00:00:24.8268", "tclevel": 1}, {"label": "1.0", "tc": "00:00:30.5663", "tclevel": 1}, {"label": "1.0", "tc": "00:00:36.6396", "tclevel": 1}, {"label": "1.0", "tc": "00:00:39.9765", "tclevel": 1}, {"label": "1.0", "tc": "00:00:44.3145", "tclevel": 1}, {"label": "1.0", "tc": "00:00:48.0185", "tclevel": 1}, {"label": "1.0", "tc": "00:00:49.8538", "tclevel": 1}, {"label": "1.0", "tc": "00:00:55.0928", "tclevel": 1}, {"label": "1.0", "tc": "00:01:00.6989", "tclevel": 1}, {"label": "1.0", "tc": "00:01:02.8012", "tclevel": 1}, {"label": "1.0", "tc": "00:01:05.3039", "tclevel": 1}, {"label": "1.0", "tc": "00:01:10.6096", "tclevel": 1}, {"label": "1.0", "tc": "00:01:13.3793", "tclevel": 1}, {"label": "1.0", "tc": "00:01:21.5881", "tclevel": 1}, {"label": "1.0", "tc": "00:01:26.4934", "tclevel": 1}, {"label": "1.0", "tc": "00:01:29.6301", "tclevel": 1}, {"label": "1.0", "tc": "00:01:34.6355", "tclevel": 1}, {"label": "1.0", "tc": "00:01:40.8423", "tclevel": 1}, {"label": "1.0", "tc": "00:01:57.4602", "tclevel": 1}, {"label": "1.0", "tc": "00:01:59.8294", "tclevel": 1}, {"label": "1.0", "tc": "00:02:02.7659", "tclevel": 1}, {"label": "1.0", "tc": "00:02:07.5711", "tclevel": 1}, {"label": "1.0", "tc": "00:02:14.9458", "tclevel": 1}, {"label": "1.0", "tc": "00:02:19.7509", "tclevel": 1}]}, "type": "keyframes", "tcin": "00:00:00.0000", "tcout": "00:00:15.0000", "tclevel": 0}], "id": "rethinking_randomized-KTS_seg_boundaries", "type": "events", "algorithm": "demo-video-generator", "processor": "", "processed": 1421141589291, "version": 1}