{"localisation": [{"sublocalisations": {"localisation": [{"label": "0.99453813_CliffDiving", "tc": "00:00:00.0", "tclevel": 1}, {"label": "0.45674759_PlayingFlute", "tc": "00:00:21.08", "tclevel": 1}, {"label": "0.318487346_Drumming", "tc": "00:00:23.6", "tclevel": 1}, {"label": "0.96623266_Haircut", "tc": "00:00:32.0", "tclevel": 1}, {"label": "0.742888272_ApplyEyeMakeup", "tc": "00:00:33.72", "tclevel": 1}, {"label": "0.975392103_Haircut", "tc": "00:00:34.56", "tclevel": 1}, {"label": "0.98748326_Haircut", "tc": "00:00:36.2", "tclevel": 1}, {"label": "0.388869941_BlowDryHair", "tc": "00:00:37.48", "tclevel": 1}, {"label": "0.572215974_Haircut", "tc": "00:00:39.64", "tclevel": 1}, {"label": "0.997044861_Haircut", "tc": "00:00:40.92", "tclevel": 1}, {"label": "0.372677714_Haircut", "tc": "00:00:43.0", "tclevel": 1}, {"label": "0.85665226_Haircut", "tc": "00:00:53.2", "tclevel": 1}, {"label": "0.465889663_PlayingFlute", "tc": "00:00:56.08", "tclevel": 1}, {"label": "0.889039516_ApplyEyeMakeup", "tc": "00:00:58.16", "tclevel": 1}, {"label": "0.530746579_Billiards", "tc": "00:00:59.96", "tclevel": 1}, {"label": "0.888518393_Drumming", "tc": "00:01:01.44", "tclevel": 1}, {"label": "0.506050646_ApplyEyeMakeup", "tc": "00:01:05.12", "tclevel": 1}, {"label": "0.979929268_ApplyEyeMakeup", "tc": "00:01:08.32", "tclevel": 1}, {"label": "0.845616579_ApplyEyeMakeup", "tc": "00:01:10.72", "tclevel": 1}, {"label": "0.981521964_Haircut", "tc": "00:01:12.2", "tclevel": 1}, {"label": "0.939676344_ApplyEyeMakeup", "tc": "00:01:13.2", "tclevel": 1}, {"label": "0.443033159_ApplyEyeMakeup", "tc": "00:01:16.16", "tclevel": 1}, {"label": "0.76717478_ShavingBeard", "tc": "00:01:18.32", "tclevel": 1}, {"label": "0.94184494_ApplyEyeMakeup", "tc": "00:01:19.4", "tclevel": 1}, {"label": "0.45040047_PlayingFlute", "tc": "00:01:19.76", "tclevel": 1}, {"label": "0.956991434_Mixing", "tc": "00:01:20.72", "tclevel": 1}, {"label": "0.618719399_Haircut", "tc": "00:01:22.2", "tclevel": 1}, {"label": "0.39030629_Punch", "tc": "00:01:24.12", "tclevel": 1}, {"label": "0.535930693_Haircut", "tc": "00:01:32.4", "tclevel": 1}, {"label": "0.880331933_Haircut", "tc": "00:01:32.84", "tclevel": 1}, {"label": "0.74783927_ApplyEyeMakeup", "tc": "00:01:33.64", "tclevel": 1}, {"label": "0.51805967_ApplyEyeMakeup", "tc": "00:01:34.48", "tclevel": 1}, {"label": "0.988479435_Haircut", "tc": "00:01:36.52", "tclevel": 1}, {"label": "0.471091628_Archery", "tc": "00:01:38.08", "tclevel": 1}, {"label": "0.505286813_PlayingFlute", "tc": "00:01:41.68", "tclevel": 1}, {"label": "0.636361063_ApplyEyeMakeup", "tc": "00:01:43.0", "tclevel": 1}, {"label": "0.907556474_YoYo", "tc": "00:01:44.28", "tclevel": 1}, {"label": "0.94512862_ApplyEyeMakeup", "tc": "00:01:48.28", "tclevel": 1}, {"label": "0.358012974_Haircut", "tc": "00:01:49.36", "tclevel": 1}, {"label": "0.377355874_PlayingGuitar", "tc": "00:01:57.24", "tclevel": 1}, {"label": "0.75764668_ApplyEyeMakeup", "tc": "00:01:59.44", "tclevel": 1}, {"label": "0.26409632_PlayingFlute", "tc": "00:02:00.64", "tclevel": 1}, {"label": "0.292680681_YoYo", "tc": "00:02:01.08", "tclevel": 1}, {"label": "0.391801596_Haircut", "tc": "00:02:03.08", "tclevel": 1}, {"label": "0.92882448_YoYo", "tc": "00:02:04.92", "tclevel": 1}, {"label": "0.689316988_Haircut", "tc": "00:02:05.6", "tclevel": 1}, {"label": "0.913447738_YoYo", "tc": "00:02:06.76", "tclevel": 1}, {"label": "0.366589695_PlayingFlute", "tc": "00:02:11.12", "tclevel": 1}, {"label": "0.168193161_MilitaryParade", "tc": "00:02:11.8", "tclevel": 1}, {"label": "0.42154318_ApplyLipstick", "tc": "00:02:15.64", "tclevel": 1}, {"label": "0.58877343_ApplyLipstick", "tc": "00:02:16.96", "tclevel": 1}, {"label": "0.655299783_ApplyLipstick", "tc": "00:02:17.64", "tclevel": 1}, {"label": "0.916857481_ApplyEyeMakeup", "tc": "00:02:17.96", "tclevel": 1}, {"label": "0.635332704_Bowling", "tc": "00:02:20.4", "tclevel": 1}, {"label": "0.284642696_PlayingGuitar", "tc": "00:02:24.32", "tclevel": 1}, {"label": "0.98524183_Haircut", "tc": "00:02:27.16", "tclevel": 1}, {"label": "0.80207938_Drumming", "tc": "00:02:28.08", "tclevel": 1}, {"label": "0.28318727_ApplyLipstick", "tc": "00:02:30.8", "tclevel": 1}, {"label": "0.869421959_BlowingCandles", "tc": "00:02:33.76", "tclevel": 1}, {"label": "0.24854894_BlowingCandles", "tc": "00:02:34.64", "tclevel": 1}, {"label": "0.61057979_BlowingCandles", "tc": "00:02:36.36", "tclevel": 1}, {"label": "0.78024387_YoYo", "tc": "00:02:42.44", "tclevel": 1}, {"label": "0.749649465_PlayingFlute", "tc": "00:02:57.2", "tclevel": 1}, {"label": "0.883953214_BlowingCandles", "tc": "00:02:58.64", "tclevel": 1}, {"label": "0.81651324_BlowingCandles", "tc": "00:03:02.84", "tclevel": 1}, {"label": "0.139861137_Mixing", "tc": "00:03:04.36", "tclevel": 1}, {"label": "0.98968327_BlowingCandles", "tc": "00:03:05.52", "tclevel": 1}, {"label": "0.784969747_ApplyEyeMakeup", "tc": "00:03:08.04", "tclevel": 1}, {"label": "0.560997188_BlowingCandles", "tc": "00:03:13.44", "tclevel": 1}, {"label": "0.734113455_Haircut", "tc": "00:03:14.92", "tclevel": 1}, {"label": "0.995792747_BlowingCandles", "tc": "00:03:15.8", "tclevel": 1}, {"label": "0.632429779_BlowingCandles", "tc": "00:03:16.72", "tclevel": 1}, {"label": "0.21063377_WritingOnBoard", "tc": "00:03:17.84", "tclevel": 1}, {"label": "0.518719494_ApplyEyeMakeup", "tc": "00:03:19.36", "tclevel": 1}, {"label": "0.856910884_BlowingCandles", "tc": "00:03:20.72", "tclevel": 1}, {"label": "0.815586805_PlayingFlute", "tc": "00:03:23.08", "tclevel": 1}, {"label": "0.822694421_ApplyEyeMakeup", "tc": "00:03:26.12", "tclevel": 1}, {"label": "0.973942876_BlowingCandles", "tc": "00:03:27.12", "tclevel": 1}, {"label": "0.411303937_ApplyLipstick", "tc": "00:03:28.2", "tclevel": 1}, {"label": "0.975098312_Haircut", "tc": "00:03:28.88", "tclevel": 1}, {"label": "0.514960349_PlayingFlute", "tc": "00:03:30.16", "tclevel": 1}, {"label": "0.991396248_BlowingCandles", "tc": "00:03:31.28", "tclevel": 1}, {"label": "0.925964296_PlayingFlute", "tc": "00:03:33.6", "tclevel": 1}, {"label": "0.990518034_PlayingFlute", "tc": "00:03:34.4", "tclevel": 1}, {"label": "0.9901281_PlayingFlute", "tc": "00:03:35.6", "tclevel": 1}, {"label": "0.60890251_PlayingTabla", "tc": "00:03:35.92", "tclevel": 1}, {"label": "0.63444066_BlowingCandles", "tc": "00:03:36.16", "tclevel": 1}, {"label": "0.792326987_Haircut", "tc": "00:03:37.0", "tclevel": 1}, {"label": "0.921102643_Drumming", "tc": "00:03:37.36", "tclevel": 1}, {"label": "0.61776787_BlowingCandles", "tc": "00:03:39.88", "tclevel": 1}, {"label": "0.89067179_PlayingFlute", "tc": "00:03:40.88", "tclevel": 1}, {"label": "0.701828539_ApplyEyeMakeup", "tc": "00:03:41.88", "tclevel": 1}, {"label": "0.656867862_BlowingCandles", "tc": "00:03:43.96", "tclevel": 1}, {"label": "0.207526952_PlayingViolin", "tc": "00:03:45.08", "tclevel": 1}, {"label": "0.56425035_Haircut", "tc": "00:03:47.72", "tclevel": 1}, {"label": "0.82571471_PlayingFlute", "tc": "00:03:48.56", "tclevel": 1}, {"label": "0.549251795_Haircut", "tc": "00:03:51.24", "tclevel": 1}, {"label": "0.925780654_ApplyEyeMakeup", "tc": "00:03:52.56", "tclevel": 1}, {"label": "0.384278089_BlowingCandles", "tc": "00:03:54.64", "tclevel": 1}, {"label": "0.978254318_ApplyEyeMakeup", "tc": "00:04:04.0", "tclevel": 1}, {"label": "0.954485536_BlowingCandles", "tc": "00:04:07.4", "tclevel": 1}, {"label": "0.520656466_PlayingFlute", "tc": "00:04:11.0", "tclevel": 1}, {"label": "0.965398014_BlowingCandles", "tc": "00:04:13.96", "tclevel": 1}, {"label": "0.991186798_ApplyEyeMakeup", "tc": "00:04:18.48", "tclevel": 1}, {"label": "0.417672694_BlowingCandles", "tc": "00:04:22.6", "tclevel": 1}, {"label": "0.51864928_PlayingFlute", "tc": "00:04:24.32", "tclevel": 1}, {"label": "0.82887703_BlowingCandles", "tc": "00:04:25.6", "tclevel": 1}, {"label": "0.768143773_PlayingTabla", "tc": "00:04:28.08", "tclevel": 1}, {"label": "0.413590461_BabyCrawling", "tc": "00:04:42.6", "tclevel": 1}, {"label": "0.550914526_PlayingTabla", "tc": "00:04:45.0", "tclevel": 1}, {"label": "0.811011553_ApplyEyeMakeup", "tc": "00:04:56.64", "tclevel": 1}, {"label": "0.571839631_BlowingCandles", "tc": "00:04:58.0", "tclevel": 1}, {"label": "0.429525286_BabyCrawling", "tc": "00:05:08.16", "tclevel": 1}, {"label": "0.24315248_JugglingBalls", "tc": "00:05:11.88", "tclevel": 1}, {"label": "0.604665101_ApplyEyeMakeup", "tc": "00:05:16.2", "tclevel": 1}, {"label": "0.648173213_PlayingFlute", "tc": "00:05:18.0", "tclevel": 1}, {"label": "0.991378784_Haircut", "tc": "00:05:19.76", "tclevel": 1}, {"label": "0.55080515_PlayingFlute", "tc": "00:05:21.68", "tclevel": 1}, {"label": "0.93769002_ApplyEyeMakeup", "tc": "00:05:23.08", "tclevel": 1}, {"label": "0.969016135_ApplyEyeMakeup", "tc": "00:05:28.4", "tclevel": 1}, {"label": "0.76399803_ApplyEyeMakeup", "tc": "00:05:31.72", "tclevel": 1}, {"label": "0.981841803_ApplyEyeMakeup", "tc": "00:05:33.88", "tclevel": 1}, {"label": "0.31133223_PlayingFlute", "tc": "00:05:39.28", "tclevel": 1}, {"label": "0.99377537_ApplyEyeMakeup", "tc": "00:05:49.6", "tclevel": 1}, {"label": "0.987438977_Haircut", "tc": "00:05:51.08", "tclevel": 1}, {"label": "0.994467497_ApplyEyeMakeup", "tc": "00:05:53.68", "tclevel": 1}, {"label": "0.901965737_Haircut", "tc": "00:05:56.16", "tclevel": 1}, {"label": "0.993507504_Haircut", "tc": "00:05:56.84", "tclevel": 1}, {"label": "0.98127651_ApplyEyeMakeup", "tc": "00:05:58.28", "tclevel": 1}, {"label": "0.972782731_Haircut", "tc": "00:05:59.92", "tclevel": 1}, {"label": "0.53200251_ShavingBeard", "tc": "00:06:01.48", "tclevel": 1}, {"label": "0.994843602_Haircut", "tc": "00:06:03.72", "tclevel": 1}, {"label": "0.96662223_ApplyEyeMakeup", "tc": "00:06:11.32", "tclevel": 1}, {"label": "0.747621119_BlowDryHair", "tc": "00:06:13.92", "tclevel": 1}, {"label": "0.989056766_Haircut", "tc": "00:06:15.6", "tclevel": 1}, {"label": "0.694842219_BlowDryHair", "tc": "00:06:17.16", "tclevel": 1}, {"label": "0.884210289_Haircut", "tc": "00:06:19.76", "tclevel": 1}, {"label": "0.99919707_ApplyEyeMakeup", "tc": "00:06:20.96", "tclevel": 1}, {"label": "0.269786537_Haircut", "tc": "00:06:22.84", "tclevel": 1}, {"label": "0.926578522_ShavingBeard", "tc": "00:06:34.32", "tclevel": 1}, {"label": "0.328997493_ApplyEyeMakeup", "tc": "00:06:36.36", "tclevel": 1}, {"label": "0.998012304_ApplyEyeMakeup", "tc": "00:06:41.32", "tclevel": 1}, {"label": "0.969815552_ShavingBeard", "tc": "00:06:42.64", "tclevel": 1}, {"label": "0.882852733_PlayingFlute", "tc": "00:06:47.32", "tclevel": 1}, {"label": "0.531371117_ShavingBeard", "tc": "00:06:53.44", "tclevel": 1}, {"label": "0.60737765_YoYo", "tc": "00:06:55.4", "tclevel": 1}, {"label": "0.27822593_StillRings", "tc": "00:06:57.64", "tclevel": 1}, {"label": "0.308438212_BlowDryHair", "tc": "00:07:48.76", "tclevel": 1}, {"label": "0.29518861_PlayingPiano", "tc": "00:07:49.72", "tclevel": 1}, {"label": "0.675217867_Archery", "tc": "00:07:52.44", "tclevel": 1}, {"label": "0.269373238_PlayingFlute", "tc": "00:07:53.72", "tclevel": 1}, {"label": "0.602102101_PlayingFlute", "tc": "00:07:54.2", "tclevel": 1}, {"label": "0.341962099_Lunges", "tc": "00:07:54.92", "tclevel": 1}, {"label": "0.876946867_Haircut", "tc": "00:07:59.72", "tclevel": 1}, {"label": "0.63677609_Haircut", "tc": "00:08:01.12", "tclevel": 1}, {"label": "0.82114804_Bowling", "tc": "00:08:04.12", "tclevel": 1}, {"label": "0.99183977_ApplyEyeMakeup", "tc": "00:08:13.68", "tclevel": 1}, {"label": "0.857180178_Haircut", "tc": "00:08:14.92", "tclevel": 1}, {"label": "0.760834336_ApplyEyeMakeup", "tc": "00:08:31.52", "tclevel": 1}, {"label": "0.619561851_ApplyEyeMakeup", "tc": "00:08:38.76", "tclevel": 1}, {"label": "0.93457431_ApplyLipstick", "tc": "00:08:42.12", "tclevel": 1}, {"label": "0.54538071_ApplyLipstick", "tc": "00:08:51.76", "tclevel": 1}, {"label": "0.36078691_WritingOnBoard", "tc": "00:08:54.76", "tclevel": 1}, {"label": "0.32311973_Haircut", "tc": "00:08:58.52", "tclevel": 1}, {"label": "0.245776594_PlayingFlute", "tc": "00:09:01.56", "tclevel": 1}, {"label": "0.394533336_BlowDryHair", "tc": "00:09:04.24", "tclevel": 1}, {"label": "0.390186697_MilitaryParade", "tc": "00:09:05.76", "tclevel": 1}, {"label": "0.374521464_ApplyLipstick", "tc": "00:09:07.28", "tclevel": 1}, {"label": "0.79105562_ApplyEyeMakeup", "tc": "00:09:08.48", "tclevel": 1}, {"label": "0.554377377_PlayingFlute", "tc": "00:09:09.96", "tclevel": 1}, {"label": "0.73680228_ApplyEyeMakeup", "tc": "00:09:11.72", "tclevel": 1}, {"label": "0.439903289_ApplyEyeMakeup", "tc": "00:09:12.88", "tclevel": 1}, {"label": "0.947276056_ApplyEyeMakeup", "tc": "00:09:15.52", "tclevel": 1}, {"label": "0.883222342_ApplyEyeMakeup", "tc": "00:09:16.48", "tclevel": 1}, {"label": "0.9943521_ApplyEyeMakeup", "tc": "00:09:18.4", "tclevel": 1}, {"label": "0.937791109_ApplyEyeMakeup", "tc": "00:09:19.64", "tclevel": 1}, {"label": "0.98973513_ApplyEyeMakeup", "tc": "00:09:22.48", "tclevel": 1}, {"label": "0.539587557_PlayingFlute", "tc": "00:09:23.4", "tclevel": 1}, {"label": "0.826714635_Archery", "tc": "00:09:25.64", "tclevel": 1}, {"label": "0.970559299_ApplyEyeMakeup", "tc": "00:09:29.68", "tclevel": 1}, {"label": "0.456365615_PlayingTabla", "tc": "00:09:30.48", "tclevel": 1}, {"label": "0.715528905_BandMarching", "tc": "00:09:33.0", "tclevel": 1}, {"label": "0.96030986_ApplyEyeMakeup", "tc": "00:09:39.36", "tclevel": 1}, {"label": "0.241272703_PlayingFlute", "tc": "00:09:43.16", "tclevel": 1}, {"label": "0.990769565_ApplyEyeMakeup", "tc": "00:09:45.96", "tclevel": 1}, {"label": "0.591248751_PlayingCello", "tc": "00:09:47.6", "tclevel": 1}, {"label": "0.952964604_ApplyEyeMakeup", "tc": "00:09:51.28", "tclevel": 1}, {"label": "0.48488575_BlowDryHair", "tc": "00:09:54.52", "tclevel": 1}, {"label": "0.916381955_ApplyEyeMakeup", "tc": "00:10:06.32", "tclevel": 1}, {"label": "0.457300961_Drumming", "tc": "00:10:07.56", "tclevel": 1}, {"label": "0.463626534_StillRings", "tc": "00:10:14.44", "tclevel": 1}, {"label": "0.543828845_PlayingFlute", "tc": "00:10:18.04", "tclevel": 1}, {"label": "0.497814298_PlayingFlute", "tc": "00:10:18.6", "tclevel": 1}, {"label": "0.519433916_PlayingFlute", "tc": "00:10:25.32", "tclevel": 1}, {"label": "0.746517777_ApplyEyeMakeup", "tc": "00:10:27.84", "tclevel": 1}, {"label": "0.460759014_ApplyLipstick", "tc": "00:10:34.04", "tclevel": 1}, {"label": "0.981432378_ApplyEyeMakeup", "tc": "00:10:36.88", "tclevel": 1}, {"label": "0.99577159_ApplyEyeMakeup", "tc": "00:10:40.04", "tclevel": 1}, {"label": "0.980140388_ApplyEyeMakeup", "tc": "00:10:43.2", "tclevel": 1}, {"label": "0.944634676_ApplyEyeMakeup", "tc": "00:10:46.96", "tclevel": 1}, {"label": "0.963886738_ApplyEyeMakeup", "tc": "00:10:50.6", "tclevel": 1}, {"label": "0.919232905_ApplyEyeMakeup", "tc": "00:10:54.72", "tclevel": 1}, {"label": "0.941470027_ApplyEyeMakeup", "tc": "00:10:57.68", "tclevel": 1}, {"label": "0.884755254_ApplyEyeMakeup", "tc": "00:10:59.84", "tclevel": 1}, {"label": "0.937413335_ApplyEyeMakeup", "tc": "00:11:03.64", "tclevel": 1}, {"label": "0.965412021_ApplyEyeMakeup", "tc": "00:11:07.28", "tclevel": 1}, {"label": "0.65505719_ApplyEyeMakeup", "tc": "00:11:08.6", "tclevel": 1}, {"label": "0.47175899_ApplyEyeMakeup", "tc": "00:11:10.12", "tclevel": 1}, {"label": "0.470137239_YoYo", "tc": "00:11:13.64", "tclevel": 1}, {"label": "0.260439128_PlayingFlute", "tc": "00:11:15.8", "tclevel": 1}, {"label": "0.272828102_PlayingFlute", "tc": "00:11:16.84", "tclevel": 1}, {"label": "0.13188069_PullUps", "tc": "00:11:18.04", "tclevel": 1}, {"label": "0.73456317_ApplyEyeMakeup", "tc": "00:11:24.68", "tclevel": 1}, {"label": "0.627664924_ApplyEyeMakeup", "tc": "00:11:25.76", "tclevel": 1}, {"label": "0.956093013_ApplyEyeMakeup", "tc": "00:11:26.08", "tclevel": 1}, {"label": "0.287528068_Hammering", "tc": "00:11:29.2", "tclevel": 1}, {"label": "0.738050818_ShavingBeard", "tc": "00:11:32.56", "tclevel": 1}, {"label": "0.765797019_PlayingFlute", "tc": "00:11:40.24", "tclevel": 1}, {"label": "0.86112279_ShavingBeard", "tc": "00:11:47.8", "tclevel": 1}, {"label": "0.461219579_ApplyEyeMakeup", "tc": "00:11:50.56", "tclevel": 1}, {"label": "0.72806549_ApplyEyeMakeup", "tc": "00:11:53.6", "tclevel": 1}, {"label": "0.62259537_ApplyEyeMakeup", "tc": "00:11:55.12", "tclevel": 1}, {"label": "0.37944186_HeadMassage", "tc": "00:11:57.36", "tclevel": 1}, {"label": "0.456823051_ApplyEyeMakeup", "tc": "00:12:03.48", "tclevel": 1}, {"label": "0.888679445_ShavingBeard", "tc": "00:12:07.32", "tclevel": 1}, {"label": "0.831873894_ApplyEyeMakeup", "tc": "00:12:13.32", "tclevel": 1}, {"label": "0.856946111_Haircut", "tc": "00:12:17.44", "tclevel": 1}, {"label": "0.625099957_Haircut", "tc": "00:12:20.76", "tclevel": 1}, {"label": "0.42959285_BlowingCandles", "tc": "00:12:22.32", "tclevel": 1}, {"label": "0.423043877_ApplyEyeMakeup", "tc": "00:12:29.32", "tclevel": 1}, {"label": "0.44192362_BlowingCandles", "tc": "00:12:32.92", "tclevel": 1}, {"label": "0.4546642_BlowDryHair", "tc": "00:12:34.2", "tclevel": 1}, {"label": "0.94764763_Haircut", "tc": "00:12:36.56", "tclevel": 1}, {"label": "0.411110073_Haircut", "tc": "00:12:38.8", "tclevel": 1}, {"label": "0.771482885_Haircut", "tc": "00:12:39.76", "tclevel": 1}, {"label": "0.99423742_ApplyEyeMakeup", "tc": "00:12:40.92", "tclevel": 1}, {"label": "0.47683132_ApplyEyeMakeup", "tc": "00:12:42.48", "tclevel": 1}, {"label": "0.273165166_ApplyLipstick", "tc": "00:12:47.92", "tclevel": 1}, {"label": "0.681472123_ApplyEyeMakeup", "tc": "00:12:49.24", "tclevel": 1}, {"label": "0.41787907_Haircut", "tc": "00:12:49.88", "tclevel": 1}, {"label": "0.842079222_ApplyEyeMakeup", "tc": "00:12:50.76", "tclevel": 1}, {"label": "0.951354265_ApplyEyeMakeup", "tc": "00:12:51.84", "tclevel": 1}, {"label": "0.543497324_Swing", "tc": "00:12:53.96", "tclevel": 1}, {"label": "0.74814576_PlayingFlute", "tc": "00:13:14.52", "tclevel": 1}, {"label": "0.52928817_ApplyEyeMakeup", "tc": "00:13:23.44", "tclevel": 1}, {"label": "0.738313913_Haircut", "tc": "00:13:25.48", "tclevel": 1}, {"label": "0.76297492_ApplyEyeMakeup", "tc": "00:13:26.96", "tclevel": 1}, {"label": "0.862487853_Haircut", "tc": "00:13:29.56", "tclevel": 1}, {"label": "0.880458236_ApplyEyeMakeup", "tc": "00:13:31.24", "tclevel": 1}, {"label": "0.97465378_Haircut", "tc": "00:13:34.16", "tclevel": 1}, {"label": "0.583287597_MilitaryParade", "tc": "00:13:41.76", "tclevel": 1}, {"label": "0.84552896_ApplyEyeMakeup", "tc": "00:13:48.84", "tclevel": 1}, {"label": "0.99665326_ApplyEyeMakeup", "tc": "00:13:53.48", "tclevel": 1}, {"label": "0.81270683_CliffDiving", "tc": "00:14:00.24", "tclevel": 1}, {"label": "0.260414809_Drumming", "tc": "00:14:01.92", "tclevel": 1}, {"label": "0.987462223_Haircut", "tc": "00:14:16.16", "tclevel": 1}, {"label": "0.992794216_ApplyEyeMakeup", "tc": "00:14:18.08", "tclevel": 1}, {"label": "0.83859295_ApplyEyeMakeup", "tc": "00:14:20.84", "tclevel": 1}, {"label": "0.867488146_PlayingFlute", "tc": "00:14:23.36", "tclevel": 1}, {"label": "0.610618114_Haircut", "tc": "00:14:25.2", "tclevel": 1}, {"label": "0.519552052_PlayingFlute", "tc": "00:14:28.28", "tclevel": 1}, {"label": "0.775033295_Haircut", "tc": "00:14:29.6", "tclevel": 1}, {"label": "0.296382487_Drumming", "tc": "00:14:30.96", "tclevel": 1}, {"label": "0.490742832_Haircut", "tc": "00:14:43.64", "tclevel": 1}, {"label": "0.524380267_Haircut", "tc": "00:14:45.4", "tclevel": 1}, {"label": "0.62673044_ApplyLipstick", "tc": "00:14:46.12", "tclevel": 1}, {"label": "0.932755589_Haircut", "tc": "00:14:49.36", "tclevel": 1}, {"label": "0.870832086_PlayingSitar", "tc": "00:14:50.72", "tclevel": 1}, {"label": "0.613489151_Haircut", "tc": "00:14:52.04", "tclevel": 1}, {"label": "0.548064113_PlayingTabla", "tc": "00:14:53.04", "tclevel": 1}, {"label": "0.322106_PlayingPiano", "tc": "00:14:55.44", "tclevel": 1}, {"label": "0.90383166_ApplyLipstick", "tc": "00:14:59.12", "tclevel": 1}, {"label": "0.733528078_BlowingCandles", "tc": "00:15:01.44", "tclevel": 1}, {"label": "0.33517385_ShavingBeard", "tc": "00:15:05.52", "tclevel": 1}, {"label": "0.173808232_ApplyEyeMakeup", "tc": "00:15:08.84", "tclevel": 1}, {"label": "0.455889672_BlowDryHair", "tc": "00:15:10.52", "tclevel": 1}, {"label": "0.553549767_ApplyEyeMakeup", "tc": "00:15:12.12", "tclevel": 1}, {"label": "0.14140886_PlayingTabla", "tc": "00:15:12.8", "tclevel": 1}, {"label": "0.79852676_ApplyEyeMakeup", "tc": "00:15:33.84", "tclevel": 1}, {"label": "0.420101851_Haircut", "tc": "00:15:39.52", "tclevel": 1}, {"label": "0.44476473_Haircut", "tc": "00:15:40.28", "tclevel": 1}, {"label": "0.834654212_YoYo", "tc": "00:15:40.8", "tclevel": 1}, {"label": "0.50667512_PlayingTabla", "tc": "00:15:42.36", "tclevel": 1}, {"label": "0.414721936_BlowDryHair", "tc": "00:15:46.8", "tclevel": 1}, {"label": "0.242955014_BlowDryHair", "tc": "00:15:47.64", "tclevel": 1}, {"label": "0.654150426_YoYo", "tc": "00:15:48.04", "tclevel": 1}, {"label": "0.568469465_ApplyEyeMakeup", "tc": "00:15:50.04", "tclevel": 1}, {"label": "0.592663467_Haircut", "tc": "00:15:52.04", "tclevel": 1}, {"label": "0.244964287_PlayingViolin", "tc": "00:16:07.44", "tclevel": 1}, {"label": "0.938115597_ApplyEyeMakeup", "tc": "00:16:18.24", "tclevel": 1}, {"label": "0.94503605_Haircut", "tc": "00:16:23.52", "tclevel": 1}, {"label": "0.996626854_ApplyEyeMakeup", "tc": "00:16:28.6", "tclevel": 1}, {"label": "0.95435894_YoYo", "tc": "00:16:36.04", "tclevel": 1}, {"label": "0.9467299_YoYo", "tc": "00:16:41.92", "tclevel": 1}, {"label": "0.952741742_YoYo", "tc": "00:16:42.96", "tclevel": 1}, {"label": "0.206328154_PlayingViolin", "tc": "00:16:48.16", "tclevel": 1}, {"label": "0.34592062_Haircut", "tc": "00:16:57.52", "tclevel": 1}, {"label": "0.35696185_PlayingFlute", "tc": "00:16:59.96", "tclevel": 1}, {"label": "0.951261044_PlayingFlute", "tc": "00:17:00.76", "tclevel": 1}, {"label": "0.949400544_PlayingFlute", "tc": "00:17:06.04", "tclevel": 1}, {"label": "0.692477763_PlayingFlute", "tc": "00:17:07.44", "tclevel": 1}, {"label": "0.288658708_ApplyEyeMakeup", "tc": "00:17:12.48", "tclevel": 1}, {"label": "0.863794923_PlayingFlute", "tc": "00:17:14.16", "tclevel": 1}, {"label": "0.490111023_PlayingFlute", "tc": "00:17:17.04", "tclevel": 1}, {"label": "0.874648094_YoYo", "tc": "00:17:21.52", "tclevel": 1}, {"label": "0.803084612_Haircut", "tc": "00:17:24.44", "tclevel": 1}, {"label": "0.414071649_ApplyEyeMakeup", "tc": "00:17:25.4", "tclevel": 1}, {"label": "0.59210318_YoYo", "tc": "00:17:27.12", "tclevel": 1}, {"label": "0.32777223_PlayingCello", "tc": "00:17:40.36", "tclevel": 1}, {"label": "0.809313118_PizzaTossing", "tc": "00:17:42.28", "tclevel": 1}, {"label": "0.907678843_BlowDryHair", "tc": "00:17:52.6", "tclevel": 1}, {"label": "0.44100675_PlayingFlute", "tc": "00:17:55.84", "tclevel": 1}, {"label": "0.44522783_ApplyEyeMakeup", "tc": "00:17:56.68", "tclevel": 1}, {"label": "0.410210192_Haircut", "tc": "00:17:57.64", "tclevel": 1}, {"label": "0.805892527_ApplyEyeMakeup", "tc": "00:17:59.52", "tclevel": 1}, {"label": "0.66050184_ApplyEyeMakeup", "tc": "00:18:01.36", "tclevel": 1}, {"label": "0.90867531_ApplyEyeMakeup", "tc": "00:18:02.8", "tclevel": 1}, {"label": "0.786707282_ApplyEyeMakeup", "tc": "00:18:03.88", "tclevel": 1}, {"label": "0.86760813_ApplyEyeMakeup", "tc": "00:18:06.56", "tclevel": 1}, {"label": "0.40152428_BlowingCandles", "tc": "00:18:08.4", "tclevel": 1}, {"label": "0.761695087_PlayingFlute", "tc": "00:18:24.48", "tclevel": 1}, {"label": "0.97203505_ApplyEyeMakeup", "tc": "00:18:28.36", "tclevel": 1}, {"label": "0.66003716_ApplyEyeMakeup", "tc": "00:18:33.36", "tclevel": 1}, {"label": "0.695051491_ApplyEyeMakeup", "tc": "00:18:33.96", "tclevel": 1}, {"label": "0.97864759_ApplyEyeMakeup", "tc": "00:18:35.6", "tclevel": 1}, {"label": "0.99816042_StillRings", "tc": "00:18:40.2", "tclevel": 1}, {"label": "0.950288713_StillRings", "tc": "00:18:43.12", "tclevel": 1}, {"label": "0.999568403_StillRings", "tc": "00:18:53.68", "tclevel": 1}, {"label": "0.535769761_StillRings", "tc": "00:18:55.56", "tclevel": 1}, {"label": "0.848576903_PlayingFlute", "tc": "00:19:02.8", "tclevel": 1}, {"label": "0.39656806_PlayingFlute", "tc": "00:19:08.08", "tclevel": 1}, {"label": "0.862790406_ApplyEyeMakeup", "tc": "00:19:10.32", "tclevel": 1}, {"label": "0.401515126_YoYo", "tc": "00:19:12.96", "tclevel": 1}, {"label": "0.247822136_ApplyEyeMakeup", "tc": "00:19:19.84", "tclevel": 1}, {"label": "0.44950622_BlowingCandles", "tc": "00:19:19.96", "tclevel": 1}, {"label": "0.346229643_PlayingFlute", "tc": "00:19:20.72", "tclevel": 1}, {"label": "0.898897529_PlayingFlute", "tc": "00:19:26.68", "tclevel": 1}, {"label": "0.5576219_Haircut", "tc": "00:19:28.6", "tclevel": 1}, {"label": "0.366116047_PlayingTabla", "tc": "00:19:32.76", "tclevel": 1}, {"label": "0.540997922_YoYo", "tc": "00:19:34.16", "tclevel": 1}, {"label": "0.941937387_ApplyEyeMakeup", "tc": "00:19:37.24", "tclevel": 1}, {"label": "0.54102963_PlayingFlute", "tc": "00:19:38.24", "tclevel": 1}, {"label": "0.901041806_PlayingFlute", "tc": "00:19:38.56", "tclevel": 1}, {"label": "0.979322374_PlayingFlute", "tc": "00:19:40.52", "tclevel": 1}, {"label": "0.360232741_BlowDryHair", "tc": "00:19:43.12", "tclevel": 1}, {"label": "0.991608143_ApplyEyeMakeup", "tc": "00:19:45.32", "tclevel": 1}, {"label": "0.24170692_PlayingPiano", "tc": "00:19:46.48", "tclevel": 1}, {"label": "0.605023444_PlayingFlute", "tc": "00:19:47.56", "tclevel": 1}, {"label": "0.662578642_PlayingFlute", "tc": "00:19:48.64", "tclevel": 1}, {"label": "0.843887866_ApplyLipstick", "tc": "00:19:50.68", "tclevel": 1}, {"label": "0.41402277_PlayingPiano", "tc": "00:19:53.16", "tclevel": 1}, {"label": "0.900768161_ApplyLipstick", "tc": "00:19:57.32", "tclevel": 1}, {"label": "0.58290714_PlayingPiano", "tc": "00:19:58.76", "tclevel": 1}, {"label": "0.94335151_ApplyEyeMakeup", "tc": "00:20:00.76", "tclevel": 1}, {"label": "0.565602064_ApplyLipstick", "tc": "00:20:02.44", "tclevel": 1}, {"label": "0.67377949_ApplyEyeMakeup", "tc": "00:20:04.48", "tclevel": 1}, {"label": "0.6412732_ApplyLipstick", "tc": "00:20:06.72", "tclevel": 1}, {"label": "0.511786044_ApplyEyeMakeup", "tc": "00:20:12.0", "tclevel": 1}, {"label": "0.81725991_ApplyEyeMakeup", "tc": "00:20:13.96", "tclevel": 1}, {"label": "0.422552466_JugglingBalls", "tc": "00:20:15.32", "tclevel": 1}, {"label": "0.452193916_ApplyLipstick", "tc": "00:20:17.16", "tclevel": 1}, {"label": "0.972226679_ApplyEyeMakeup", "tc": "00:20:18.24", "tclevel": 1}, {"label": "0.411447525_JugglingBalls", "tc": "00:20:23.52", "tclevel": 1}, {"label": "0.555330694_Drumming", "tc": "00:20:24.52", "tclevel": 1}, {"label": "0.628085971_PlayingFlute", "tc": "00:20:26.8", "tclevel": 1}, {"label": "0.26750502_PlayingFlute", "tc": "00:20:28.52", "tclevel": 1}, {"label": "0.627902269_ApplyLipstick", "tc": "00:20:30.08", "tclevel": 1}, {"label": "0.703667521_PlayingFlute", "tc": "00:20:32.84", "tclevel": 1}, {"label": "0.23892987_BlowDryHair", "tc": "00:20:34.4", "tclevel": 1}, {"label": "0.99102861_ApplyEyeMakeup", "tc": "00:20:41.52", "tclevel": 1}, {"label": "0.407810092_ApplyEyeMakeup", "tc": "00:20:43.92", "tclevel": 1}, {"label": "0.853652477_PlayingCello", "tc": "00:20:47.04", "tclevel": 1}, {"label": "0.42472497_PlayingFlute", "tc": "00:20:49.32", "tclevel": 1}, {"label": "0.84885508_ApplyEyeMakeup", "tc": "00:20:51.16", "tclevel": 1}, {"label": "0.56376851_PlayingFlute", "tc": "00:20:53.16", "tclevel": 1}, {"label": "0.65458435_ApplyEyeMakeup", "tc": "00:20:55.44", "tclevel": 1}, {"label": "0.8811816_ApplyEyeMakeup", "tc": "00:20:58.8", "tclevel": 1}, {"label": "0.894868672_ApplyEyeMakeup", "tc": "00:21:02.84", "tclevel": 1}, {"label": "0.512159526_ApplyEyeMakeup", "tc": "00:21:04.88", "tclevel": 1}, {"label": "0.40043786_PlayingTabla", "tc": "00:21:08.24", "tclevel": 1}, {"label": "0.54458433_YoYo", "tc": "00:21:11.32", "tclevel": 1}, {"label": "0.723516762_ApplyEyeMakeup", "tc": "00:21:15.84", "tclevel": 1}, {"label": "0.4537994_Haircut", "tc": "00:21:16.92", "tclevel": 1}, {"label": "0.472694784_ApplyLipstick", "tc": "00:21:18.04", "tclevel": 1}, {"label": "0.877042592_ApplyEyeMakeup", "tc": "00:21:19.16", "tclevel": 1}, {"label": "0.424379647_PlayingGuitar", "tc": "00:21:20.16", "tclevel": 1}, {"label": "0.789070368_ApplyLipstick", "tc": "00:21:23.04", "tclevel": 1}, {"label": "0.985068142_ApplyEyeMakeup", "tc": "00:21:28.52", "tclevel": 1}, {"label": "0.399948806_YoYo", "tc": "00:21:31.04", "tclevel": 1}, {"label": "0.9865188_ApplyEyeMakeup", "tc": "00:21:34.6", "tclevel": 1}, {"label": "0.660421014_Haircut", "tc": "00:21:36.32", "tclevel": 1}, {"label": "0.554808915_ApplyEyeMakeup", "tc": "00:21:37.92", "tclevel": 1}, {"label": "0.492400974_ApplyEyeMakeup", "tc": "00:21:41.76", "tclevel": 1}, {"label": "0.864292264_ApplyEyeMakeup", "tc": "00:21:44.44", "tclevel": 1}, {"label": "0.842043459_ApplyLipstick", "tc": "00:21:45.72", "tclevel": 1}, {"label": "0.858558953_ApplyEyeMakeup", "tc": "00:21:48.24", "tclevel": 1}, {"label": "0.797745943_ShavingBeard", "tc": "00:21:50.56", "tclevel": 1}, {"label": "0.99409497_ApplyEyeMakeup", "tc": "00:21:52.08", "tclevel": 1}, {"label": "0.96486634_ShavingBeard", "tc": "00:21:52.96", "tclevel": 1}, {"label": "0.995588779_ApplyEyeMakeup", "tc": "00:21:56.72", "tclevel": 1}, {"label": "0.340584785_PlayingFlute", "tc": "00:21:59.72", "tclevel": 1}, {"label": "0.959496558_PlayingFlute", "tc": "00:22:02.68", "tclevel": 1}, {"label": "0.45480445_PlayingTabla", "tc": "00:22:05.24", "tclevel": 1}, {"label": "0.999962807_ApplyEyeMakeup", "tc": "00:22:10.0", "tclevel": 1}, {"label": "0.412103862_ApplyEyeMakeup", "tc": "00:22:14.88", "tclevel": 1}, {"label": "0.996093452_ApplyEyeMakeup", "tc": "00:22:23.88", "tclevel": 1}, {"label": "0.961300731_ApplyEyeMakeup", "tc": "00:22:24.84", "tclevel": 1}, {"label": "0.971228004_ApplyEyeMakeup", "tc": "00:22:25.48", "tclevel": 1}, {"label": "0.420173228_ApplyEyeMakeup", "tc": "00:22:28.12", "tclevel": 1}, {"label": "0.538541317_ApplyLipstick", "tc": "00:22:29.64", "tclevel": 1}, {"label": "0.91263193_ApplyEyeMakeup", "tc": "00:22:32.2", "tclevel": 1}, {"label": "0.998431742_ApplyEyeMakeup", "tc": "00:22:33.64", "tclevel": 1}, {"label": "0.677457154_Haircut", "tc": "00:22:35.32", "tclevel": 1}, {"label": "0.83697027_Drumming", "tc": "00:22:37.08", "tclevel": 1}, {"label": "0.610138178_PlayingFlute", "tc": "00:22:41.04", "tclevel": 1}, {"label": "0.788622916_Drumming", "tc": "00:22:41.88", "tclevel": 1}, {"label": "0.680268705_Haircut", "tc": "00:22:53.6", "tclevel": 1}, {"label": "0.975164533_Drumming", "tc": "00:22:54.12", "tclevel": 1}, {"label": "0.872702181_ApplyEyeMakeup", "tc": "00:23:03.0", "tclevel": 1}, {"label": "0.36717048_ApplyEyeMakeup", "tc": "00:23:03.96", "tclevel": 1}, {"label": "0.444839865_BlowingCandles", "tc": "00:23:04.4", "tclevel": 1}, {"label": "0.767727554_PlayingFlute", "tc": "00:23:07.6", "tclevel": 1}, {"label": "0.463047266_YoYo", "tc": "00:23:11.64", "tclevel": 1}, {"label": "0.973118365_PlayingFlute", "tc": "00:23:20.52", "tclevel": 1}, {"label": "0.440991163_PlayingSitar", "tc": "00:23:25.2", "tclevel": 1}, {"label": "0.406740218_PlayingViolin", "tc": "00:23:27.4", "tclevel": 1}, {"label": "0.35371381_Haircut", "tc": "00:23:31.0", "tclevel": 1}, {"label": "0.46655881_RockClimbingIndoor", "tc": "00:23:33.04", "tclevel": 1}, {"label": "0.822731316_PlayingFlute", "tc": "00:23:37.12", "tclevel": 1}, {"label": "0.4282552_ApplyEyeMakeup", "tc": "00:23:41.76", "tclevel": 1}, {"label": "0.77703017_ApplyEyeMakeup", "tc": "00:23:43.16", "tclevel": 1}, {"label": "0.758837759_ApplyEyeMakeup", "tc": "00:23:45.04", "tclevel": 1}, {"label": "0.975765049_Haircut", "tc": "00:23:45.72", "tclevel": 1}, {"label": "0.52292705_ApplyEyeMakeup", "tc": "00:23:46.56", "tclevel": 1}, {"label": "0.958879232_PlayingFlute", "tc": "00:23:48.76", "tclevel": 1}, {"label": "0.55647475_PlayingFlute", "tc": "00:23:51.2", "tclevel": 1}, {"label": "0.44976294_ApplyLipstick", "tc": "00:23:58.68", "tclevel": 1}, {"label": "0.953344285_ApplyEyeMakeup", "tc": "00:24:03.92", "tclevel": 1}, {"label": "0.44270495_ApplyEyeMakeup", "tc": "00:24:05.56", "tclevel": 1}, {"label": "0.725320458_ApplyEyeMakeup", "tc": "00:24:08.0", "tclevel": 1}, {"label": "0.558466971_PlayingPiano", "tc": "00:24:09.24", "tclevel": 1}, {"label": "0.659330368_Haircut", "tc": "00:24:10.16", "tclevel": 1}, {"label": "0.96108156_Drumming", "tc": "00:24:12.52", "tclevel": 1}, {"label": "0.818049669_PlayingFlute", "tc": "00:24:29.32", "tclevel": 1}, {"label": "0.345764577_PlayingFlute", "tc": "00:24:30.32", "tclevel": 1}, {"label": "0.52318597_BlowingCandles", "tc": "00:24:32.24", "tclevel": 1}, {"label": "0.264862329_Drumming", "tc": "00:24:33.52", "tclevel": 1}, {"label": "0.79213578_PlayingFlute", "tc": "00:24:51.64", "tclevel": 1}, {"label": "0.503022671_ApplyEyeMakeup", "tc": "00:24:52.28", "tclevel": 1}, {"label": "0.78217113_BlowingCandles", "tc": "00:24:56.04", "tclevel": 1}, {"label": "0.359473646_YoYo", "tc": "00:24:59.12", "tclevel": 1}, {"label": "0.3225781_ApplyLipstick", "tc": "00:25:04.44", "tclevel": 1}, {"label": "0.31095311_YoYo", "tc": "00:25:04.64", "tclevel": 1}, {"label": "0.696599305_ApplyLipstick", "tc": "00:25:05.76", "tclevel": 1}, {"label": "0.40908229_PlayingFlute", "tc": "00:25:07.04", "tclevel": 1}, {"label": "0.405791044_PlayingFlute", "tc": "00:25:13.8", "tclevel": 1}, {"label": "0.43520889_Kayaking", "tc": "00:25:16.68", "tclevel": 1}, {"label": "0.510118842_PlayingViolin", "tc": "00:25:17.88", "tclevel": 1}, {"label": "0.960349441_ApplyEyeMakeup", "tc": "00:25:27.12", "tclevel": 1}, {"label": "0.835019708_ApplyLipstick", "tc": "00:25:28.2", "tclevel": 1}, {"label": "0.94633269_ApplyEyeMakeup", "tc": "00:25:29.36", "tclevel": 1}, {"label": "0.743405342_YoYo", "tc": "00:25:31.24", "tclevel": 1}, {"label": "0.481639534_ApplyEyeMakeup", "tc": "00:25:38.28", "tclevel": 1}, {"label": "0.81776011_Haircut", "tc": "00:25:41.44", "tclevel": 1}, {"label": "0.984146297_Haircut", "tc": "00:25:47.12", "tclevel": 1}, {"label": "0.464545786_PlayingFlute", "tc": "00:25:49.12", "tclevel": 1}, {"label": "0.80369335_Haircut", "tc": "00:25:51.96", "tclevel": 1}, {"label": "0.447313696_ApplyEyeMakeup", "tc": "00:25:53.32", "tclevel": 1}, {"label": "0.23189855_Haircut", "tc": "00:25:53.88", "tclevel": 1}, {"label": "0.534798503_Haircut", "tc": "00:25:54.72", "tclevel": 1}, {"label": "0.40462297_ShavingBeard", "tc": "00:25:56.56", "tclevel": 1}, {"label": "0.86959815_Haircut", "tc": "00:25:57.92", "tclevel": 1}, {"label": "0.505283892_Haircut", "tc": "00:26:00.4", "tclevel": 1}, {"label": "0.315033019_YoYo", "tc": "00:26:02.08", "tclevel": 1}, {"label": "0.733801782_BlowingCandles", "tc": "00:26:12.76", "tclevel": 1}, {"label": "0.95677215_ApplyEyeMakeup", "tc": "00:26:19.04", "tclevel": 1}, {"label": "0.504800141_ApplyLipstick", "tc": "00:26:20.92", "tclevel": 1}, {"label": "0.997952044_ApplyEyeMakeup", "tc": "00:26:22.04", "tclevel": 1}, {"label": "0.884982765_StillRings", "tc": "00:26:23.24", "tclevel": 1}, {"label": "0.731743932_Haircut", "tc": "00:26:41.96", "tclevel": 1}, {"label": "0.67785275_Haircut", "tc": "00:26:44.4", "tclevel": 1}, {"label": "0.194619745_PlayingFlute", "tc": "00:26:46.6", "tclevel": 1}, {"label": "0.543883562_PlayingFlute", "tc": "00:27:13.12", "tclevel": 1}, {"label": "0.55113256_RockClimbingIndoor", "tc": "00:27:19.28", "tclevel": 1}, {"label": "0.947001576_BandMarching", "tc": "00:27:19.96", "tclevel": 1}, {"label": "0.703587_Typing", "tc": "00:27:34.68", "tclevel": 1}, {"label": "0.60126251_ApplyLipstick", "tc": "00:27:38.08", "tclevel": 1}, {"label": "0.24264361_StillRings", "tc": "00:27:43.32", "tclevel": 1}, {"label": "0.459924787_Drumming", "tc": "00:27:47.04", "tclevel": 1}, {"label": "0.810821593_BlowingCandles", "tc": "00:27:59.6", "tclevel": 1}, {"label": "0.9062081_PlayingFlute", "tc": "00:28:01.2", "tclevel": 1}, {"label": "0.608170331_PlayingFlute", "tc": "00:28:03.76", "tclevel": 1}, {"label": "0.815855563_PlayingFlute", "tc": "00:28:10.28", "tclevel": 1}, {"label": "0.615614533_Haircut", "tc": "00:28:12.6", "tclevel": 1}, {"label": "0.427106082_PlayingFlute", "tc": "00:28:14.8", "tclevel": 1}, {"label": "0.732181251_Haircut", "tc": "00:28:16.56", "tclevel": 1}, {"label": "0.928964734_PlayingFlute", "tc": "00:28:18.52", "tclevel": 1}, {"label": "0.835101247_CliffDiving", "tc": "00:28:20.2", "tclevel": 1}, {"label": "0.358820528_PlayingFlute", "tc": "00:28:23.68", "tclevel": 1}, {"label": "0.62442106_PlayingFlute", "tc": "00:28:24.64", "tclevel": 1}]}, "type": "keyframes", "tcin": "00:00:00.0000", "tcout": "00:00:15.0000", "tclevel": 0}], "id": "c3d", "type": "events", "algorithm": "demo-video-generator", "processor": "", "processed": 1421141589291, "version": 1}